Workbook
Name ADDS_AUS: 0.4937
Name ADDS_MTL: 0.39
Name ADDS_SIN: 0.5834
Name ADDS_STG: 0.42
Name BE006K: 700
Name BE010K: 600
Name BT074K: 100
Name BT369K: 100
Name COUNTER: 6
Name CTL.ORDERINGSTATE: 0
Name EXCH_AUD: 1.446
Name EXCH_CAD: 1.3167
Name EXCH_CLP: 626.8
Name EXCH_SGD: 1.7069
Name IN: '[23]Instru Correa'!$AH$9
Name INDIMES: {#N/A,#N/A,FALSE,"Costos_Elem_Hid";#N/A,#N/A,FALSE,"Costos_Elem_Hid";#N/A,#N/A,FALSE,"Costos_Elem_Hid"}
Name initialWorkingCapital: 0
Name IPC_E: [24]Inversiones!$D$718
Name IPC_N: [24]Inversiones!$D$717
Name lbsPerTon: 2204.6
Name Materiales_2004_Consulta: [25]Materiales_2004_Consulta!$A$3:$Q$203
Name MB_24A25: (108.2/103.15)
Name MESES_05: '[26]CTOS. ORIG.'!$C$5:$N$5
Name MESES_06: '[26]CTOS. ORIG.'!$O$5:$Z$5
Name MESESGANTT: [26]Gantt!$F$55:$U$55
Name modelStartDate: 33604
Name no: 0
Name Numero_Unidades_Funcionales: [27]Constantes!$C$54
Name oreProductionDaily: 26640
Name Plazo_Obra: [27]Constantes!$C$58
Name Plus_No_Remunerativo: [28]Constantes!$C$45
Name preProductionDurationMonths: 2
Name PRODUCTIVIDAD: [29]DOTACION_CBV99!$A$67:$AA$135
Name RANTOT: [30]TABLAS!$R$105:$AE$200
Name riskATSToutputStatistic: 4
Name RiskAutoStopPercChange: 1.5
Name RiskExcelReportsToGenerate: 32
Name RiskReportGraphFormat: 0
Name RiskResultsUpdateFreq: 100
Name RiskStatFunctionsUpdateFreq: 1
Name RPTC: '[23]Instru Correa'!$AD$9
Name shiftPeriodConversion: 0.36
Name sí: 1
Name STOCK: '[23]Instru Correa'!$AE$9
Name taxRate: 0.5
Name TC: 920
Name TC_AUS: 650
Name TC_CAD: 693
Name TC_CAD: 693
Name TC_CAD: 693
Name TC_CAD: 681
Name TComp: '[35]Tabla Comparativa'!$B$2:$I$23
Name TopRankOnlyInputsChangeThreshold: 0.01
Name UF: 40000
Name ujuu: 1000
Name vvvvv: [38]TE2GEFUND_MES!$B$8:$E$154
Name wageEscalation: 0.02

Sheet R. Actividades
B1: Registro de actividades M24G005
B2: Etapa | C2: Actividad | D2: Comentario | E2: Proveedor | F2: Fecha Incio | G2: Fecha fin | H2: ESTATUS
B3: Monitoreo y búsqueda de nuevas oportunidades | C3: Participación congresos y otros (PDAC) | D3: PDAC: 3 internos 3 viajes | F3: 46082 | G3: 46082 | H3: Pendiente
B4: Monitoreo y búsqueda de nuevas oportunidades | C4: Terreno proyectos Canadá | D4: 25 días: JR-SC-AA + consultor (darren) 3 viajes | F4: 46174 | G4: 46174 | H4: Pendiente
B5: Monitoreo y búsqueda de nuevas oportunidades | C5: Evaluación oportunidades + firma NDA Canadá | D5: RRM proyecto corto | F5: 46266 | G5: 46266 | H5: Pendiente
B6: Monitoreo y búsqueda de nuevas oportunidades | C6: Evaluación oportunidades + firma NDA Australia | D6: RRM proyecto corto | F6: 46174 | G6: 46174 | H6: Pendiente
B7: Seguimiento proyecto 1 | C7: Terreno proyectos USA | F7: 46054 | G7: 46054 | H7: Pendiente
B8: Seguimiento proyecto 1 | C8: Análisis y recomendaciones proy. USA | F8: 46082 | G8: 46082 | H8: Pendiente

Sheet Form. Cochilco RealProyectado
B2: API M24G005 - FORMATO COCHILCO
B4: API | C4: NOMBRE | D4: 2024 | E4: 2025 | F4: 2026 | G4: 2027 | H4: 2028 | I4: TOTAL US$ | L4: M Nac | M4: M Ext
L5: 1.0336488 | M5: 1.0237726
B6: M24G005 | C6: Exploración Internacional Otros Países | D6: =SUM(D7) -> 228189.96 | E6: =SUM(E7) -> 476667.45 | F6: =SUM(F7) -> 1674600.4 | G6: =SUM(G7) -> 2034249.7 | H6: =SUM(H7) -> 2331209 | I6: =SUM(I7) -> 6744916.6
B7: M24G005-1.1 | C7: E. Internacional Otros Países | D7: =SUM(D8:D9) -> 228189.96 | E7: =SUM(E8:E9) -> 476667.45 | F7: =SUM(F8:F9) -> 1674600.4 | G7: =SUM(G8:G9) -> 2034249.7 | H7: =SUM(H8:H9) -> 2331209 | I7: =SUM(I8:I9) -> 6744916.6
B8: M24G005-1.1.1 | C8: Metalotectos de Interés Item I | D8: ='Formato SAP'!G6 -> 228189.96 | E8: ='Formato SAP'!I6 -> 127558.07 | F8: ='Formato SAP'!K6 -> 0 | G8: ='Formato SAP'!M6 -> 0 | H8: ='Formato SAP'!O6 -> 0 | I8: =SUM(D8:H8) -> 355748.03 | L8: =+#REF!*L5 -> #REF! | M8: =+(#REF!-#REF!)*M5 -> #REF! | N8: =+M8+L8 -> #REF!
B9: M24G005-1.1.2 | C9: Metalotectos de Interés Item II | D9: ='Formato SAP'!G22 -> 0 | E9: ='Formato SAP'!I22 -> 349109.38 | F9: ='Formato SAP'!K22 -> 1674600.4 | G9: ='Formato SAP'!M22 -> 2034249.7 | H9: ='Formato SAP'!O22 -> 2331209 | I9: =SUM(D9:H9) -> 6389168.5 | L9: =+#REF!*L6 -> #REF! | M9: =+(#REF!-#REF!)*M6 -> #REF! | N9: =+M9+L9 -> #REF!

Sheet formato sap original 
E2: 2024-2027 | F2: 2024-2027 | I2: 2024 | K2: 2025 | M2: 2026 | O2: 2027 | Q2: PLANIFICACION AÑO 2024 | AD2: PLANIFICACION AÑO 2025 | AQ2: PLANIFICACION AÑO 2026 | BD2: PLANIFICACION AÑO 2027
E3: TOTAL | F3: TOTAL | I3: TOTAL AÑO | K3: TOTAL AÑO | M3: TOTAL AÑO | O3: TOTAL AÑO | Q3: 45322 | R3: 45351 | S3: 45382 | T3: 45412 | U3: 45443 | V3: 45473 | W3: 45504 | X3: 45535 | Y3: 45565 | Z3: 45596 | AA3: 45626 | AB3: 45657 | AD3: 45688 | AE3: 45716 | AF3: 45747 | AG3: 45777 | AH3: 45808 | AI3: 45838 | AJ3: 45869 | AK3: 45900 | AL3: 45930 | AM3: 45961 | AN3: 45991 | AO3: 46022 | AQ3: 46053 | AR3: 46081 | AS3: 46112 | AT3: 46142 | AU3: 46173 | AV3: 46203 | AW3: 46234 | AX3: 46265 | AY3: 46295 | AZ3: 46326 | BA3: 46356 | BB3: 46387 | BD3: 46053 | BE3: 46081 | BF3: 46112 | BG3: 46142 | BH3: 46173 | BI3: 46203 | BJ3: 46234 | BK3: 46265 | BL3: 46295 | BM3: 46326 | BN3: 46356 | BO3: 46387
C4: Exploración Internacional Otros Países | E4: 6571392.7 | F4: =F5 -> 6567358 | G4: =G5 -> 6692580.5 | I4: 655490.84 | K4: 1998016.6 | M4: 1999923.5 | O4: 1917961.8 | Q4: 0 | R4: 0 | S4: 0 | T4: 0 | U4: 0 | V4: 0 | W4: 0 | X4: 230144.25 | Y4: 65585.624 | Z4: 254411.09 | AA4: 61027.5 | AB4: 44322.382 | AD4: 69996.621 | AE4: 36799.149 | AF4: 73509.501 | AG4: 144894.91 | AH4: 0 | AI4: 0 | AJ4: 0 | AK4: 0 | AL4: 0 | AM4: 0 | AN4: 0 | AO4: 0 | AQ4: 0 | AR4: 0 | AS4: 0 | AT4: 0 | AU4: 0 | AV4: 0 | AW4: 0 | AX4: 0 | AY4: 0 | AZ4: 0 | BA4: 0 | BB4: 0 | BD4: 0 | BE4: 0 | BF4: 0 | BG4: 0 | BH4: 0 | BI4: 0 | BJ4: 0 | BK4: 0 | BL4: 0 | BM4: 0 | BN4: 0 | BO4: 0
C5: E. Internacional Otros Países | E5: 6571392.7 | F5: =F6+F22 -> 6567358 | G5: =G6+G22 -> 6692580.5 | I5: 655490.84 | K5: 1998016.6 | M5: 1999923.5 | O5: 1917961.8 | Q5: 0 | R5: 0 | S5: 0 | T5: 0 | U5: 0 | V5: 0 | W5: 0 | X5: 230144.25 | Y5: 65585.624 | Z5: 254411.09 | AA5: 61027.5 | AB5: 44322.382 | AD5: 69996.621 | AE5: 36799.149 | AF5: 73509.501 | AG5: 144894.91 | AH5: 0 | AI5: 0 | AJ5: 0 | AK5: 0 | AL5: 0 | AM5: 0 | AN5: 0 | AO5: 0 | AQ5: 0 | AR5: 0 | AS5: 0 | AT5: 0 | AU5: 0 | AV5: 0 | AW5: 0 | AX5: 0 | AY5: 0 | AZ5: 0 | BA5: 0 | BB5: 0 | BD5: 0 | BE5: 0 | BF5: 0 | BG5: 0 | BH5: 0 | BI5: 0 | BJ5: 0 | BK5: 0 | BL5: 0 | BM5: 0 | BN5: 0 | BO5: 0
C6: Metalotectos de Interés Item I | E6: 861309.8 | F6: 367893.41 | G6: =SUM(G7:G21) -> 368944.88 | I6: 655490.84 | K6: 205818.96 | M6: 0 | O6: 0 | Q6: 0 | R6: 0 | S6: 0 | T6: 0 | U6: 0 | V6: 0 | W6: 0 | X6: 230144.25 | Y6: 65585.624 | Z6: 254411.09 | AA6: 61027.5 | AB6: 44322.382 | AD6: 36799.149 | AE6: 36799.149 | AF6: 36799.149 | AG6: 95421.518 | AH6: 0 | AI6: 0 | AJ6: 0 | AK6: 0 | AL6: 0 | AM6: 0 | AN6: 0 | AO6: 0 | AQ6: 0 | AR6: 0 | AS6: 0 | AT6: 0 | AU6: 0 | AV6: 0 | AW6: 0 | AX6: 0 | AY6: 0 | AZ6: 0 | BA6: 0 | BB6: 0 | BD6: 0 | BE6: 0 | BF6: 0 | BG6: 0 | BH6: 0 | BI6: 0 | BJ6: 0 | BK6: 0 | BL6: 0 | BM6: 0 | BN6: 0 | BO6: 0
C7: Geología MN | D7: 91243110 | E7: 311221.55 | F7: 260912.23 | G7: =F7*$E$51 -> 260155.53 | I7: 171711.94 | K7: 139509.62 | M7: 0 | O7: 0 | X7: 29286.014 | Y7: 16866.007 | Z7: 44758.215 | AA7: 38793.948 | AB7: 42007.754 | AD7: 34877.404 | AE7: 34877.404 | AF7: 34877.404 | AG7: 34877.404
C8: Geología ME | D8: 91243120 | E8: 181824 | F8: 71122.181 | G8: =F8*$F$51 -> 73083.421 | I8: 181824 | K8: 0 | M8: 0 | O8: 0 | X8: 67366 | Y8: 15546 | Z8: 88314.286 | AA8: 10597.714 | AB8: 0
C9: Geoquímica ME | D9: 91243220 | E9: 0 | F9: 0 | G9: =F9*$F$51 -> 0 | I9: 0 | K9: 0 | M9: 0 | O9: 0 | X9: 0 | Y9: 0 | Z9: 0 | AA9: 0 | AB9: 0
C10: Geofísica ME | D10: 91243310 | E10: 0 | F10: 0 | G10: =F10*$F$51 -> 0 | I10: 0 | K10: 0 | M10: 0 | O10: 0 | X10: 0 | Y10: 0 | Z10: 0 | AA10: 0 | AB10: 0
C11: Sondajes ME | D11: 91243510 | E11: 0 | F11: 0 | G11: =F11*$F$51 -> 0 | I11: 0 | K11: 0 | M11: 0 | O11: 0 | X11: 0 | Y11: 0 | Z11: 0 | AA11: 0 | AB11: 0
C12: Logística MN | D12: 91243520 | E12: 144957.87 | F12: 20598.61 | G12: =F12*$E$51 -> 20538.87 | I12: 144957.87 | K12: 0 | M12: 0 | O12: 0 | X12: 71228.697 | Y12: 325.08514 | Z12: 68390.392 | AA12: 5013.6988 | AB12: 0
C13: Logística ME | D13: 91243530 | E13: 137937.38 | F13: -1610.0539 | G13: =F13*$F$51 -> -1654.4522 | I13: 137937.38 | K13: 0 | M13: 0 | O13: 0 | X13: 56674.054 | Y13: 30770.7 | Z13: 46479.522 | AA13: 4013.1024 | AB13: 0
C14: Propiedad Minera ME | D14: 91243610 | E14: 0 | F14: 0 | G14: =F14*$F$51 -> 0 | I14: 0 | K14: 0 | M14: 0 | O14: 0 | X14: 0 | Y14: 0 | Z14: 0 | AA14: 0 | AB14: 0
C15: Medio Ambiente MN | D15: 91243620 | E15: 0 | F15: 0 | G15: =F15*$E$51 -> 0 | I15: 0 | K15: 0 | M15: 0 | O15: 0 | X15: 0 | Y15: 0 | Z15: 0 | AA15: 0 | AB15: 0
C16: Medio Ambiente ME | D16: 91243630 | E16: 0 | F16: 0 | G16: =F16*$F$51 -> 0 | I16: 0 | K16: 0 | M16: 0 | O16: 0 | X16: 0 | Y16: 0 | Z16: 0 | AA16: 0 | AB16: 0
C17: Seguridad ME | D17: 91243640 | E17: 0 | F17: 0 | G17: =F17*$F$51 -> 0 | I17: 0 | K17: 0 | M17: 0 | O17: 0 | X17: 0 | Y17: 0 | Z17: 0 | AA17: 0 | AB17: 0
C18: Comunidades ME | D18: 91243650 | E18: 0 | F18: 0 | G18: =F18*$F$51 -> 0 | I18: 0 | K18: 0 | M18: 0 | O18: 0 | X18: 0 | Y18: 0 | Z18: 0 | AA18: 0 | AB18: 0
C19: Administración MN | D19: 91243660 | E19: 0 | F19: 3012.3191 | G19: =F19*$E$51 -> 3003.5827 | I19: 0 | K19: 0 | M19: 0 | O19: 0 | X19: 0 | Y19: 0 | Z19: 0 | AA19: 0 | AB19: 0
C20: Contingencia ME | D20: 91243750 | E20: 58622.369 | F20: 0 | G20: =F20*$F$51 -> 0 | I20: 0 | K20: 58622.369 | M20: 0 | O20: 0 | X20: 0 | Y20: 0 | Z20: 0 | AA20: 0 | AB20: 0 | AG20: 58622.369
C21: Fee MN | D21: 91243910 | E21: 26746.631 | F21: 13858.122 | G21: =F21*$E$51 -> 13817.931 | I21: 19059.651 | K21: 7686.9798 | M21: 0 | O21: 0 | X21: 5589.4831 | Y21: 2077.8328 | Z21: 6468.6709 | AA21: 2609.0371 | AB21: 2314.6273 | AD21: 1921.745 | AE21: 1921.745 | AF21: 1921.745 | AG21: 1921.745
C22: Metalotectos de Interés Item II | E22: 5710082.9 | F22: =SUM(F23:F37) -> 6199464.6 | G22: =SUM(G23:G37) -> 6323635.6 | I22: 0 | K22: 1792197.7 | M22: 1999923.5 | O22: 1917961.8 | Q22: 0 | R22: 0 | S22: 0 | T22: 0 | U22: 0 | V22: 0 | W22: 0 | X22: 0 | Y22: 0 | Z22: 0 | AA22: 0 | AB22: 0 | AD22: 33197.472 | AE22: 0 | AF22: 36710.352 | AG22: 49473.394 | AH22: 282718.02 | AI22: 819846.4 | AJ22: 214169.88 | AK22: 109794.44 | AL22: 65622.678 | AM22: 99543.501 | AN22: 36799.149 | AO22: 44322.382 | AQ22: 13718.836 | AR22: 13718.836 | AS22: 373078.04 | AT22: 665606.68 | AU22: 331598.57 | AV22: 321344.39 | AW22: 17340.332 | AX22: 17340.332 | AY22: 37223.509 | AZ22: 13718.836 | BA22: 13718.836 | BB22: 181516.3 | BD22: 1530718.8 | BE22: 139236.08 | BF22: 221199.63 | BG22: 26807.203 | BH22: 0 | BI22: 0 | BJ22: 0 | BK22: 0 | BL22: 0 | BM22: 0 | BN22: 0 | BO22: 0
C23: Geología MN | D23: 91243110 | E23: 489204.74 | F23: 1204379.7 | G23: =F23*$E$51 -> 1200886.7 | I23: 0 | K23: 294588.11 | M23: 156028.85 | O23: 38587.779 | AG23: 1194.5701 | AH23: 34955.082 | AI23: 27329.242 | AJ23: 49591.849 | AK23: 34877.404 | AL23: 34877.404 | AM23: 34877.404 | AN23: 34877.404 | AO23: 42007.754 | AQ23: 13002.404 | AR23: 13002.404 | AS23: 13002.404 | AT23: 13002.404 | AU23: 13002.404 | AV23: 13002.404 | AW23: 13002.404 | AX23: 13002.404 | AY23: 13002.404 | AZ23: 13002.404 | BA23: 13002.404 | BB23: 13002.404 | BD23: 13002.404 | BE23: 13002.404 | BF23: 12582.971 | BG23: 0
C24: Geología ME | D24: 91243120 | E24: 233024 | F24: 1301131.7 | G24: =F24*$F$51 -> 1337011.2 | I24: 0 | K24: 233024 | M24: 0 | O24: 0 | AD24: 0 | AE24: 0 | AF24: 0 | AG24: 6769.2308 | AH24: 93742.769 | AI24: 54128 | AJ24: 78384 | AK24: 0 | AL24: 0 | AM24: 0 | AN24: 0 | AO24: 0 | AQ24: 0 | AR24: 0 | AS24: 0 | AT24: 0 | AU24: 0 | AV24: 0 | AW24: 0 | AX24: 0 | AY24: 0 | AZ24: 0 | BA24: 0 | BB24: 0 | BD24: 0 | BE24: 0 | BF24: 0 | BG24: 0
C25: Geoquímica ME | D25: 91243220 | E25: 0 | F25: 0 | G25: =F25*$F$51 -> 0 | I25: 0 | K25: 0 | M25: 0 | O25: 0 | AD25: 0 | AE25: 0 | AF25: 0 | AG25: 0 | AH25: 0 | AI25: 0 | AJ25: 0 | AK25: 0 | AL25: 0 | AM25: 0 | AN25: 0 | AO25: 0 | AQ25: 0 | AR25: 0 | AS25: 0 | AT25: 0 | AU25: 0 | AV25: 0 | AW25: 0 | AX25: 0 | AY25: 0 | AZ25: 0 | BA25: 0 | BB25: 0 | BD25: 0 | BE25: 0 | BF25: 0 | BG25: 0
C26: Geofísica ME | D26: 91243310 | E26: 1650000 | F26: 1657397.3 | G26: =F26*$F$51 -> 1703101.1 | I26: 0 | K26: 0 | M26: 1050000 | O26: 600000 | AD26: 0 | AE26: 0 | AF26: 0 | AG26: 0 | AH26: 0 | AI26: 0 | AJ26: 0 | AK26: 0 | AL26: 0 | AM26: 0 | AN26: 0 | AO26: 0 | AQ26: 0 | AR26: 0 | AS26: 0 | AT26: 296703.3 | AU26: 306593.41 | AV26: 296703.3 | AW26: 0 | AX26: 0 | AY26: 0 | AZ26: 0 | BA26: 0 | BB26: 150000 | BD26: 600000 | BE26: 0 | BF26: 0 | BG26: 0
C27: Sondajes ME | D27: 91243510 | E27: 880000 | F27: 884062.6 | G27: =F27*$F$51 -> 908441.2 | I27: 0 | K27: 0 | M27: 0 | O27: 880000 | AD27: 0 | AE27: 0 | AF27: 0 | AG27: 0 | AH27: 0 | AI27: 0 | AJ27: 0 | AK27: 0 | AL27: 0 | AM27: 0 | AN27: 0 | AO27: 0 | AQ27: 0 | AR27: 0 | AS27: 0 | AT27: 0 | AU27: 0 | AV27: 0 | AW27: 0 | AX27: 0 | AY27: 0 | AZ27: 0 | BA27: 0 | BB27: 0 | BD27: 880000 | BE27: 0 | BF27: 0 | BG27: 0
C28: Logística MN | D28: 91243520 | E28: 260785.11 | F28: 226848.59 | G28: =F28*$E$51 -> 226190.68 | I28: 0 | K28: 260785.11 | M28: 0 | O28: 0 | AD28: 33197.472 | AE28: 0 | AF28: 36710.352 | AG28: 0 | AH28: 45704.485 | AI28: 10259.199 | AJ28: 30777.597 | AK28: 52068 | AL28: 0 | AM28: 52068 | AN28: 0 | AO28: 0 | AQ28: 0 | AR28: 0 | AS28: 0 | AT28: 0 | AU28: 0 | AV28: 0 | AW28: 0 | AX28: 0 | AY28: 0 | AZ28: 0 | BA28: 0 | BB28: 0 | BD28: 0 | BE28: 0 | BF28: 0 | BG28: 0
C29: Logística ME | D29: 91243530 | E29: 170117.15 | F29: 200867.5 | G29: =F29*$F$51 -> 206406.55 | I29: 0 | K29: 170117.15 | M29: 0 | O29: 0 | AD29: 0 | AE29: 0 | AF29: 0 | AG29: 0 | AH29: 91645.702 | AI29: 15991.897 | AJ29: 39993.563 | AK29: 11809.64 | AL29: 0 | AM29: 10676.352 | AN29: 0 | AO29: 0 | AQ29: 0 | AR29: 0 | AS29: 0 | AT29: 0 | AU29: 0 | AV29: 0 | AW29: 0 | AX29: 0 | AY29: 0 | AZ29: 0 | BA29: 0 | BB29: 0 | BD29: 0 | BE29: 0 | BF29: 0 | BG29: 0
C30: Propiedad Minera ME | D30: 91243610 | E30: 1700000 | F30: 331549.75 | G30: =F30*$F$51 -> 340692.45 | I30: 0 | K30: 720000 | M30: 720000 | O30: 260000 | AD30: 0 | AE30: 0 | AF30: 0 | AG30: 0 | AH30: 0 | AI30: 700000 | AJ30: 0 | AK30: 0 | AL30: 20000 | AM30: 0 | AN30: 0 | AO30: 0 | AQ30: 0 | AR30: 0 | AS30: 355737.7 | AT30: 344262.3 | AU30: 0 | AV30: 0 | AW30: 0 | AX30: 0 | AY30: 20000 | AZ30: 0 | BA30: 0 | BB30: 0 | BD30: 0 | BE30: 125517.24 | BF30: 134482.76 | BG30: 0
C31: Medio Ambiente MN | D31: 91243620 | E31: 0 | F31: 0 | G31: =F31*$E$51 -> 0 | I31: 0 | K31: 0 | M31: 0 | O31: 0 | AD31: 0 | AE31: 0 | AF31: 0 | AG31: 0 | AH31: 0 | AI31: 0 | AJ31: 0 | AK31: 0 | AL31: 0 | AM31: 0 | AN31: 0 | AO31: 0 | AQ31: 0 | AR31: 0 | AS31: 0 | AT31: 0 | AU31: 0 | AV31: 0 | AW31: 0 | AX31: 0 | AY31: 0 | AZ31: 0 | BA31: 0 | BB31: 0 | BD31: 0 | BE31: 0 | BF31: 0 | BG31: 0
C32: Medio Ambiente ME | D32: 91243630 | E32: 70000 | F32: 70323.079 | G32: =F32*$F$51 -> 72262.283 | I32: 0 | K32: 45000 | M32: 25000 | O32: 0 | AD32: 0 | AE32: 0 | AF32: 0 | AG32: 0 | AH32: 9117.6471 | AI32: 8823.5294 | AJ32: 9117.6471 | AK32: 9117.6471 | AL32: 8823.5294 | AM32: 0 | AN32: 0 | AO32: 0 | AQ32: 0 | AR32: 0 | AS32: 3621.4953 | AT32: 3504.6729 | AU32: 3621.4953 | AV32: 3504.6729 | AW32: 3621.4953 | AX32: 3621.4953 | AY32: 3504.6729 | AZ32: 0 | BA32: 0 | BB32: 0 | BD32: 0 | BE32: 0 | BF32: 0 | BG32: 0
C33: Seguridad ME | D33: 91243640 | E33: 0 | F33: 0 | G33: =F33*$F$51 -> 0 | I33: 0 | K33: 0 | M33: 0 | O33: 0 | AD33: 0 | AE33: 0 | AF33: 0 | AG33: 0 | AH33: 0 | AI33: 0 | AJ33: 0 | AK33: 0 | AL33: 0 | AM33: 0 | AN33: 0 | AO33: 0 | AQ33: 0 | AR33: 0 | AS33: 0 | AT33: 0 | AU33: 0 | AV33: 0 | AW33: 0 | AX33: 0 | AY33: 0 | AZ33: 0 | BA33: 0 | BB33: 0 | BD33: 0 | BE33: 0 | BF33: 0 | BG33: 0
C34: Comunidades ME | D34: 91243650 | E34: 83667.488 | F34: 85483.936 | G34: =F34*$F$51 -> 87841.21 | I34: 0 | K34: 0 | M34: 14047.465 | O34: 69620.023 | AD34: 0 | AE34: 0 | AF34: 0 | AG34: 0 | AH34: 0 | AI34: 0 | AJ34: 0 | AK34: 0 | AL34: 0 | AM34: 0 | AN34: 0 | AO34: 0 | AQ34: 0 | AR34: 0 | AS34: 0 | AT34: 0 | AU34: 0 | AV34: 0 | AW34: 0 | AX34: 0 | AY34: 0 | AZ34: 0 | BA34: 0 | BB34: 14047.465 | BD34: 0 | BE34: 0 | BF34: 69620.023 | BG34: 0
C35: Administración MN | D35: 91243660 | E35: 3820.5583 | F35: 783.34799 | G35: =F35*$E$51 -> 781.0761 | I35: 0 | K35: 0 | M35: 0 | O35: 3820.5583 | AD35: 0 | AE35: 0 | AF35: 0 | AG35: 0 | AH35: 0 | AI35: 0 | AJ35: 0 | AK35: 0 | AL35: 0 | AM35: 0 | AN35: 0 | AO35: 0 | AQ35: 0 | AR35: 0 | AS35: 0 | AT35: 0 | AU35: 0 | AV35: 0 | AW35: 0 | AX35: 0 | AY35: 0 | AZ35: 0 | BA35: 0 | BB35: 0 | BD35: 0 | BE35: 0 | BF35: 3820.5583 | BG35: 0
C36: Contingencia ME | D36: 91243750 | E36: 68117.701 | F36: 133558.82 | G36: =F36*$F$51 -> 137241.79 | I36: 0 | K36: 41310.498 | M36: 0 | O36: 26807.203 | AD36: 0 | AE36: 0 | AF36: 0 | AG36: 41310.498 | AH36: 0 | AI36: 0 | AJ36: 0 | AK36: 0 | AL36: 0 | AM36: 0 | AN36: 0 | AO36: 0 | AQ36: 0 | AR36: 0 | AS36: 0 | AT36: 0 | AU36: 0 | AV36: 0 | AW36: 0 | AX36: 0 | AY36: 0 | AZ36: 0 | BA36: 0 | BB36: 0 | BD36: 0 | BE36: 0 | BF36: 0 | BG36: 26807.203
C37: Fee MN | D37: 91243910 | E37: 101346.17 | F37: 103078.35 | G37: =F37*$E$51 -> 102779.4 | I37: 0 | K37: 27372.791 | M37: 34847.189 | O37: 39126.187 | AG37: 199.09502 | AH37: 7552.3314 | AI37: 3314.5339 | AJ37: 6305.224 | AK37: 1921.745 | AL37: 1921.745 | AM37: 1921.745 | AN37: 1921.745 | AO37: 2314.6273 | AQ37: 716.43245 | AR37: 716.43245 | AS37: 716.43245 | AT37: 8134.0149 | AU37: 8381.2676 | AV37: 8134.0149 | AW37: 716.43245 | AX37: 716.43245 | AY37: 716.43245 | AZ37: 716.43245 | BA37: 716.43245 | BB37: 4466.4325 | BD37: 37716.432 | BE37: 716.43245 | BF37: 693.32173 | BG37: 0
E40: 6571392.7 | I40: 655490.84 | K40: 1998016.6 | M40: 1999923.5 | O40: 1917961.8
C44: MN | E44: 1338082.6 | F44: =E44*E51 -> 1334201.9 | I44: 335729.46 | K44: 729942.61 | M44: 190876.04 | O44: 81534.524
C45: ME | E45: 5233310.1 | F45: =E45*F51 -> 5377622 | I45: 319761.38 | K45: 1268074 | M45: 1809047.5 | O45: 1836427.2
E46: 6571392.7 | I46: 655490.84 | K46: 1998016.6 | M46: 1999923.5 | O46: 1917961.8
E51: 0.99709977 | F51: 1.0275756

Sheet Vor-RP
D2: ORIG | E2: RP
D3: TOTAL | E3: TOTAL
B4: Exploración Internacional Otros Países | D4: 6574033.2 | E4: =E5 -> 6744916.6
B5: E. Internacional Otros Países | D5: 6574033.2 | E5: =E6+E22 -> 6744916.6
B6: Metalotectos de Interés Item I | D6: 855289.16 | E6: =SUM(E7:E21) -> 355748.03
B7: Geología MN | C7: 91243110 | D7: 306215.66 | E7: ='Formato SAP'!E7 -> 257951.07
B8: Geología ME | C8: 91243120 | D8: 182663.51 | E8: ='Formato SAP'!E8 -> 73547.228
B9: Geoquímica ME | C9: 91243220 | D9: 0 | E9: ='Formato SAP'!E9 -> 0
B10: Geofísica ME | C10: 91243310 | D10: 0 | E10: ='Formato SAP'!E10 -> 0
B11: Sondajes ME | C11: 91243510 | D11: 0 | E11: ='Formato SAP'!E11 -> 0
B12: Logística MN | C12: 91243520 | D12: 142626.28 | E12: ='Formato SAP'!E12 -> 665.30466 | H12: 144957.87
B13: Logística ME | C13: 91243530 | D13: 138574.26 | E13: ='Formato SAP'!E13 -> -1909.942 | H13: 137937.38
B14: Propiedad Minera ME | C14: 91243610 | D14: 0 | E14: ='Formato SAP'!E14 -> 0
B15: Medio Ambiente MN | C15: 91243620 | D15: 0 | E15: ='Formato SAP'!E15 -> 0
B16: Medio Ambiente ME | C16: 91243630 | D16: 0 | E16: ='Formato SAP'!E16 -> 0
B17: Seguridad ME | C17: 91243640 | D17: 0 | E17: ='Formato SAP'!E17 -> 0
B18: Comunidades ME | C18: 91243650 | D18: 0 | E18: ='Formato SAP'!E18 -> 0
B19: Administración MN | C19: 91243660 | D19: 0 | E19: ='Formato SAP'!E19 -> 11960.166
B20: Contingencia ME | C20: 91243750 | D20: 58893.038 | E20: ='Formato SAP'!E20 -> 0
B21: Fee MN | C21: 91243910 | D21: 26316.421 | E21: ='Formato SAP'!E21 -> 13534.209
B22: Metalotectos de Interés Item II | D22: 5718744 | E22: ='Formato SAP'!E22 -> 6389168.5
B23: Geología MN | C23: 91243110 | D23: 481336.05 | E23: ='Formato SAP'!E23 -> 1172987.2
B24: Geología ME | C24: 91243120 | D24: 234099.91 | E24: ='Formato SAP'!E24 -> 1337011
B25: Geoquímica ME | C25: 91243220 | D25: 0 | E25: ='Formato SAP'!E25 -> 0
B26: Geofísica ME | C26: 91243310 | D26: 1657618.3 | E26: ='Formato SAP'!E26 -> 1703101.1
B27: Sondajes ME | C27: 91243510 | D27: 884063.1 | E27: ='Formato SAP'!E27 -> 908441.2
B28: Logística MN | C28: 91243520 | D28: 256590.47 | E28: ='Formato SAP'!E28 -> 314827.15 | H28: 242945.28 | I28: =H28+H12 -> 387903.15 | J28: =I28*I56 -> 0
B29: Logística ME | C29: 91243530 | D29: 170902.61 | E29: ='Formato SAP'!E29 -> 206407 | H29: 187956.98 | I29: =H29+H13 -> 325894.36 | J29: =I29*I57 -> 0
B30: Propiedad Minera ME | C30: 91243610 | D30: 1707849.2 | E30: ='Formato SAP'!E30 -> 340692
B31: Medio Ambiente MN | C31: 91243620 | D31: 0 | E31: ='Formato SAP'!E31 -> 0
B32: Medio Ambiente ME | C32: 91243630 | D32: 70323.201 | E32: ='Formato SAP'!E32 -> 72262.202
B33: Seguridad ME | C33: 91243640 | D33: 0 | E33: ='Formato SAP'!E33 -> 0
B34: Comunidades ME | C34: 91243650 | D34: 84053.794 | E34: ='Formato SAP'!E34 -> 87841.21
B35: Administración MN | C35: 91243660 | D35: 3759.106 | E35: ='Formato SAP'!E35 -> 8230.627
B36: Contingencia ME | C36: 91243750 | D36: 68432.211 | E36: ='Formato SAP'!E36 -> 137241.79
B37: Fee MN | C37: 91243910 | D37: 99716.05 | E37: ='Formato SAP'!E37 -> 100126.13
B42: TOTAL | D42: ORIG | E42: RP
D43: TOTAL | E43: TOTAL
B44: Exploración Internacional Otros Países | D44: =D45 -> 6574402.5 | E44: =E45 -> 6744916.6
B45: E. Internacional Otros Países | D45: =D46+D62 -> 6574402.5 | E45: =E46+E62 -> 6744916.6
B46: Metalotectos de Interés Item I y II | D46: =SUM(D47:D61) -> 6574402.5 | E46: =SUM(E47:E61) -> 6744916.6
B47: Geología MN | C47: 91243110 | D47: =D7+D23 -> 787551.71 | E47: =E7+E23 -> 1430938.2
B48: Geología ME | C48: 91243120 | D48: =D8+D24 -> 416763.42 | E48: =E8+E24 -> 1410558.2
B49: Geoquímica ME | C49: 91243220 | D49: =D9+D25 -> 0 | E49: =E9+E25 -> 0
B50: Geofísica ME | C50: 91243310 | D50: =D10+D26 -> 1657618.3 | E50: =E10+E26 -> 1703101.1
B51: Sondajes ME | C51: 91243510 | D51: =D11+D27 -> 884063.1 | E51: =E11+E27 -> 908441.2
B52: Logística MN | C52: 91243520 | D52: 381663.87 | E52: =E12+E28 -> 315492.46
B53: Logística ME | C53: 91243530 | D53: 327399.06 | E53: =E13+E29 -> 204497.06
B54: Propiedad Minera ME | C54: 91243610 | D54: =D14+D30 -> 1707849.2 | E54: =E14+E30 -> 340692
B55: Medio Ambiente MN | C55: 91243620 | D55: =D15+D31 -> 0 | E55: =E15+E31 -> 0
B56: Medio Ambiente ME | C56: 91243630 | D56: =D16+D32 -> 70323.201 | E56: =E16+E32 -> 72262.202
B57: Seguridad ME | C57: 91243640 | D57: =D17+D33 -> 0 | E57: =E17+E33 -> 0
B58: Comunidades ME | C58: 91243650 | D58: =D18+D34 -> 84053.794 | E58: =E18+E34 -> 87841.21
B59: Administración MN | C59: 91243660 | D59: =D19+D35 -> 3759.106 | E59: =E19+E35 -> 20190.793
B60: Contingencia ME | C60: 91243750 | D60: =D20+D36 -> 127325.25 | E60: =E20+E36 -> 137241.79
B61: Fee MN | C61: 91243910 | D61: =D21+D37 -> 126032.47 | E61: =E21+E37 -> 113660.34
D65: =D47+D52+D55+D59+D61 -> 1299007.2 | E65: =E47+E52+E55+E59+E61 -> 1880281.8
D66: =D48+D49+D50+D51+D53+D54+D56+D57+D58+D60 -> 5275395.3 | E66: =E48+E49+E50+E51+E53+E54+E56+E57+E58+E60 -> 4864634.7

Sheet Formato SAP
E2: 2024-2028 | G2: 2024 | I2: 2025 | K2: 2026 | M2: 2027 | O2: 2028 | Q2: PLANIFICACION AÑO 2024 | AD2: PLANIFICACION AÑO 2025 | AQ2: PLANIFICACION AÑO 2026 | BD2: PLANIFICACION AÑO 2027 | BQ2: PLANIFICACION AÑO 2028
E3: TOTAL | G3: TOTAL AÑO | I3: TOTAL AÑO | K3: TOTAL AÑO | M3: TOTAL AÑO | O3: TOTAL AÑO | Q3: 45322 | R3: 45351 | S3: 45382 | T3: 45412 | U3: 45443 | V3: 45473 | W3: 45504 | X3: 45535 | Y3: 45565 | Z3: 45596 | AA3: 45626 | AB3: 45657 | AD3: 45688 | AE3: 45716 | AF3: 45747 | AG3: 45777 | AH3: 45808 | AI3: 45838 | AJ3: 45869 | AK3: 45900 | AL3: 45930 | AM3: 45961 | AN3: 45991 | AO3: 46022 | AQ3: 46053 | AR3: 46081 | AS3: 46112 | AT3: 46142 | AU3: 46173 | AV3: 46203 | AW3: 46234 | AX3: 46265 | AY3: 46295 | AZ3: 46326 | BA3: 46356 | BB3: 46387 | BD3: 46053 | BE3: 46081 | BF3: 46112 | BG3: 46142 | BH3: 46173 | BI3: 46203 | BJ3: 46234 | BK3: 46265 | BL3: 46295 | BM3: 46326 | BN3: 46356 | BO3: 46387 | BQ3: 46053 | BR3: 46081 | BS3: 46112 | BT3: 46142 | BU3: 46173 | BV3: 46203 | BW3: 46234 | BX3: 46265 | BY3: 46295 | BZ3: 46326 | CA3: 46356 | CB3: 46387
C4: Exploración Internacional Otros Países | E4: =+E5 -> 6744916.6 | G4: =+G5 -> 228189.96 | I4: =+I5 -> 476667.45 | K4: =+K5 -> 1674600.4 | M4: =+M5 -> 2034249.7 | O4: =+O5 -> 2331209 | Q4: 0 | R4: 0 | S4: 0 | T4: 0 | U4: 0 | V4: 0 | W4: =+W5 -> 0 | X4: =+X5 -> 21748.877 | Y4: =+Y5 -> 24753.417 | Z4: =+Z5 -> 58248.926 | AA4: =+AA5 -> 71397.225 | AB4: =+AB5 -> 52041.513 | AD4: =+AD5 -> 43626.259 | AE4: =+AE5 -> 21064.505 | AF4: =+AF5 -> 57868.451 | AG4: =+AG5 -> 13727.544 | AH4: =+AH5 -> -8728.6852 | AI4: =+AI5 -> 3288.7309 | AJ4: =+AJ5 -> 18808.842 | AK4: =+AK5 -> 37716.249 | ... AO4: =+AO5 -> 129527.49 | AQ4: =+AQ5 -> 51205.759 | AR4: =+AR5 -> 141610.1 | AS4: =+AS5 -> 85751.189 | AT4: =+AT5 -> 167840.01 | AU4: =+AU5 -> 77005.517 | AV4: =+AV5 -> 243732.71 | AW4: =+AW5 -> 166508.08 | AX4: =+AX5 -> 62506.951 | ... BB4: =+BB5 -> 473054.62 | BD4: =+BD5 -> 445558.68 | BE4: =+BE5 -> 321275.77 | BF4: =+BF5 -> 481336.31 | BG4: =+BG5 -> 90864.362 | BH4: =+BH5 -> 81346.411 | BI4: =+BI5 -> 240676.62 | BJ4: =+BJ5 -> 77005.128 | BK4: =+BK5 -> 60528.503 | ... BO4: =+BO5 -> 59163.317 | BQ4: =+BQ5 -> 954863.42 | BR4: =+BR5 -> 452697.51 | BS4: =+BS5 -> 497211.73 | BT4: =+BT5 -> 426436.38 | BU4: =+BU5 -> 0 | BV4: =+BV5 -> 0 | BW4: =+BW5 -> 0 | BX4: =+BX5 -> 0 | ... CB4: =+CB5 -> 0
C5: E. Internacional Otros Países | E5: =+E6+E22 -> 6744916.6 | G5: =+G6+G22 -> 228189.96 | I5: =+I6+I22 -> 476667.45 | K5: =+K6+K22 -> 1674600.4 | M5: =+M6+M22 -> 2034249.7 | O5: =+O6+O22 -> 2331209 | Q5: 0 | R5: 0 | S5: 0 | T5: 0 | U5: 0 | V5: 0 | W5: =+W6 -> 0 | X5: =+X6 -> 21748.877 | Y5: =+Y6 -> 24753.417 | Z5: =+Z6 -> 58248.926 | AA5: =+AA6 -> 71397.225 | AB5: =+AB6 -> 52041.513 | AD5: =+AD6+AD22 -> 43626.259 | AE5: =+AE6+AE22 -> 21064.505 | AF5: =+AF6+AF22 -> 57868.451 | AG5: =+AG6+AG22 -> 13727.544 | AH5: =+AH6 -> -8728.6852 | AI5: =+AI6+AI22 -> 3288.7309 | AJ5: =+AJ6+AJ22 -> 18808.842 | AK5: =+AK6+AK22 -> 37716.249 | AL5: =+AL6+AL22 -> 39383.381 | AM5: =+AM6+AM22 -> 56904.187 | AN5: =+AN6+AN22 -> 63480.502 | AO5: =+AO6+AO22 -> 129527.49 | AP5: =+AP6+AP22 -> 0 | ... BO5: =+BO6+BO22 -> 59163.317 | BQ5: =+BQ6+BQ22 -> 954863.42 | BR5: =+BR6+BR22 -> 452697.51 | BS5: =+BS6+BS22 -> 497211.73 | BT5: =+BT6+BT22 -> 426436.38 | BU5: =+BU6+BU22 -> 0 | BV5: =+BV6+BV22 -> 0 | BW5: =+BW6+BW22 -> 0 | BX5: =+BX6+BX22 -> 0 | ... CB5: =+CB6+CB22 -> 0
C6: Metalotectos de Interés Item I | E6: =SUM(E7:E21) -> 355748.03 | G6: =SUM(G7:G21) -> 228189.96 | I6: =SUM(I7:I21) -> 127558.07 | K6: =SUM(K7:K21) -> 0 | M6: =SUM(M7:M21) -> 0 | O6: =SUM(O7:O21) -> 0 | Q6: 0 | R6: 0 | S6: 0 | T6: 0 | U6: 0 | V6: 0 | W6: =SUM(W7:W21) -> 0 | X6: =SUM(X7:X21) -> 21748.877 | Y6: =SUM(Y7:Y21) -> 24753.417 | Z6: =SUM(Z7:Z21) -> 58248.926 | AA6: =SUM(AA7:AA21) -> 71397.225 | AB6: =SUM(AB7:AB21) -> 52041.513 | AD6: =SUM(AD7:AD21) -> 43626.259 | AE6: =SUM(AE7:AE21) -> 21064.505 | AF6: =SUM(AF7:AF21) -> 57868.451 | AG6: =SUM(AG7:AG21) -> 13727.544 | AH6: =SUM(AH7:AH21) -> -8728.6852 | AI6: =SUM(AI7:AI21) -> 0 | AJ6: =SUM(AJ7:AJ21) -> 0 | AK6: =SUM(AK7:AK21) -> 0 | ... AO6: =SUM(AO7:AO21) -> 0 | AQ6: =SUM(AQ7:AQ21) -> 0 | AR6: =SUM(AR7:AR21) -> 0 | AS6: =SUM(AS7:AS21) -> 0 | AT6: =SUM(AT7:AT21) -> 0 | AU6: =SUM(AU7:AU21) -> 0 | AV6: =SUM(AV7:AV21) -> 0 | AW6: =SUM(AW7:AW21) -> 0 | AX6: =SUM(AX7:AX21) -> 0 | ... BB6: =SUM(BB7:BB21) -> 0 | BD6: =SUM(BD7:BD21) -> 0 | BE6: =SUM(BE7:BE21) -> 0 | BF6: =SUM(BF7:BF21) -> 0 | BG6: =SUM(BG7:BG21) -> 0 | BH6: =SUM(BH7:BH21) -> 0 | BI6: =SUM(BI7:BI21) -> 0 | BJ6: =SUM(BJ7:BJ21) -> 0 | BK6: =SUM(BK7:BK21) -> 0 | ... BO6: =SUM(BO7:BO21) -> 0 | BQ6: =SUM(BQ7:BQ21) -> 0 | BR6: =SUM(BR7:BR21) -> 0 | BS6: =SUM(BS7:BS21) -> 0 | BT6: =SUM(BT7:BT21) -> 0 | BU6: =SUM(BU7:BU21) -> 0 | BV6: =SUM(BV7:BV21) -> 0 | BW6: =SUM(BW7:BW21) -> 0 | BX6: =SUM(BX7:BX21) -> 0 | ... CB6: =SUM(CB7:CB21) -> 0
C7: Geología MN | D7: 91243110 | E7: =SUM(G7,I7,K7,M7) -> 257951.07 | G7: =SUM(Q7:AB7) -> 114348.9 | I7: =SUM(AD7:AO7) -> 143602.17 | K7: =SUM(AQ7:BB7) -> 0 | M7: =SUM(BD7:BO7) -> 0 | O7: =SUM(BF7:BQ7) -> 0 | X7: ='G2'!F5 -> 12378.409 | Y7: ='G2'!G5 -> 10182.36 | Z7: ='G2'!H5 -> 23485.148 | AA7: ='G2'!I5 -> 31742.915 | AB7: ='G2'!J5 -> 36560.068 | AD7: ='G2'!K5 -> 36762.03 | AE7: ='G2'!L5 -> 17427.218 | AF7: ='G2'!M5 -> 47239.649 | AG7: ='G2'!N5 -> 9877.9764 | AH7: ='G2'!O5 -> 32295.292
C8: Geología ME | D8: 91243120 | E8: =SUM(G8,I8,K8,M8) -> 73547.228 | G8: =SUM(Q8:AB8) -> 62050.552 | I8: =SUM(AD8:AO8) -> 11496.676 | K8: =SUM(AQ8:BB8) -> 0 | M8: =SUM(BD8:BO8) -> 0 | O8: =SUM(BF8:BQ8) -> 0 | X8: ='G2'!F6 -> 0 | Y8: ='G2'!G6 -> 7923.3141 | Z8: ='G2'!H6 -> 3931.0941 | AA8: ='G2'!I6 -> 39727.013 | AB8: ='G2'!J6 -> 10469.13 | AD8: ='G2'!K6 -> 4379.1953 | AE8: ='G2'!L6 -> 0 | AF8: ='G2'!M6 -> 1942.9534 | AG8: ='G2'!N6 -> 3398.8437 | AH8: ='G2'!O6 -> 1775.6841
C9: Geoquímica ME | D9: 91243220 | E9: =SUM(G9,I9,K9,M9) -> 0 | G9: =SUM(Q9:AB9) -> 0 | I9: =SUM(AD9:AO9) -> 0 | K9: =SUM(AQ9:BB9) -> 0 | M9: =SUM(BD9:BO9) -> 0 | O9: =SUM(BF9:BQ9) -> 0 | X9: ='G2'!F7 -> 0 | Y9: ='G2'!G7 -> 0 | Z9: ='G2'!H7 -> 0 | AA9: ='G2'!I7 -> 0 | AB9: ='G2'!J7 -> 0 | AD9: ='G2'!K7 -> 0 | AE9: ='G2'!L7 -> 0 | AF9: ='G2'!M7 -> 0 | AG9: ='G2'!N7 -> 0 | AH9: ='G2'!O7 -> 0
C10: Geofísica ME | D10: 91243310 | E10: =SUM(G10,I10,K10,M10) -> 0 | G10: =SUM(Q10:AB10) -> 0 | I10: =SUM(AD10:AO10) -> 0 | K10: =SUM(AQ10:BB10) -> 0 | M10: =SUM(BD10:BO10) -> 0 | O10: =SUM(BF10:BQ10) -> 0 | X10: ='G2'!F8 -> 0 | Y10: ='G2'!G8 -> 0 | Z10: ='G2'!H8 -> 0 | AA10: ='G2'!I8 -> 0 | AB10: ='G2'!J8 -> 0 | AD10: ='G2'!K8 -> 0 | AE10: ='G2'!L8 -> 0 | AF10: ='G2'!M8 -> 0 | AG10: ='G2'!N8 -> 0 | AH10: ='G2'!O8 -> 0
C11: Sondajes ME | D11: 91243510 | E11: =SUM(G11,I11,K11,M11) -> 0 | G11: =SUM(Q11:AB11) -> 0 | I11: =SUM(AD11:AO11) -> 0 | K11: =SUM(AQ11:BB11) -> 0 | M11: =SUM(BD11:BO11) -> 0 | O11: =SUM(BF11:BQ11) -> 0 | X11: ='G2'!F9 -> 0 | Y11: ='G2'!G9 -> 0 | Z11: ='G2'!H9 -> 0 | AA11: ='G2'!I9 -> 0 | AB11: ='G2'!J9 -> 0 | AD11: ='G2'!K9 -> 0 | AE11: ='G2'!L9 -> 0 | AF11: ='G2'!M9 -> 0 | AG11: ='G2'!N9 -> 0 | AH11: ='G2'!O9 -> 0
C12: Logística MN | D12: 91243520 | E12: =SUM(G12,I12,K12,M12) -> 665.30466 | G12: =SUM(Q12:AB12) -> 34560.192 | I12: =SUM(AD12:AO12) -> -33894.887 | K12: =SUM(AQ12:BB12) -> 0 | M12: =SUM(BD12:BO12) -> 0 | O12: =SUM(BF12:BQ12) -> 0 | X12: ='G2'!F10 -> 8892.6998 | Y12: ='G2'!G10 -> 5768.8417 | Z12: ='G2'!H10 -> 23445.938 | AA12: ='G2'!I10 -> 2833.7478 | AB12: ='G2'!J10 -> -6381.0353 | AD12: ='G2'!K10 -> 0 | AE12: ='G2'!L10 -> 0 | AF12: ='G2'!M10 -> 8069.1979 | AG12: ='G2'!N10 -> 0 | AH12: ='G2'!O10 -> -41964.085
C13: Logística ME | D13: 91243530 | E13: =SUM(G13,I13,K13,M13) -> -1909.942 | G13: =SUM(Q13:AB13) -> -125.16104 | I13: =SUM(AD13:AO13) -> -1784.7809 | K13: =SUM(AQ13:BB13) -> 0 | M13: =SUM(BD13:BO13) -> 0 | O13: =SUM(BF13:BQ13) -> 0 | X13: ='G2'!F11 -> 0 | Y13: ='G2'!G11 -> 0 | Z13: ='G2'!H11 -> 4713.5532 | AA13: ='G2'!I11 -> -4663.9872 | AB13: ='G2'!J11 -> -174.72702 | AD13: ='G2'!K11 -> 0 | AE13: ='G2'!L11 -> 0 | AF13: ='G2'!M11 -> 0 | AG13: ='G2'!N11 -> 0 | AH13: ='G2'!O11 -> -1784.7809
C14: Propiedad Minera ME | D14: 91243610 | E14: =SUM(G14,I14,K14,M14) -> 0 | G14: =SUM(Q14:AB14) -> 0 | I14: =SUM(AD14:AO14) -> 0 | K14: =SUM(AQ14:BB14) -> 0 | M14: =SUM(BD14:BO14) -> 0 | O14: =SUM(BF14:BQ14) -> 0 | X14: ='G2'!F12 -> 0 | Y14: ='G2'!G12 -> 0 | Z14: ='G2'!H12 -> 0 | AA14: ='G2'!I12 -> 0 | AB14: ='G2'!J12 -> 0 | AD14: ='G2'!K12 -> 0 | AE14: ='G2'!L12 -> 0 | AF14: ='G2'!M12 -> 0 | AG14: ='G2'!N12 -> 0 | AH14: ='G2'!O12 -> 0
C15: Medio Ambiente MN | D15: 91243620 | E15: =SUM(G15,I15,K15,M15) -> 0 | G15: =SUM(Q15:AB15) -> 0 | I15: =SUM(AD15:AO15) -> 0 | K15: =SUM(AQ15:BB15) -> 0 | M15: =SUM(BD15:BO15) -> 0 | O15: =SUM(BF15:BQ15) -> 0 | X15: ='G2'!F13 -> 0 | Y15: ='G2'!G13 -> 0 | Z15: ='G2'!H13 -> 0 | AA15: ='G2'!I13 -> 0 | AB15: ='G2'!J13 -> 0 | AD15: ='G2'!K13 -> 0 | AE15: ='G2'!L13 -> 0 | AF15: ='G2'!M13 -> 0 | AG15: ='G2'!N13 -> 0 | AH15: ='G2'!O13 -> 0
C16: Medio Ambiente ME | D16: 91243630 | E16: =SUM(G16,I16,K16,M16) -> 0 | G16: =SUM(Q16:AB16) -> 0 | I16: =SUM(AD16:AO16) -> 0 | K16: =SUM(AQ16:BB16) -> 0 | M16: =SUM(BD16:BO16) -> 0 | O16: =SUM(BF16:BQ16) -> 0 | X16: ='G2'!F14 -> 0 | Y16: ='G2'!G14 -> 0 | Z16: ='G2'!H14 -> 0 | AA16: ='G2'!I14 -> 0 | AB16: ='G2'!J14 -> 0 | AD16: ='G2'!K14 -> 0 | AE16: ='G2'!L14 -> 0 | AF16: ='G2'!M14 -> 0 | AG16: ='G2'!N14 -> 0 | AH16: ='G2'!O14 -> 0
C17: Seguridad ME | D17: 91243640 | E17: =SUM(G17,I17,K17,M17) -> 0 | G17: =SUM(Q17:AB17) -> 0 | I17: =SUM(AD17:AO17) -> 0 | K17: =SUM(AQ17:BB17) -> 0 | M17: =SUM(BD17:BO17) -> 0 | O17: =SUM(BF17:BQ17) -> 0 | X17: ='G2'!F15 -> 0 | Y17: ='G2'!G15 -> 0 | Z17: ='G2'!H15 -> 0 | AA17: ='G2'!I15 -> 0 | AB17: ='G2'!J15 -> 0 | AD17: ='G2'!K15 -> 0 | AE17: ='G2'!L15 -> 0 | AF17: ='G2'!M15 -> 0 | AG17: ='G2'!N15 -> 0 | AH17: ='G2'!O15 -> 0
C18: Comunidades ME | D18: 91243650 | E18: =SUM(G18,I18,K18,M18) -> 0 | G18: =SUM(Q18:AB18) -> 0 | I18: =SUM(AD18:AO18) -> 0 | K18: =SUM(AQ18:BB18) -> 0 | M18: =SUM(BD18:BO18) -> 0 | O18: =SUM(BF18:BQ18) -> 0 | X18: ='G2'!F16 -> 0 | Y18: ='G2'!G16 -> 0 | Z18: ='G2'!H16 -> 0 | AA18: ='G2'!I16 -> 0 | AB18: ='G2'!J16 -> 0 | AD18: ='G2'!K16 -> 0 | AE18: ='G2'!L16 -> 0 | AF18: ='G2'!M16 -> 0 | AG18: ='G2'!N16 -> 0 | AH18: ='G2'!O16 -> 0
... C20: Contingencia ME | D20: 91243750 | E20: =SUM(G20,I20,K20,M20) -> 0 | G20: =SUM(Q20:AB20) -> 0 | I20: =SUM(AD20:AO20) -> 0 | K20: =SUM(AQ20:BB20) -> 0 | M20: =SUM(BD20:BO20) -> 0 | O20: =SUM(BF20:BQ20) -> 0 | X20: ='G2'!F18 -> 0 | Y20: ='G2'!G18 -> 0 | Z20: ='G2'!H18 -> 0 | AA20: ='G2'!I18 -> 0 | AB20: ='G2'!J18 -> 0 | AD20: ='G2'!K18 -> 0 | AE20: ='G2'!L18 -> 0 | AF20: ='G2'!M18 -> 0 | AG20: ='G2'!N18 -> 0 | AH20: ='G2'!O18 -> 0
C21: Fee MN | D21: 91243910 | E21: =SUM(G21,I21,K21,M21) -> 13534.209 | G21: =SUM(Q21:AB21) -> 8398.8917 | I21: =SUM(AD21:AO21) -> 5135.3171 | K21: =SUM(AQ21:BB21) -> 0 | M21: =SUM(BD21:BO21) -> 0 | O21: =SUM(BF21:BQ21) -> 0 | X21: ='G2'!F20+'G2'!F21 -> 477.76831 | Y21: ='G2'!G20+'G2'!G21 -> 878.90031 | Z21: ='G2'!H20+'G2'!H21 -> 2673.1929 | AA21: ='G2'!I20+'G2'!I21 -> 1757.5362 | AB21: ='G2'!J20+'G2'!J21 -> 2611.4939 | AD21: ='G2'!K20+'G2'!K21 -> 2485.0338 | AE21: ='G2'!L20+'G2'!L21 -> 710.64931 | AF21: ='G2'!M20+'G2'!M21 -> 539.70597 | AG21: ='G2'!N20+'G2'!N21 -> 450.72355 | AH21: ='G2'!O20+'G2'!O21 -> 949.2045
C22: Metalotectos de Interés Item II | E22: =SUM(E23:E37) -> 6389168.5 | G22: =SUM(G23:G37) -> 0 | I22: =SUM(I23:I37) -> 349109.38 | K22: =SUM(K23:K37) -> 1674600.4 | M22: =SUM(M23:M37) -> 2034249.7 | O22: =SUM(O23:O37) -> 2331209 | Q22: 0 | R22: 0 | S22: 0 | T22: 0 | U22: 0 | V22: 0 | W22: =SUM(W23:W37) -> 0 | X22: =SUM(X23:X37) -> 0 | Y22: =SUM(Y23:Y37) -> 0 | Z22: =SUM(Z23:Z37) -> 0 | AA22: =SUM(AA23:AA37) -> 0 | AB22: =SUM(AB23:AB37) -> 0 | AD22: =SUM(AD23:AD37) -> 0 | AE22: =SUM(AE23:AE37) -> 0 | AF22: =SUM(AF23:AF37) -> 0 | AG22: =SUM(AG23:AG37) -> 0 | AH22: =SUM(AH23:AH37) -> 0 | AI22: =SUM(AI23:AI37) -> 3288.7309 | AJ22: =SUM(AJ23:AJ37) -> 18808.842 | AK22: =SUM(AK23:AK37) -> 37716.249 | ... AO22: =SUM(AO23:AO37) -> 129527.49 | AQ22: =SUM(AQ23:AQ37) -> 51205.759 | AR22: =SUM(AR23:AR37) -> 141610.1 | AS22: =SUM(AS23:AS37) -> 85751.189 | AT22: =SUM(AT23:AT37) -> 167840.01 | AU22: =SUM(AU23:AU37) -> 77005.517 | AV22: =SUM(AV23:AV37) -> 243732.71 | AW22: =SUM(AW23:AW37) -> 166508.08 | AX22: =SUM(AX23:AX37) -> 62506.951 | ... BB22: =SUM(BB23:BB37) -> 473054.62 | BD22: =SUM(BD23:BD37) -> 445558.68 | BE22: =SUM(BE23:BE37) -> 321275.77 | BF22: =SUM(BF23:BF37) -> 481336.31 | BG22: =SUM(BG23:BG37) -> 90864.362 | BH22: =SUM(BH23:BH37) -> 81346.411 | BI22: =SUM(BI23:BI37) -> 240676.62 | BJ22: =SUM(BJ23:BJ37) -> 77005.128 | BK22: =SUM(BK23:BK37) -> 60528.503 | ... BO22: =SUM(BO23:BO37) -> 59163.317 | BQ22: =SUM(BQ23:BQ37) -> 954863.42 | BR22: =SUM(BR23:BR37) -> 452697.51 | BS22: =SUM(BS23:BS37) -> 497211.73 | BT22: =SUM(BT23:BT37) -> 426436.38 | BU22: =SUM(BU23:BU37) -> 0 | BV22: =SUM(BV23:BV37) -> 0 | BW22: =SUM(BW23:BW37) -> 0 | BX22: =SUM(BX23:BX37) -> 0 | ... CB22: =SUM(CB23:CB37) -> 0
C23: Geología MN | D23: 91243110 | E23: =SUM(G23,I23,K23,M23,O23) -> 1172987.2 | G23: =SUM(Q23:AB23) -> 0 | I23: =SUM(AD23:AO23) -> 166801.34 | K23: =SUM(AQ23:BB23) -> 405733.35 | M23: =SUM(BD23:BO23) -> 429592.71 | O23: =SUM(BQ23:CB23) -> 170859.77 | AI23: ='G2'!P5 -> 3138.7192 | AJ23: ='G2'!Q5 -> 17880.952 | AK23: ='G2'!R5 -> 27566.242 | AL23: ='G2'!S5 -> 28961.285 | AM23: ='G2'!T5 -> 27516.976 | AN23: ='G2'!U5 -> 27686.975 | AO23: ='G2'!V5 -> 34050.191 | AQ23: ='G2'!W5 -> 22330.695 | AR23: ='G2'!X5 -> 32333.243 | AS23: ='G2'!Y5 -> 38517.066 | AT23: ='G2'!Z5 -> 45624.881 | AU23: ='G2'!AA5 -> 38517.066 | AV23: ='G2'!AB5 -> 41820.587 | AW23: ='G2'!AC5 -> 38517.066 | AX23: ='G2'!AD5 -> 29781.565 | ... BB23: ='G2'!AH5 -> 29781.565 | BD23: ='G2'!AI5 -> 31072.688 | BE23: ='G2'!AJ5 -> 29657.695 | BF23: ='G2'!AK5 -> 48187.583 | BG23: ='G2'!AL5 -> 39999.23 | BH23: ='G2'!AM5 -> 40578.993 | BI23: ='G2'!AN5 -> 43803.524 | BJ23: ='G2'!AO5 -> 40578.993 | BK23: ='G2'!AP5 -> 32366.581 | ... BO23: ='G2'!AT5 -> 31072.688 | BQ23: ='G2'!AU5 -> 89315.397 | BR23: ='G2'!AV5 -> 30129.359 | BS23: ='G2'!AW5 -> 31072.688 | BT23: ='G2'!AX5 -> 20342.325 | BU23: ='G2'!AY5 -> 0 | BV23: ='G2'!AZ5 -> 0 | BW23: ='G2'!BA5 -> 0 | BX23: ='G2'!BB5 -> 0 | ... CB23: ='G2'!BF5 -> 0
C24: Geología ME | D24: 91243120 | E24: =SUM(G24,I24,K24,M24,O24) -> 1337011 | G24: =SUM(Q24:AB24) -> 0 | I24: =SUM(AD24:AO24) -> 55339.997 | K24: =SUM(AQ24:BB24) -> 418417.1 | M24: =SUM(BD24:BO24) -> 434267.95 | O24: =SUM(BQ24:CB24) -> 428985.95 | AI24: ='G2'!P6 -> 0 | AJ24: ='G2'!Q6 -> 0 | AK24: ='G2'!R6 -> 0 | AL24: ='G2'!S6 -> 8202.506 | AM24: ='G2'!T6 -> 13865.574 | AN24: ='G2'!U6 -> 0.0010971051 | AO24: ='G2'!V6 -> 33271.915 | AQ24: ='G2'!W6 -> 10773.278 | AR24: ='G2'!X6 -> 52560.391 | AS24: ='G2'!Y6 -> 28233.43 | AT24: ='G2'!Z6 -> 71272.505 | AU24: ='G2'!AA6 -> 29145.125 | AV24: ='G2'!AB6 -> 50597.12 | AW24: ='G2'!AC6 -> 29145.125 | AX24: ='G2'!AD6 -> 29145.125 | ... BB24: ='G2'!AH6 -> 28638.353 | BD24: ='G2'!AI6 -> 28638.353 | BE24: ='G2'!AJ6 -> 33457.012 | BF24: ='G2'!AK6 -> 82259.998 | BG24: ='G2'!AL6 -> 38716.417 | BH24: ='G2'!AM6 -> 33513.019 | BI24: ='G2'!AN6 -> 54824.114 | BJ24: ='G2'!AO6 -> 33513.019 | BK24: ='G2'!AP6 -> 25869.204 | ... BO24: ='G2'!AT6 -> 25869.204 | BQ24: ='G2'!AU6 -> 321031.64 | BR24: ='G2'!AV6 -> 35647.584 | BS24: ='G2'!AW6 -> 36321.955 | BT24: ='G2'!AX6 -> 35984.769 | BU24: ='G2'!AY6 -> 0 | BV24: ='G2'!AZ6 -> 0 | BW24: ='G2'!BA6 -> 0 | BX24: ='G2'!BB6 -> 0 | ... CB24: ='G2'!BF6 -> 0
C25: Geoquímica ME | D25: 91243220 | E25: =SUM(G25,I25,K25,M25,O25) -> 0 | G25: =SUM(Q25:AB25) -> 0 | I25: =SUM(AD25:AO25) -> 0 | K25: =SUM(AQ25:BB25) -> 0 | M25: =SUM(BD25:BO25) -> 0 | O25: =SUM(BQ25:CB25) -> 0 | AI25: ='G2'!P7 -> 0 | AJ25: ='G2'!Q7 -> 0 | AK25: ='G2'!R7 -> 0 | AL25: ='G2'!S7 -> 0 | AM25: ='G2'!T7 -> 0 | AN25: ='G2'!U7 -> 0 | AO25: ='G2'!V7 -> 0 | AQ25: ='G2'!W7 -> 0 | AR25: ='G2'!X7 -> 0 | AS25: ='G2'!Y7 -> 0 | AT25: ='G2'!Z7 -> 0 | AU25: ='G2'!AA7 -> 0 | AV25: ='G2'!AB7 -> 0 | AW25: ='G2'!AC7 -> 0 | AX25: ='G2'!AD7 -> 0 | ... BB25: ='G2'!AH7 -> 0 | BD25: ='G2'!AI7 -> 0 | BE25: ='G2'!AJ7 -> 0 | BF25: ='G2'!AK7 -> 0 | BG25: ='G2'!AL7 -> 0 | BH25: ='G2'!AM7 -> 0 | BI25: ='G2'!AN7 -> 0 | BJ25: ='G2'!AO7 -> 0 | BK25: ='G2'!AP7 -> 0 | ... BO25: ='G2'!AT7 -> 0 | BQ25: ='G2'!AU7 -> 0 | BR25: ='G2'!AV7 -> 0 | BS25: ='G2'!AW7 -> 0 | BT25: ='G2'!AX7 -> 0 | BU25: ='G2'!AY7 -> 0 | BV25: ='G2'!AZ7 -> 0 | BW25: ='G2'!BA7 -> 0 | BX25: ='G2'!BB7 -> 0 | ... CB25: ='G2'!BF7 -> 0
C26: Geofísica ME | D26: 91243310 | E26: =SUM(G26,I26,K26,M26,O26) -> 1703101.1 | G26: =SUM(Q26:AB26) -> 0 | I26: =SUM(AD26:AO26) -> 0 | K26: =SUM(AQ26:BB26) -> 342561.73 | M26: =SUM(BD26:BO26) -> 831440.7 | O26: =SUM(BQ26:CB26) -> 529098.63 | AI26: ='G2'!P8 -> 0 | AJ26: ='G2'!Q8 -> 0 | AK26: ='G2'!R8 -> 0 | AL26: ='G2'!S8 -> 0 | AM26: ='G2'!T8 -> 0 | AN26: ='G2'!U8 -> 0 | AO26: ='G2'!V8 -> 0 | AQ26: ='G2'!W8 -> 0 | AR26: ='G2'!X8 -> 0 | AS26: ='G2'!Y8 -> 0 | AT26: ='G2'!Z8 -> 0 | AU26: ='G2'!AA8 -> 0 | AV26: ='G2'!AB8 -> 0 | AW26: ='G2'!AC8 -> 0 | AX26: ='G2'!AD8 -> 0 | ... BB26: ='G2'!AH8 -> 342561.73 | BD26: ='G2'!AI8 -> 283238.04 | BE26: ='G2'!AJ8 -> 255827.91 | BF26: ='G2'!AK8 -> 283238.04 | BG26: ='G2'!AL8 -> 9136.711 | BH26: ='G2'!AM8 -> 0 | BI26: ='G2'!AN8 -> 0 | BJ26: ='G2'!AO8 -> 0 | BK26: ='G2'!AP8 -> 0 | ... BO26: ='G2'!AT8 -> 0 | BQ26: ='G2'!AU8 -> 178283.23 | BR26: ='G2'!AV8 -> 166781.09 | BS26: ='G2'!AW8 -> 178283.23 | BT26: ='G2'!AX8 -> 5751.072 | BU26: ='G2'!AY8 -> 0 | BV26: ='G2'!AZ8 -> 0 | BW26: ='G2'!BA8 -> 0 | BX26: ='G2'!BB8 -> 0 | ... CB26: ='G2'!BF8 -> 0
C27: Sondajes ME | D27: 91243510 | E27: =SUM(G27,I27,K27,M27,O27) -> 908441.2 | G27: =SUM(Q27:AB27) -> 0 | I27: =SUM(AD27:AO27) -> 0 | K27: =SUM(AQ27:BB27) -> 0 | M27: =SUM(BD27:BO27) -> 0 | O27: =SUM(BQ27:CB27) -> 908441.2 | AI27: ='G2'!P9 -> 0 | AJ27: ='G2'!Q9 -> 0 | AK27: ='G2'!R9 -> 0 | AL27: ='G2'!S9 -> 0 | AM27: ='G2'!T9 -> 0 | AN27: ='G2'!U9 -> 0 | AO27: ='G2'!V9 -> 0 | AQ27: ='G2'!W9 -> 0 | AR27: ='G2'!X9 -> 0 | AS27: ='G2'!Y9 -> 0 | AT27: ='G2'!Z9 -> 0 | AU27: ='G2'!AA9 -> 0 | AV27: ='G2'!AB9 -> 0 | AW27: ='G2'!AC9 -> 0 | AX27: ='G2'!AD9 -> 0 | ... BB27: ='G2'!AH9 -> 0 | BD27: ='G2'!AI9 -> 0 | BE27: ='G2'!AJ9 -> 0 | BF27: ='G2'!AK9 -> 0 | BG27: ='G2'!AL9 -> 0 | BH27: ='G2'!AM9 -> 0 | BI27: ='G2'!AN9 -> 0 | BJ27: ='G2'!AO9 -> 0 | BK27: ='G2'!AP9 -> 0 | ... BO27: ='G2'!AT9 -> 0 | BQ27: ='G2'!AU9 -> 232741.13 | BR27: ='G2'!AV9 -> 217725.58 | BS27: ='G2'!AW9 -> 232741.13 | BT27: ='G2'!AX9 -> 225233.35 | BU27: ='G2'!AY9 -> 0 | BV27: ='G2'!AZ9 -> 0 | BW27: ='G2'!BA9 -> 0 | BX27: ='G2'!BB9 -> 0 | ... CB27: ='G2'!BF9 -> 0
C28: Logística MN | D28: 91243520 | E28: =SUM(G28,I28,K28,M28,O28) -> 314827.15 | G28: =SUM(Q28:AB28) -> 0 | I28: =SUM(AD28:AO28) -> 109488.13 | K28: =SUM(AQ28:BB28) -> 77912.711 | M28: =SUM(BD28:BO28) -> 87445.543 | O28: =SUM(BQ28:CB28) -> 39980.767 | AI28: ='G2'!P10 -> 0 | AJ28: ='G2'!Q10 -> 0 | AK28: ='G2'!R10 -> 8620.6651 | AL28: ='G2'!S10 -> 1012.9016 | AM28: ='G2'!T10 -> 13594.026 | AN28: ='G2'!U10 -> 34373.876 | AO28: ='G2'!V10 -> 51886.662 | AQ28: ='G2'!W10 -> 16885.307 | AR28: ='G2'!X10 -> 19126.215 | AS28: ='G2'!Y10 -> 0 | AT28: ='G2'!Z10 -> 23443.536 | AU28: ='G2'!AA10 -> 0 | AV28: ='G2'!AB10 -> 18457.654 | AW28: ='G2'!AC10 -> 0 | AX28: ='G2'!AD10 -> 0 | ... BB28: ='G2'!AH10 -> 0 | BD28: ='G2'!AI10 -> 41732.893 | BE28: ='G2'!AJ10 -> 0 | BF28: ='G2'!AK10 -> 23297.897 | BG28: ='G2'!AL10 -> 0 | BH28: ='G2'!AM10 -> 0 | BI28: ='G2'!AN10 -> 22414.753 | BJ28: ='G2'!AO10 -> 0 | BK28: ='G2'!AP10 -> 0 | ... BO28: ='G2'!AT10 -> 0 | BQ28: ='G2'!AU10 -> 39980.767 | BR28: ='G2'!AV10 -> 0 | BS28: ='G2'!AW10 -> 0 | BT28: ='G2'!AX10 -> 0 | BU28: ='G2'!AY10 -> 0 | BV28: ='G2'!AZ10 -> 0 | BW28: ='G2'!BA10 -> 0 | BX28: ='G2'!BB10 -> 0 | ... CB28: ='G2'!BF10 -> 0
C29: Logística ME | D29: 91243530 | E29: =SUM(G29,I29,K29,M29,O29) -> 206407 | G29: =SUM(Q29:AB29) -> 0 | I29: =SUM(AD29:AO29) -> 1.0231815e-12 | K29: =SUM(AQ29:BB29) -> 100676.49 | M29: =SUM(BD29:BO29) -> 89818.332 | O29: =SUM(BQ29:CB29) -> 15912.175 | AI29: ='G2'!P11 -> 0 | AJ29: ='G2'!Q11 -> 0 | AK29: ='G2'!R11 -> 0 | AL29: ='G2'!S11 -> 0 | AM29: ='G2'!T11 -> 0 | AN29: ='G2'!U11 -> 0 | AO29: ='G2'!V11 -> 1.0231815e-12 | AQ29: ='G2'!W11 -> 0 | AR29: ='G2'!X11 -> 33432.627 | AS29: ='G2'!Y11 -> 15912.175 | AT29: ='G2'!Z11 -> 22423.109 | AU29: ='G2'!AA11 -> 0 | AV29: ='G2'!AB11 -> 28908.583 | AW29: ='G2'!AC11 -> 0 | AX29: ='G2'!AD11 -> 0 | ... BB29: ='G2'!AH11 -> 0 | BD29: ='G2'!AI11 -> 0 | BE29: ='G2'!AJ11 -> 0 | BF29: ='G2'!AK11 -> 38486.187 | BG29: ='G2'!AL11 -> 0 | BH29: ='G2'!AM11 -> 0 | BI29: ='G2'!AN11 -> 51332.145 | BJ29: ='G2'!AO11 -> 0 | BK29: ='G2'!AP11 -> 0 | ... BO29: ='G2'!AT11 -> 0 | BQ29: ='G2'!AU11 -> 0 | BR29: ='G2'!AV11 -> 0 | BS29: ='G2'!AW11 -> 15912.175 | BT29: ='G2'!AX11 -> 0 | BU29: ='G2'!AY11 -> 0 | BV29: ='G2'!AZ11 -> 0 | BW29: ='G2'!BA11 -> 0 | BX29: ='G2'!BB11 -> 0 | ... CB29: ='G2'!BF11 -> 0
C30: Propiedad Minera ME | D30: 91243610 | E30: =SUM(G30,I30,K30,M30,O30) -> 340692 | G30: =SUM(Q30:AB30) -> 0 | I30: =SUM(AD30:AO30) -> 0 | K30: =SUM(AQ30:BB30) -> 222430.69 | M30: =SUM(BD30:BO30) -> 36991.406 | O30: =SUM(BQ30:CB30) -> 81269.903 | AI30: ='G2'!P12 -> 0 | AJ30: ='G2'!Q12 -> 0 | AK30: ='G2'!R12 -> 0 | AL30: ='G2'!S12 -> 0 | AM30: ='G2'!T12 -> 0 | AN30: ='G2'!U12 -> 0 | AO30: ='G2'!V12 -> 0 | AQ30: ='G2'!W12 -> 0 | AR30: ='G2'!X12 -> 0 | AS30: ='G2'!Y12 -> 0 | AT30: ='G2'!Z12 -> 0 | AU30: ='G2'!AA12 -> 6629.8193 | AV30: ='G2'!AB12 -> 99447.29 | AW30: ='G2'!AC12 -> 96132.38 | AX30: ='G2'!AD12 -> 1348.0801 | ... BB30: ='G2'!AH12 -> 0 | BD30: ='G2'!AI12 -> 36991.406 | BE30: ='G2'!AJ12 -> 0 | BF30: ='G2'!AK12 -> 0 | BG30: ='G2'!AL12 -> 0 | BH30: ='G2'!AM12 -> 0 | BI30: ='G2'!AN12 -> 0 | BJ30: ='G2'!AO12 -> 0 | BK30: ='G2'!AP12 -> 0 | ... BO30: ='G2'!AT12 -> 0 | BQ30: ='G2'!AU12 -> 81269.903 | BR30: ='G2'!AV12 -> 0 | BS30: ='G2'!AW12 -> 0 | BT30: ='G2'!AX12 -> 0 | BU30: ='G2'!AY12 -> 0 | BV30: ='G2'!AZ12 -> 0 | BW30: ='G2'!BA12 -> 0 | BX30: ='G2'!BB12 -> 0 | ... CB30: ='G2'!BF12 -> 0
C31: Medio Ambiente MN | D31: 91243620 | E31: =SUM(G31,I31,K31,M31,O31) -> 0 | G31: =SUM(Q31:AB31) -> 0 | I31: =SUM(AD31:AO31) -> 0 | K31: =SUM(AQ31:BB31) -> 0 | M31: =SUM(BD31:BO31) -> 0 | O31: =SUM(BQ31:CB31) -> 0 | AI31: ='G2'!P13 -> 0 | AJ31: ='G2'!Q13 -> 0 | AK31: ='G2'!R13 -> 0 | AL31: ='G2'!S13 -> 0 | AM31: ='G2'!T13 -> 0 | AN31: ='G2'!U13 -> 0 | AO31: ='G2'!V13 -> 0 | AQ31: ='G2'!W13 -> 0 | AR31: ='G2'!X13 -> 0 | AS31: ='G2'!Y13 -> 0 | AT31: ='G2'!Z13 -> 0 | AU31: ='G2'!AA13 -> 0 | AV31: ='G2'!AB13 -> 0 | AW31: ='G2'!AC13 -> 0 | AX31: ='G2'!AD13 -> 0 | ... BB31: ='G2'!AH13 -> 0 | BD31: ='G2'!AI13 -> 0 | BE31: ='G2'!AJ13 -> 0 | BF31: ='G2'!AK13 -> 0 | BG31: ='G2'!AL13 -> 0 | BH31: ='G2'!AM13 -> 0 | BI31: ='G2'!AN13 -> 0 | BJ31: ='G2'!AO13 -> 0 | BK31: ='G2'!AP13 -> 0 | ... BO31: ='G2'!AT13 -> 0 | BQ31: ='G2'!AU13 -> 0 | BR31: ='G2'!AV13 -> 0 | BS31: ='G2'!AW13 -> 0 | BT31: ='G2'!AX13 -> 0 | BU31: ='G2'!AY13 -> 0 | BV31: ='G2'!AZ13 -> 0 | BW31: ='G2'!BA13 -> 0 | BX31: ='G2'!BB13 -> 0 | ... CB31: ='G2'!BF13 -> 0
C32: Medio Ambiente ME | D32: 91243630 | E32: =SUM(G32,I32,K32,M32,O32) -> 72262.202 | G32: =SUM(Q32:AB32) -> 0 | I32: =SUM(AD32:AO32) -> 0 | K32: =SUM(AQ32:BB32) -> 72262.202 | M32: =SUM(BD32:BO32) -> 0 | O32: =SUM(BQ32:CB32) -> 0 | AI32: ='G2'!P14 -> 0 | AJ32: ='G2'!Q14 -> 0 | AK32: ='G2'!R14 -> 0 | AL32: ='G2'!S14 -> 0 | AM32: ='G2'!T14 -> 0 | AN32: ='G2'!U14 -> 0 | AO32: ='G2'!V14 -> 0 | AQ32: ='G2'!W14 -> 0 | AR32: ='G2'!X14 -> 0 | AS32: ='G2'!Y14 -> 0 | AT32: ='G2'!Z14 -> 0 | AU32: ='G2'!AA14 -> 0 | AV32: ='G2'!AB14 -> 0 | AW32: ='G2'!AC14 -> 0 | AX32: ='G2'!AD14 -> 0 | ... BB32: ='G2'!AH14 -> 69853.462 | BD32: ='G2'!AI14 -> 0 | BE32: ='G2'!AJ14 -> 0 | BF32: ='G2'!AK14 -> 0 | BG32: ='G2'!AL14 -> 0 | BH32: ='G2'!AM14 -> 0 | BI32: ='G2'!AN14 -> 0 | BJ32: ='G2'!AO14 -> 0 | BK32: ='G2'!AP14 -> 0 | ... BO32: ='G2'!AT14 -> 0 | BQ32: ='G2'!AU14 -> 0 | BR32: ='G2'!AV14 -> 0 | BS32: ='G2'!AW14 -> 0 | BT32: ='G2'!AX14 -> 0 | BU32: ='G2'!AY14 -> 0 | BV32: ='G2'!AZ14 -> 0 | BW32: ='G2'!BA14 -> 0 | BX32: ='G2'!BB14 -> 0 | ... CB32: ='G2'!BF14 -> 0
C33: Seguridad ME | D33: 91243640 | E33: =SUM(G33,I33,K33,M33,O33) -> 0 | G33: =SUM(Q33:AB33) -> 0 | I33: =SUM(AD33:AO33) -> 0 | K33: =SUM(AQ33:BB33) -> 0 | M33: =SUM(BD33:BO33) -> 0 | O33: =SUM(BQ33:CB33) -> 0 | AI33: ='G2'!P15 -> 0 | AJ33: ='G2'!Q15 -> 0 | AK33: ='G2'!R15 -> 0 | AL33: ='G2'!S15 -> 0 | AM33: ='G2'!T15 -> 0 | AN33: ='G2'!U15 -> 0 | AO33: ='G2'!V15 -> 0 | AQ33: ='G2'!W15 -> 0 | AR33: ='G2'!X15 -> 0 | AS33: ='G2'!Y15 -> 0 | AT33: ='G2'!Z15 -> 0 | AU33: ='G2'!AA15 -> 0 | AV33: ='G2'!AB15 -> 0 | AW33: ='G2'!AC15 -> 0 | AX33: ='G2'!AD15 -> 0 | ... BB33: ='G2'!AH15 -> 0 | BD33: ='G2'!AI15 -> 0 | BE33: ='G2'!AJ15 -> 0 | BF33: ='G2'!AK15 -> 0 | BG33: ='G2'!AL15 -> 0 | BH33: ='G2'!AM15 -> 0 | BI33: ='G2'!AN15 -> 0 | BJ33: ='G2'!AO15 -> 0 | BK33: ='G2'!AP15 -> 0 | ... BO33: ='G2'!AT15 -> 0 | BQ33: ='G2'!AU15 -> 0 | BR33: ='G2'!AV15 -> 0 | BS33: ='G2'!AW15 -> 0 | BT33: ='G2'!AX15 -> 0 | BU33: ='G2'!AY15 -> 0 | BV33: ='G2'!AZ15 -> 0 | BW33: ='G2'!BA15 -> 0 | BX33: ='G2'!BB15 -> 0 | ... CB33: ='G2'!BF15 -> 0
C34: Comunidades ME | D34: 91243650 | E34: =SUM(G34,I34,K34,M34,O34) -> 87841.21 | G34: =SUM(Q34:AB34) -> 0 | I34: =SUM(AD34:AO34) -> 0 | K34: =SUM(AQ34:BB34) -> 0 | M34: =SUM(BD34:BO34) -> 87841.21 | O34: =SUM(BQ34:CB34) -> 0 | AI34: ='G2'!P16 -> 0 | AJ34: ='G2'!Q16 -> 0 | AK34: ='G2'!R16 -> 0 | AL34: ='G2'!S16 -> 0 | AM34: ='G2'!T16 -> 0 | AN34: ='G2'!U16 -> 0 | AO34: ='G2'!V16 -> 0 | AQ34: ='G2'!W16 -> 0 | AR34: ='G2'!X16 -> 0 | AS34: ='G2'!Y16 -> 0 | AT34: ='G2'!Z16 -> 0 | AU34: ='G2'!AA16 -> 0 | AV34: ='G2'!AB16 -> 0 | AW34: ='G2'!AC16 -> 0 | AX34: ='G2'!AD16 -> 0 | ... BB34: ='G2'!AH16 -> 0 | BD34: ='G2'!AI16 -> 20551.325 | BE34: ='G2'!AJ16 -> 0 | BF34: ='G2'!AK16 -> 0 | BG34: ='G2'!AL16 -> 0 | BH34: ='G2'!AM16 -> 4341.2829 | BI34: ='G2'!AN16 -> 62948.602 | BJ34: ='G2'!AO16 -> 0 | BK34: ='G2'!AP16 -> 0 | ... BO34: ='G2'!AT16 -> 0 | BQ34: ='G2'!AU16 -> 0 | BR34: ='G2'!AV16 -> 0 | BS34: ='G2'!AW16 -> 0 | BT34: ='G2'!AX16 -> 0 | BU34: ='G2'!AY16 -> 0 | BV34: ='G2'!AZ16 -> 0 | BW34: ='G2'!BA16 -> 0 | BX34: ='G2'!BB16 -> 0 | ... CB34: ='G2'!BF16 -> 0
... C36: Contingencia ME | D36: 91243750 | E36: =SUM(G36,I36,K36,M36,O36) -> 137241.79 | G36: =SUM(Q36:AB36) -> 0 | I36: =SUM(AD36:AO36) -> 0 | K36: =SUM(AQ36:BB36) -> 0 | M36: =SUM(BD36:BO36) -> 0 | O36: =SUM(BQ36:CB36) -> 137241.79 | AI36: ='G2'!P18 -> 0 | AJ36: ='G2'!Q18 -> 0 | AK36: ='G2'!R18 -> 0 | AL36: ='G2'!S18 -> 0 | AM36: ='G2'!T18 -> 0 | AN36: ='G2'!U18 -> 0 | AO36: ='G2'!V18 -> 0 | AQ36: ='G2'!W18 -> 0 | AR36: ='G2'!X18 -> 0 | AS36: ='G2'!Y18 -> 0 | AT36: ='G2'!Z18 -> 0 | AU36: ='G2'!AA18 -> 0 | AV36: ='G2'!AB18 -> 0 | AW36: ='G2'!AC18 -> 0 | AX36: ='G2'!AD18 -> 0 | ... BB36: ='G2'!AH18 -> 0 | BD36: ='G2'!AI18 -> 0 | BE36: ='G2'!AJ18 -> 0 | BF36: ='G2'!AK18 -> 0 | BG36: ='G2'!AL18 -> 0 | BH36: ='G2'!AM18 -> 0 | BI36: ='G2'!AN18 -> 0 | BJ36: ='G2'!AO18 -> 0 | BK36: ='G2'!AP18 -> 0 | ... BO36: ='G2'!AT18 -> 0 | BQ36: ='G2'!AU18 -> 0 | BR36: ='G2'!AV18 -> 0 | BS36: ='G2'!AW18 -> 0 | BT36: ='G2'!AX18 -> 137241.79 | BU36: ='G2'!AY18 -> 0 | BV36: ='G2'!AZ18 -> 0 | BW36: ='G2'!BA18 -> 0 | BX36: ='G2'!BB18 -> 0 | ... CB36: ='G2'!BF18 -> 0
C37: Fee MN | D37: 91243910 | E37: =SUM(G37,I37,K37,M37,O37) -> 100126.13 | G37: =SUM(Q37:AB37) -> 0 | I37: =SUM(AD37:AO37) -> 9249.2833 | K37: =SUM(AQ37:BB37) -> 34606.099 | M37: =SUM(BD37:BO37) -> 36851.884 | O37: =SUM(BQ37:CB37) -> 19418.868 | AI37: ='G2'!P20+'G2'!P21 -> 150.01162 | AJ37: ='G2'!Q20+'G2'!Q21 -> 927.89061 | AK37: ='G2'!R20+'G2'!R21 -> 1529.3421 | AL37: ='G2'!S20+'G2'!S21 -> 1206.6878 | AM37: ='G2'!T20+'G2'!T21 -> 1927.6101 | AN37: ='G2'!U20+'G2'!U21 -> 1419.6506 | AO37: ='G2'!V20+'G2'!V21 -> 2088.0904 | AQ37: ='G2'!W20+'G2'!W21 -> 1216.4791 | AR37: ='G2'!X20+'G2'!X21 -> 4157.6221 | AS37: ='G2'!Y20+'G2'!Y21 -> 3088.5193 | AT37: ='G2'!Z20+'G2'!Z21 -> 5075.98 | AU37: ='G2'!AA20+'G2'!AA21 -> 2713.5073 | AV37: ='G2'!AB20+'G2'!AB21 -> 4501.4779 | AW37: ='G2'!AC20+'G2'!AC21 -> 2713.5073 | AX37: ='G2'!AD20+'G2'!AD21 -> 2232.1812 | ... BB37: ='G2'!AH20+'G2'!AH21 -> 2219.5119 | BD37: ='G2'!AI20+'G2'!AI21 -> 3333.9751 | BE37: ='G2'!AJ20+'G2'!AJ21 -> 2333.1532 | BF37: ='G2'!AK20+'G2'!AK21 -> 5866.607 | BG37: ='G2'!AL20+'G2'!AL21 -> 3012.004 | BH37: ='G2'!AM20+'G2'!AM21 -> 2913.1157 | BI37: ='G2'!AN20+'G2'!AN21 -> 5353.4763 | BJ37: ='G2'!AO20+'G2'!AO21 -> 2913.1157 | BK37: ='G2'!AP20+'G2'!AP21 -> 2292.7176 | ... BO37: ='G2'!AT20+'G2'!AT21 -> 2221.4241 | BQ37: ='G2'!AU20+'G2'!AU21 -> 12241.344 | BR37: ='G2'!AV20+'G2'!AV21 -> 2413.9062 | BS37: ='G2'!AW20+'G2'!AW21 -> 2880.5472 | BT37: ='G2'!AX20+'G2'!AX21 -> 1883.0702 | BU37: ='G2'!AY19 -> 0 | BV37: ='G2'!AZ19 -> 0 | BW37: ='G2'!BA19 -> 0 | BX37: ='G2'!BB19 -> 0 | BY37: ='G2'!BC19 -> 0 | BZ37: ='G2'!BD19 -> 0 | CA37: ='G2'!BE19 -> 0 | CB37: ='G2'!BF19 -> 0
E40: =E4 -> 6744916.6 | G40: =G4 -> 228189.96 | I40: =I4 -> 476667.45 | K40: =K4 -> 1674600.4 | M40: =M4 -> 2034249.7 | O40: =O4 -> 2331209
C44: MN | E44: =+G44+I44+K44+M44+O44 -> 1863094.6 | G44: =+G37+G28+G23+G7+G21+G12 -> 157307.98 | I44: =+I37+I28+I23+I7+I21+I12+I19 -> 403384.93 | K44: =+K7+K12+K21+K23+K28+K31+K35+K37 -> 518252.16 | M44: =+M7+M12+M21+M23+M28+M31+M35+M37 -> 553890.14 | O44: =+O7+O12+O21+O23+O28+O31+O35+O37 -> 230259.4
C45: ME | E45: =+G45+I45+K45+M45+O45 -> 4864634.7 | G45: =+G36+G32+G30+G29+G24+G20+G10+G34+G13+G8 -> 61925.39 | I45: =+I36+I32+I30+I29+I24+I20+I10+I34+I13+I8 -> 65051.892 | K45: =+K8+K13+K20+K24+K25+K26+K27+K29+K30+K32+K33+K34+K36 -> 1156348.2 | M45: =+M8+M13+M20+M24+M25+M26+M27+M29+M30+M32+M33+M34+M36 -> 1480359.6 | O45: =+O8+O13+O20+O24+O25+O26+O27+O29+O30+O32+O33+O34+O36 -> 2100949.6
E46: =+E44+E45 -> 6727729.4 | G46: =+G44+G45 -> 219233.37 | I46: =+I44+I45 -> 468436.82 | K46: =+K44+K45 -> 1674600.4 | M46: =+M44+M45 -> 2034249.7 | O46: =+O44+O45 -> 2331209

Sheet Hoja4
A1: PROGRAMA | D1: 2024 | F1: 2025 | L1: 2024 | M1: REAL | N1: 2025
D2: TOTAL AÑO | F2: TOTAL AÑO | L2: TOTAL AÑO | N2: TOTAL AÑO | P2: DIFERENCIA
A3: Exploración Internacional Otros Países | D3: 226681.02 | F3: 1389013.9 | I3: Exploración Internacional Otros Países | L3: 226879.95 | N3: 414531.47 | P3: =N3-F3 -> -974482.45
A4: Metalotectos de Interés Item I | D4: 226681.02 | F4: 634159.56 | I4: Metalotectos de Interés Item I | L4: 226879.95 | N4: 127714.39 | P4: =N4-F4 -> -506445.17
A5: Geología MN | B5: 91243110 | D5: 113532.73 | F5: 112091.08 | I5: Geología MN | J5: 91243110 | L5: 114687.36 | N5: 144019.86 | P5: =N5-F5 -> 31928.78
A6: Geología ME | B6: 91243120 | D6: 59999.071 | F6: 477383.66 | I6: Geología ME | J6: 91243120 | L6: 59933.249 | N6: 11188.156 | P6: =N6-F6 -> -466195.51
A7: Geoquímica ME | B7: 91243220 | D7: 0 | F7: 0 | I7: Geoquímica ME | J7: 91243220 | L7: 0 | N7: 0 | P7: =N7-F7 -> 0
A8: Geofísica ME | B8: 91243310 | D8: 0 | F8: 0 | I8: Geofísica ME | J8: 91243310 | L8: 0 | N8: 0 | P8: =N8-F8 -> 0
A9: Sondajes ME | B9: 91243510 | D9: 0 | F9: 0 | I9: Sondajes ME | J9: 91243510 | L9: 0 | N9: 0 | P9: =N9-F9 -> 0
A10: Logística MN | B10: 91243520 | D10: 44418.162 | F10: 1260.515 | I10: Logística MN | J10: 91243520 | L10: 34704.318 | N10: -33871.417 | P10: =N10-F10 -> -35131.932
A11: Logística ME | B11: 91243530 | D11: 173.63333 | F11: 0 | I11: Logística ME | J11: 91243530 | L11: 174.72702 | N11: -1784.7809 | P11: =N11-F11 -> -1784.7809
A12: Propiedad Minera ME | B12: 91243610 | D12: 0 | F12: 0 | I12: Propiedad Minera ME | J12: 91243610 | L12: 0 | N12: 0 | P12: =N12-F12 -> 0
A13: Medio Ambiente MN | B13: 91243620 | D13: 0 | F13: 0 | I13: Medio Ambiente MN | J13: 91243620 | L13: 8956.5833 | N13: 0 | P13: =N13-F13 -> 0
A14: Medio Ambiente ME | B14: 91243630 | D14: 0 | F14: 0 | I14: Medio Ambiente ME | J14: 91243630 | L14: 0 | N14: 0 | P14: =N14-F14 -> 0
A15: Seguridad ME | B15: 91243640 | D15: 0 | F15: 0 | I15: Seguridad ME | J15: 91243640 | L15: 0 | N15: 0 | P15: =N15-F15 -> 0
A16: Comunidades ME | B16: 91243650 | D16: 0 | F16: 0 | I16: Comunidades ME | J16: 91243650 | L16: 0 | N16: 0 | P16: =N16-F16 -> 0
... A19: Fee MN | B19: 91243910 | D19: 8557.4204 | F19: 18774.25 | I19: Fee MN | J19: 91243910 | L19: 8423.7101 | N19: 5150.254 | P19: =N19-F19 -> -13623.996
A20: Metalotectos de Interés Item II | D20: 0 | F20: 754854.36 | I20: Metalotectos de Interés Item II | L20: 0 | N20: 286817.08 | P20: =N20-F20 -> -468037.28
A21: Geología MN | B21: 91243110 | D21: 0 | F21: 251050.27 | I21: Geología MN | J21: 91243110 | L21: 0 | N21: 166903.83 | P21: =N21-F21 -> -84146.434
A22: Geología ME | B22: 91243120 | D22: 0 | F22: 165014.41 | I22: Geología ME | J22: 91243120 | L22: 0 | N22: 52837.154 | P22: =N22-F22 -> -112177.26
A23: Geoquímica ME | B23: 91243220 | D23: 0 | F23: 0 | I23: Geoquímica ME | J23: 91243220 | L23: 0 | N23: 0 | P23: =N23-F23 -> 0
A24: Geofísica ME | B24: 91243310 | D24: 0 | F24: 0 | I24: Geofísica ME | J24: 91243310 | L24: 0 | N24: 0 | P24: =N24-F24 -> 0
A25: Sondajes ME | B25: 91243510 | D25: 0 | F25: 0 | I25: Sondajes ME | J25: 91243510 | L25: 0 | N25: 0 | P25: =N25-F25 -> 0
A26: Logística MN | B26: 91243520 | D26: 0 | F26: 192194.54 | I26: Logística MN | J26: 91243520 | L26: 0 | N26: 57803.922 | P26: =N26-F26 -> -134390.62
A27: Logística ME | B27: 91243530 | D27: 0 | F27: 0 | I27: Logística ME | J27: 91243530 | L27: 0 | N27: 0 | P27: =N27-F27 -> 0
A28: Propiedad Minera ME | B28: 91243610 | D28: 0 | F28: 63954.498 | I28: Propiedad Minera ME | J28: 91243610 | L28: 0 | N28: 0 | P28: =N28-F28 -> -63954.498
A29: Medio Ambiente MN | B29: 91243620 | D29: 0 | F29: 0 | I29: Medio Ambiente MN | J29: 91243620 | L29: 0 | N29: 0 | P29: =N29-F29 -> 0
A30: Medio Ambiente ME | B30: 91243630 | D30: 0 | F30: 0 | I30: Medio Ambiente ME | J30: 91243630 | L30: 0 | N30: 0 | P30: =N30-F30 -> 0
A31: Seguridad ME | B31: 91243640 | D31: 0 | F31: 0 | I31: Seguridad ME | J31: 91243640 | L31: 0 | N31: 0 | P31: =N31-F31 -> 0
A32: Comunidades ME | B32: 91243650 | D32: 0 | F32: 19766.69 | I32: Comunidades ME | J32: 91243650 | L32: 0 | N32: 0 | P32: =N32-F32 -> -19766.69
... A35: Fee MN | B35: 91243910 | D35: 0 | F35: 22227.918 | I35: Fee MN | J35: 91243910 | L35: 0 | N35: 9272.169 | P35: =N35-F35 -> -12955.749

Sheet REPORTE GEX
D2: GASTO MENSUAL PESOS CHILENOS $ | R2: GASTO MENSUAL DOLARES $ (dólar corriente) | AF2: GASTO MENSUAL MILES DE DOLARES BASE $
D4: 46053 | E4: 46081 | F4: 46112 | G4: 46142 | H4: 46173 | I4: 46203 | J4: 46234 | K4: 46265 | L4: 46295 | M4: 46326 | N4: 46356 | O4: 46387 | P4: TOTAL PESOS $ | R4: 44927 | S4: 44958 | T4: 44986 | U4: 45017 | V4: 45047 | W4: 45078 | X4: 45108 | Y4: 45139 | Z4: 45170 | AA4: 45200 | AB4: 45231 | AC4: 45261 | AD4: TOTAL US$ | AF4: 44957 | AG4: Incurrido | AH4: Gasto Sap | AI4: Total Enero | AJ4: Ptto Ene | AK4: Cumpl. | AM4: 44985 | AN4: Incurrido | AO4: Gasto SAP | AP4: Total Febrero | AQ4: Ptto Feb | AR4: Cumpl. | AT4: 45016 | AU4: Incurrido | AV4: Gasto SAP | AW4: Total Marzo | AX4: Ptto Mar | AY4: Cumpl. | BA4: 45046 | BB4: Incurrido | BC4: Gasto SAP | BD4: Total Abril | BE4: Ptto Abr | BF4: Cumpl. | BH4: 45077 | BI4: Incurrido | BJ4: Gasto SAP | BK4: Total Mayo | BL4: Ptto May | BM4: Cumpl. | BO4: 45107 | BP4: Incurrido | BQ4: Gasto SAP | BR4: Total Junio | BS4: Ptto Jun | BT4: Cumpl. | BV4: 45137 | BW4: Incurrido | BX4: Gasto SAP | BY4: Total Julio | BZ4: Ptto Jul | CA4: Cumpl. | CC4: 45169 | CD4: Incurrido | CE4: Gasto SAP | CF4: Total Agosto | CG4: Ptto Ago | CH4: Cumpl. | CJ4: 45199 | CK4: Incurrido | CL4: Gasto SAP | CM4: Total Septiembre | CN4: Ptto Sept | CO4: Cumpl. | CQ4: 45230 | CR4: Incurrido | CS4: Gasto SAP | CT4: Total Octubre | CU4: Ptto Oct | CV4: Cumpl. | CX4: 45260 | CY4: Incurrido | CZ4: Gasto SAP | DA4: Total Noviembre | DB4: Ptto Nov | DC4: Cumpl. | DE4: 45291 | DF4: Incurrido | DG4: Gasto SAP | DH4: Total Diciembre | DI4: Ptto Dic | DJ4: Cumpl.
B5: APIS 20224 | R5: =826.34*1000 -> 826340 | S5: =798.26*1000 -> 798260 | T5: =809.5*1000 -> 809500 | U5: =809.5*1000 -> 809500 | V5: 712260 | W5: 726540 | X5: 750440 | Y5: 953710 | Z5: 783630 | AA5: 813950 | AB5: 812620 | AC5: 849120 | AF5: =#REF! -> #REF! | AG5: =#REF! -> #REF! | AK5: % | AM5: =#REF! -> #REF! | AN5: =#REF! -> #REF! | AR5: % | AT5: =#REF! -> #REF! | AU5: =#REF! -> #REF! | AY5: % | BA5: =#REF! -> #REF! | BB5: =#REF! -> #REF! | BF5: % | BM5: % | BT5: % | CA5: % | CH5: % | CO5: % | CV5: % | CX5: 1 | DC5: % | DE5: 1 | DJ5: %
B6: EXPLORACIÓN INTERNACIONAL OTROS PAISES | D6: =+D7+D28 -> 45953008 | E6: =+E7+E28 -> 0 | F6: =+F7+F28 -> 0 | G6: =+G7+G28 -> 0 | H6: =+H7+H28 -> 0 | I6: =+I7+I28 -> 0 | J6: =+J7+J28 -> 0 | K6: =+K7+K28 -> 0 | ... O6: =+O7+O28 -> 0 | P6: =SUM(D6:O6) -> 45953008 | R6: =+R7+R52 -> 0 | S6: =+S7+S52 -> 0 | T6: =+T7+T52 -> 0 | U6: =+U7+U52 -> 0 | V6: =+V7+V52 -> 0 | W6: =+W7+W52 -> 0 | X6: =+X7+X52 -> 0 | Y6: =+Y7+Y52 -> 0 | ... AC6: =+AC7+AC52 -> 0 | AD6: =SUM(R6:AC6) -> 0 | AF6: =+AF7 -> #REF! | AG6: =+AG7 -> #REF! | AH6: =+AH7 -> #REF! | AI6: =+AI7 -> #REF! | AJ6: =+AJ7 -> #REF! | AK6: =+AK7 -> #REF! | AM6: =+AM7 -> #REF! | AN6: =+AN7 -> #REF! | AO6: =+AO7 -> #REF! | AP6: =+AP7 -> #REF! | AQ6: =+AQ7 -> #REF! | AR6: =+AR7 -> #REF! | AT6: =+AT7 -> #REF! | AU6: =+AU7 -> #REF! | AV6: =+AV7 -> #REF! | AW6: =+AW7 -> #REF! | AX6: =+AX7 -> #REF! | AY6: =+AY7 -> #REF! | BA6: =+BA7 -> #REF! | BB6: =+BB7 -> #REF! | BC6: =+BC7 -> #REF! | BD6: =+BD7 -> #REF! | BE6: =+BE7 -> #REF! | BF6: =+BF7 -> #REF! | BH6: =+BH7 -> #REF! | BI6: =+BI7 -> #REF! | BJ6: =+BJ7 -> #REF! | BK6: =+BK7 -> #REF! | BL6: =+BL7 -> #REF! | BM6: =+BM7 -> #REF! | BO6: =+BO7 -> #REF! | BP6: =+BP7 -> #REF! | BQ6: =+BQ7 -> #REF! | BR6: =+BR7 -> #REF! | BS6: =+BS7 -> #REF! | BT6: =+BT7 -> #REF! | BV6: =+BV7 -> #REF! | BW6: =+BW7 -> #REF! | BX6: =+BX7 -> #REF! | BY6: =+BY7 -> #REF! | BZ6: =+BZ7 -> #REF! | CA6: =+CA7 -> #REF! | CC6: =+CC7 -> #REF! | CD6: =+CD7 -> #REF! | CE6: =+CE7 -> #REF! | CF6: =+CF7 -> #REF! | CG6: =+CG7 -> #REF! | CH6: =+CH7 -> #REF! | CJ6: =+CJ7 -> #REF! | CK6: =+CK7 -> #REF! | CL6: =+CL7 -> #REF! | CM6: =+CM7 -> #REF! | CN6: =+CN7 -> #REF! | CO6: =+CO7 -> #REF! | CQ6: =+CQ7 -> #REF! | CR6: =+CR7 -> #REF! | CS6: =+CS7 -> #REF! | CT6: =+CT7 -> #REF! | CU6: =+CU7 -> #REF! | CV6: =+CV7 -> #REF! | CX6: =+CX7 -> #REF! | CY6: =+CY7 -> #REF! | CZ6: =+CZ7 -> #REF! | DA6: =+DA7 -> #REF! | DB6: =+DB7 -> #REF! | DC6: =+DC7 -> #REF! | DE6: =+DE7 -> #REF! | DF6: =+DF7 -> #REF! | DG6: =+DG7 -> #REF! | DH6: =+DH7 -> #REF! | DI6: =+DI7 -> #REF! | DJ6: =+DJ7 -> #REF!
B7: Item I | D7: =+D8+D23 -> 0 | E7: =+E8+E23 -> 0 | F7: =+F8+F23 -> 0 | G7: =+G8+G23 -> 0 | H7: =+H8+H23 -> 0 | I7: =+I8+I23 -> 0 | J7: =+J8+J23 -> 0 | K7: =+K8+K23 -> 0 | ... P7: =+P8+P23 -> 0 | R7: =+R8+R23 -> 0 | S7: =+S8+S23 -> 0 | T7: =+T8+T23 -> 0 | U7: =+U8+U23 -> 0 | V7: =+V8+V23 -> 0 | W7: =+W8+W23 -> 0 | X7: =+X8+X23 -> 0 | Y7: =+Y8+Y23 -> 0 | ... AC7: =+AC8+AC23 -> 0 | AD7: =+AD8+#REF!+AD23+#REF!+#REF!+#REF! -> #REF! | AF7: =+AF8+#REF!+#REF!+AF23+#REF!+#REF! -> #REF! | AG7: =+AG8+#REF!+#REF!+AG23+#REF!+#REF! -> #REF! | AH7: =+AH8+#REF!+#REF!+AH23+#REF!+#REF! -> #REF! | AI7: =+AI8+#REF!+#REF!+AI23+#REF!+#REF! -> #REF! | AJ7: =+AJ8+#REF!+#REF!+AJ23+#REF!+#REF! -> #REF! | AK7: =+AK8+#REF!+#REF!+AK23+#REF!+#REF! -> #REF! | AM7: =+AM8+#REF!+#REF!+AM23+#REF!+#REF! -> #REF! | AN7: =+AN8+#REF!+#REF!+AN23+#REF!+#REF! -> #REF! | AO7: =+AO8+#REF!+#REF!+AO23+#REF!+#REF! -> #REF! | AP7: =+AP8+#REF!+#REF!+AP23+#REF!+#REF! -> #REF! | AQ7: =+AQ8+#REF!+#REF!+AQ23+#REF!+#REF! -> #REF! | AR7: =+AR8+#REF!+#REF!+AR23+#REF!+#REF! -> #REF! | AT7: =+AT8+#REF!+#REF!+AT23+#REF!+#REF! -> #REF! | AU7: =+AU8+#REF!+#REF!+AU23+#REF!+#REF! -> #REF! | AV7: =+AV8+#REF!+#REF!+AV23+#REF!+#REF! -> #REF! | AW7: =+AW8+#REF!+#REF!+AW23+#REF!+#REF! -> #REF! | AX7: =+AX8+#REF!+#REF!+AX23+#REF!+#REF! -> #REF! | AY7: =+AY8+#REF!+#REF!+AY23+#REF!+#REF! -> #REF! | BA7: =+BA8+#REF!+#REF!+BA23+#REF!+#REF! -> #REF! | BB7: =+BB8+#REF!+#REF!+BB23+#REF!+#REF! -> #REF! | BC7: =+BC8+#REF!+#REF!+BC23+#REF!+#REF! -> #REF! | BD7: =+BD8+#REF!+#REF!+BD23+#REF!+#REF! -> #REF! | BE7: =+BE8+#REF!+#REF!+BE23+#REF!+#REF! -> #REF! | BF7: =+BF8+#REF!+#REF!+BF23+#REF!+#REF! -> #REF! | BH7: =+BH8+#REF!+#REF!+BH23+#REF!+#REF! -> #REF! | BI7: =+BI8+#REF!+#REF!+BI23+#REF!+#REF! -> #REF! | BJ7: =+BJ8+#REF!+#REF!+BJ23+#REF!+#REF! -> #REF! | BK7: =+BK8+#REF!+#REF!+BK23+#REF!+#REF! -> #REF! | BL7: =+BL8+#REF!+#REF!+BL23+#REF!+#REF! -> #REF! | BM7: =+BM8+#REF!+#REF!+BM23+#REF!+#REF! -> #REF! | BO7: =+BO8+#REF!+#REF!+BO23+#REF!+#REF! -> #REF! | BP7: =+BP8+#REF!+#REF!+BP23+#REF!+#REF! -> #REF! | BQ7: =+BQ8+#REF!+#REF!+BQ23+#REF!+#REF! -> #REF! | BR7: =+BR8+#REF!+#REF!+BR23+#REF!+#REF! -> #REF! | BS7: =+BS8+#REF!+#REF!+BS23+#REF!+#REF! -> #REF! | BT7: =+BT8+#REF!+#REF!+BT23+#REF!+#REF! -> #REF! | BV7: =+BV8+#REF!+#REF!+BV23+#REF!+#REF! -> #REF! | BW7: =+BW8+#REF!+#REF!+BW23+#REF!+#REF! -> #REF! | BX7: =+BX8+#REF!+#REF!+BX23+#REF!+#REF! -> #REF! | BY7: =+BY8+#REF!+#REF!+BY23+#REF!+#REF! -> #REF! | BZ7: =+BZ8+#REF!+#REF!+BZ23+#REF!+#REF! -> #REF! | CA7: =+CA8+#REF!+#REF!+CA23+#REF!+#REF! -> #REF! | CC7: =+CC8+#REF!+#REF!+CC23+#REF!+#REF! -> #REF! | CD7: =+CD8+#REF!+#REF!+CD23+#REF!+#REF! -> #REF! | CE7: =+CE8+#REF!+#REF!+CE23+#REF!+#REF! -> #REF! | CF7: =+CF8+#REF!+#REF!+CF23+#REF!+#REF! -> #REF! | CG7: =+CG8+#REF!+#REF!+CG23+#REF!+#REF! -> #REF! | CH7: =+CH8+#REF!+#REF!+CH23+#REF!+#REF! -> #REF! | CJ7: =+CJ8+#REF!+#REF!+CJ23+#REF!+#REF! -> #REF! | CK7: =+CK8+#REF!+#REF!+CK23+#REF!+#REF! -> #REF! | CL7: =+CL8+#REF!+#REF!+CL23+#REF!+#REF! -> #REF! | CM7: =+CM8+#REF!+#REF!+CM23+#REF!+#REF! -> #REF! | CN7: =+CN8+#REF!+#REF!+CN23+#REF!+#REF! -> #REF! | CO7: =+CO8+#REF!+#REF!+CO23+#REF!+#REF! -> #REF! | CQ7: =+CQ8+#REF!+#REF!+CQ23+#REF!+#REF! -> #REF! | CR7: =+CR8+#REF!+#REF!+CR23+#REF!+#REF! -> #REF! | CS7: =+CS8+#REF!+#REF!+CS23+#REF!+#REF! -> #REF! | CT7: =+CT8+#REF!+#REF!+CT23+#REF!+#REF! -> #REF! | CU7: =+CU8+#REF!+#REF!+CU23+#REF!+#REF! -> #REF! | CV7: =+CV8+#REF!+#REF!+CV23+#REF!+#REF! -> #REF! | CX7: =+CX8+#REF!+#REF!+CX23+#REF!+#REF! -> #REF! | CY7: =+CY8+#REF!+#REF!+CY23+#REF!+#REF! -> #REF! | CZ7: =+CZ8+#REF!+#REF!+CZ23+#REF!+#REF! -> #REF! | DA7: =+DA8+#REF!+#REF!+DA23+#REF!+#REF! -> #REF! | DB7: =+DB8+#REF!+#REF!+DB23+#REF!+#REF! -> #REF! | DC7: =+DC8+#REF!+#REF!+DC23+#REF!+#REF! -> #REF! | DE7: =+DE8+#REF!+#REF!+DE23+#REF!+#REF! -> #REF! | DF7: =+DF8+#REF!+#REF!+DF23+#REF!+#REF! -> #REF! | DG7: =+DG8+#REF!+#REF!+DG23+#REF!+#REF! -> #REF! | DH7: =+DH8+#REF!+#REF!+DH23+#REF!+#REF! -> #REF! | DI7: =+DI8+#REF!+#REF!+DI23+#REF!+#REF! -> #REF! | DJ7: =+DJ8+#REF!+#REF!+DJ23+#REF!+#REF! -> #REF!
A8: 912431 | B8: GEOLOGÍA | D8: =SUM(D9:D12) -> 0 | E8: =SUM(E9:E12) -> 0 | F8: =SUM(F9:F22) -> 0 | G8: =SUM(G9:G22) -> 0 | H8: =SUM(H9:H22) -> 0 | I8: =SUM(I9:I22) -> 0 | J8: =SUM(J9:J22) -> 0 | K8: =SUM(K9:K22) -> 0 | L8: =SUM(L9:L22) -> 0 | M8: =SUM(M9:M22) -> 0 | ... O8: =SUM(O9:O22) -> 0 | P8: =SUM(P9:P12) -> 0 | R8: =SUM(R9:R12) -> 0 | S8: =SUM(S9:S12) -> 0 | T8: =SUM(T9:T12) -> 0 | U8: =SUM(U9:U12) -> 0 | V8: =SUM(V9:V12) -> 0 | W8: =SUM(W9:W12) -> 0 | X8: =SUM(X9:X12) -> 0 | Y8: =SUM(Y9:Y12) -> 0 | ... AD8: =SUM(AD9:AD12) -> 0 | AF8: =SUM(AF9:AF12) -> #REF! | AG8: =SUM(AG9:AG12) -> 0 | AH8: =SUM(AH9:AH12) -> 0 | AI8: =SUM(AI9:AI12) -> #REF! | AJ8: =SUM(AJ9:AJ12) -> 0 | AK8: =SUM(AK9:AK12) -> 0 | AM8: =SUM(AM9:AM12) -> #REF! | AN8: =SUM(AN9:AN12) -> 0 | AO8: =SUM(AO9:AO12) -> 0 | AP8: =SUM(AP9:AP12) -> #REF! | AQ8: =SUM(AQ9:AQ12) -> 0 | AR8: =SUM(AR9:AR12) -> 0 | AT8: =SUM(AT9:AT12) -> #REF! | AU8: =SUM(AU9:AU12) -> 0 | AV8: =SUM(AV9:AV12) -> 0 | AW8: =SUM(AW9:AW12) -> #REF! | AX8: =SUM(AX9:AX12) -> 0 | AY8: =SUM(AY9:AY12) -> 0 | BA8: =SUM(BA9:BA12) -> #REF! | BB8: =SUM(BB9:BB12) -> 0 | BC8: =SUM(BC9:BC12) -> 0 | BD8: =SUM(BD9:BD12) -> #REF! | BE8: =SUM(BE9:BE12) -> 0 | BF8: =SUM(BF9:BF12) -> 0 | BH8: =SUM(BH9:BH12) -> 0 | BI8: =SUM(BI9:BI12) -> 0 | BJ8: =SUM(BJ9:BJ12) -> 0 | BK8: =SUM(BK9:BK12) -> 0 | BL8: =SUM(BL9:BL12) -> 0 | BM8: =SUM(BM9:BM12) -> 0 | BO8: =SUM(BO9:BO12) -> 0 | BP8: =SUM(BP9:BP12) -> 0 | BQ8: =SUM(BQ9:BQ12) -> 0 | BR8: =SUM(BR9:BR12) -> 0 | BS8: =SUM(BS9:BS12) -> 0 | BT8: =SUM(BT9:BT12) -> 0 | BV8: =SUM(BV9:BV12) -> 0 | BW8: =SUM(BW9:BW12) -> 0 | BX8: =SUM(BX9:BX12) -> 0 | BY8: =SUM(BY9:BY12) -> 0 | BZ8: =SUM(BZ9:BZ12) -> 0 | CA8: =SUM(CA9:CA12) -> 0 | CC8: =SUM(CC9:CC12) -> 0 | CD8: =SUM(CD9:CD12) -> 0 | CE8: =SUM(CE9:CE12) -> 0 | CF8: =SUM(CF9:CF12) -> 0 | CG8: =SUM(CG9:CG12) -> 0 | CH8: =SUM(CH9:CH12) -> 0 | CJ8: =SUM(CJ9:CJ12) -> 0 | CK8: =SUM(CK9:CK12) -> 0 | CL8: =SUM(CL9:CL12) -> 0 | CM8: =SUM(CM9:CM12) -> 0 | CN8: =SUM(CN9:CN12) -> 0 | CO8: =SUM(CO9:CO12) -> 0 | CQ8: =SUM(CQ9:CQ12) -> 0 | CR8: =SUM(CR9:CR12) -> 0 | CS8: =SUM(CS9:CS12) -> 0 | CT8: =SUM(CT9:CT12) -> 0 | CU8: =SUM(CU9:CU12) -> 0 | CV8: =SUM(CV9:CV12) -> 0 | CX8: =SUM(CX9:CX12) -> 0 | CY8: =SUM(CY9:CY12) -> 0 | CZ8: =SUM(CZ9:CZ12) -> 0 | DA8: =SUM(DA9:DA12) -> 0 | DB8: =SUM(DB9:DB12) -> 0 | DC8: =SUM(DC9:DC12) -> 0 | DE8: =SUM(DE9:DE12) -> 0 | DF8: =SUM(DF9:DF12) -> 0 | DG8: =SUM(DG9:DG12) -> 0 | DH8: =SUM(DH9:DH12) -> 0 | DI8: =SUM(DI9:DI12) -> 0 | DJ8: =SUM(DJ9:DJ12) -> 0
A9: 91243110 | B9: Geología MN | C9: 9076860 0010 | P9: =SUM(D9:O9) -> 0 | R9: =+D9/R$5 -> 0 | S9: =+E9/S$5 -> 0 | T9: =+F9/T$5 -> 0 | U9: =+G9/U$5 -> 0 | V9: =+H9/V$5 -> 0 | W9: =+I9/W$5 -> 0 | X9: =+J9/X$5 -> 0 | Y9: =+K9/Y$5 -> 0 | ... AC9: =+O9/AC$5 -> 0 | AF9: =+R9*AF$5 -> #REF! | AI9: =SUM(AF9:AH9) -> #REF! | AK9: =+IFERROR(AI9/AJ9,0) -> 0 | AM9: =+S9*AM$5 -> #REF! | AP9: =SUM(AM9:AO9) -> #REF! | AR9: =+IFERROR(AP9/AQ9,0) -> 0 | AT9: =+T9*AT$5 -> #REF! | AW9: =SUM(AT9:AV9) -> #REF! | AY9: =+IFERROR(AW9/AX9,0) -> 0 | BA9: =+U9*$BA$5 -> #REF! | BD9: =SUM(BA9:BC9) -> #REF! | BF9: =+IFERROR(BD9/BE9,0) -> 0 | BH9: =+V9*$BH$5 -> 0 | BK9: =SUM(BH9:BJ9) -> 0 | BM9: =+IFERROR(BK9/BL9,0) -> 0 | BR9: =SUM(BO9:BQ9) -> 0 | BT9: =+IFERROR(BR9/BS9,0) -> 0 | BV9: =+X9*$BV$5 -> 0 | BY9: =SUM(BV9:BX9) -> 0 | CA9: =+IFERROR(BY9/BZ9,0) -> 0 | CC9: =+Y9*$CC$5 -> 0 | CF9: =SUM(CC9:CE9) -> 0 | CH9: =+IFERROR(CF9/CG9,0) -> 0 | CJ9: =+Z9*$CJ$5 -> 0 | CM9: =SUM(CJ9:CL9) -> 0 | CO9: =+IFERROR(CM9/CN9,0) -> 0 | CQ9: =+AA9*$CQ$5 -> 0 | CT9: =SUM(CQ9:CS9) -> 0 | CV9: =+IFERROR(CT9/CU9,0) -> 0 | CX9: =+AB9*$CX$5 -> 0 | DA9: =SUM(CX9:CZ9) -> 0 | DC9: =+IFERROR(DA9/DB9,0) -> 0 | DE9: =+AC9*$DE$5 -> 0 | DH9: =SUM(DE9:DG9) -> 0 | DJ9: =+IFERROR(DH9/DI9,0) -> 0
A10: 91243120 | B10: Geología ME | C10: 9076860 0020 | P10: =SUM(D10:O10) -> 0 | R10: =+D10/R$5 -> 0 | S10: =+E10/S$5 -> 0 | T10: =+F10/T$5 -> 0 | U10: =+G10/U$5 -> 0 | V10: =+H10/V$5 -> 0 | W10: =+I10/W$5 -> 0 | X10: =+J10/X$5 -> 0 | Y10: =+K10/Y$5 -> 0 | ... AC10: =+O10/AC$5 -> 0 | AF10: =+R10*AF$5 -> #REF! | AI10: =SUM(AF10:AH10) -> #REF! | AK10: =+IFERROR(AI10/AJ10,0) -> 0 | AM10: =+S10*AM$5 -> #REF! | AP10: =SUM(AM10:AO10) -> #REF! | AR10: =+IFERROR(AP10/AQ10,0) -> 0 | AT10: =+T10*AT$5 -> #REF! | AW10: =SUM(AT10:AV10) -> #REF! | AY10: =+IFERROR(AW10/AX10,0) -> 0 | BA10: =+U10*$BA$5 -> #REF! | BD10: =SUM(BA10:BC10) -> #REF! | BF10: =+IFERROR(BD10/BE10,0) -> 0 | BH10: =+V10*$BH$5 -> 0 | BK10: =SUM(BH10:BJ10) -> 0 | BM10: =+IFERROR(BK10/BL10,0) -> 0 | BR10: =SUM(BO10:BQ10) -> 0 | BT10: =+IFERROR(BR10/BS10,0) -> 0 | BV10: =+X10*$BV$5 -> 0 | BY10: =SUM(BV10:BX10) -> 0 | CA10: =+IFERROR(BY10/BZ10,0) -> 0 | CC10: =+Y10*$CC$5 -> 0 | CF10: =SUM(CC10:CE10) -> 0 | CH10: =+IFERROR(CF10/CG10,0) -> 0 | CJ10: =+Z10*$CJ$5 -> 0 | CM10: =SUM(CJ10:CL10) -> 0 | CO10: =+IFERROR(CM10/CN10,0) -> 0 | CQ10: =+AA10*$CQ$5 -> 0 | CT10: =SUM(CQ10:CS10) -> 0 | CV10: =+IFERROR(CT10/CU10,0) -> 0 | CX10: =+AB10*$CX$5 -> 0 | DA10: =SUM(CX10:CZ10) -> 0 | DC10: =+IFERROR(DA10/DB10,0) -> 0 | DE10: =+AC10*$DE$5 -> 0 | DH10: =SUM(DE10:DG10) -> 0 | DJ10: =+IFERROR(DH10/DI10,0) -> 0
A11: 91243220 | B11: Geoquímica ME | C11: 9076860 0030 | P11: =SUM(D11:O11) -> 0 | R11: =+D11/R$5 -> 0 | S11: =+E11/S$5 -> 0 | T11: =+F11/T$5 -> 0 | U11: =+G11/U$5 -> 0 | V11: =+H11/V$5 -> 0 | W11: =+I11/W$5 -> 0 | X11: =+J11/X$5 -> 0 | Y11: =+K11/Y$5 -> 0 | ... AC11: =+O11/AC$5 -> 0 | AF11: =+R11*AF$5 -> #REF! | AI11: =SUM(AF11:AH11) -> #REF! | AK11: =+IFERROR(AI11/AJ11,0) -> 0 | AM11: =+S11*AM$5 -> #REF! | AP11: =SUM(AM11:AO11) -> #REF! | AR11: =+IFERROR(AP11/AQ11,0) -> 0 | AT11: =+T11*AT$5 -> #REF! | AW11: =SUM(AT11:AV11) -> #REF! | AY11: =+IFERROR(AW11/AX11,0) -> 0 | BA11: =+U11*$BA$5 -> #REF! | BD11: =SUM(BA11:BC11) -> #REF! | BF11: =+IFERROR(BD11/BE11,0) -> 0 | BH11: =+V11*$BH$5 -> 0 | BK11: =SUM(BH11:BJ11) -> 0 | BM11: =+IFERROR(BK11/BL11,0) -> 0 | BR11: =SUM(BO11:BQ11) -> 0 | BT11: =+IFERROR(BR11/BS11,0) -> 0 | BV11: =+X11*$BV$5 -> 0 | BY11: =SUM(BV11:BX11) -> 0 | CA11: =+IFERROR(BY11/BZ11,0) -> 0 | CC11: =+Y11*$CC$5 -> 0 | CF11: =SUM(CC11:CE11) -> 0 | CH11: =+IFERROR(CF11/CG11,0) -> 0 | CJ11: =+Z11*$CJ$5 -> 0 | CM11: =SUM(CJ11:CL11) -> 0 | CO11: =+IFERROR(CM11/CN11,0) -> 0 | CQ11: =+AA11*$CQ$5 -> 0 | CT11: =SUM(CQ11:CS11) -> 0 | CV11: =+IFERROR(CT11/CU11,0) -> 0 | CX11: =+AB11*$CX$5 -> 0 | DA11: =SUM(CX11:CZ11) -> 0 | DC11: =+IFERROR(DA11/DB11,0) -> 0 | DE11: =+AC11*$DE$5 -> 0 | DH11: =SUM(DE11:DG11) -> 0 | DJ11: =+IFERROR(DH11/DI11,0) -> 0
A12: 91243310 | B12: Geofísica ME | C12: 9076860 0040 | P12: =SUM(D12:O12) -> 0 | R12: =+D12/R$5 -> 0 | S12: =+E12/S$5 -> 0 | T12: =+F12/T$5 -> 0 | U12: =+G12/U$5 -> 0 | V12: =+H12/V$5 -> 0 | W12: =+I12/W$5 -> 0 | X12: =+J12/X$5 -> 0 | Y12: =+K12/Y$5 -> 0 | ... AC12: =+O12/AC$5 -> 0 | AF12: =+R12*AF$5 -> #REF! | AI12: =SUM(AF12:AH12) -> #REF! | AK12: =+IFERROR(AI12/AJ12,0) -> 0 | AM12: =+S12*AM$5 -> #REF! | AP12: =SUM(AM12:AO12) -> #REF! | AR12: =+IFERROR(AP12/AQ12,0) -> 0 | AT12: =+T12*AT$5 -> #REF! | AW12: =SUM(AT12:AV12) -> #REF! | AY12: =+IFERROR(AW12/AX12,0) -> 0 | BA12: =+U12*$BA$5 -> #REF! | BD12: =SUM(BA12:BC12) -> #REF! | BF12: =+IFERROR(BD12/BE12,0) -> 0 | BH12: =+V12*$BH$5 -> 0 | BK12: =SUM(BH12:BJ12) -> 0 | BM12: =+IFERROR(BK12/BL12,0) -> 0 | BR12: =SUM(BO12:BQ12) -> 0 | BT12: =+IFERROR(BR12/BS12,0) -> 0 | BV12: =+X12*$BV$5 -> 0 | BY12: =SUM(BV12:BX12) -> 0 | CA12: =+IFERROR(BY12/BZ12,0) -> 0 | CC12: =+Y12*$CC$5 -> 0 | CF12: =SUM(CC12:CE12) -> 0 | CH12: =+IFERROR(CF12/CG12,0) -> 0 | CJ12: =+Z12*$CJ$5 -> 0 | CM12: =SUM(CJ12:CL12) -> 0 | CO12: =+IFERROR(CM12/CN12,0) -> 0 | CQ12: =+AA12*$CQ$5 -> 0 | CT12: =SUM(CQ12:CS12) -> 0 | CV12: =+IFERROR(CT12/CU12,0) -> 0 | CX12: =+AB12*$CX$5 -> 0 | DA12: =SUM(CX12:CZ12) -> 0 | DC12: =+IFERROR(DA12/DB12,0) -> 0 | DE12: =+AC12*$DE$5 -> 0 | DH12: =SUM(DE12:DG12) -> 0 | DJ12: =+IFERROR(DH12/DI12,0) -> 0
A13: 91243510 | B13: Sondajes ME | C13: 9076860 0050 | P13: =SUM(D13:O13) -> 0 | R13: =+D13/R$5 -> 0 | S13: =+E13/S$5 -> 0 | T13: =+F13/T$5 -> 0 | U13: =+G13/U$5 -> 0 | V13: =+H13/V$5 -> 0 | W13: =+I13/W$5 -> 0 | X13: =+J13/X$5 -> 0 | Y13: =+K13/Y$5 -> 0 | ... AC13: =+O13/AC$5 -> 0 | AF13: =+R13*AF$5 -> #REF! | AI13: =SUM(AF13:AH13) -> #REF! | AK13: =+IFERROR(AI13/AJ13,0) -> 0 | AM13: =+S13*AM$5 -> #REF! | AP13: =SUM(AM13:AO13) -> #REF! | AR13: =+IFERROR(AP13/AQ13,0) -> 0 | AT13: =+T13*AT$5 -> #REF! | AW13: =SUM(AT13:AV13) -> #REF! | AY13: =+IFERROR(AW13/AX13,0) -> 0 | BA13: =+U13*$BA$5 -> #REF! | BD13: =SUM(BA13:BC13) -> #REF! | BF13: =+IFERROR(BD13/BE13,0) -> 0 | BH13: =+V13*$BH$5 -> 0 | BK13: =SUM(BH13:BJ13) -> 0 | BM13: =+IFERROR(BK13/BL13,0) -> 0 | BR13: =SUM(BO13:BQ13) -> 0 | BT13: =+IFERROR(BR13/BS13,0) -> 0 | BV13: =+X13*$BV$5 -> 0 | BY13: =SUM(BV13:BX13) -> 0 | CA13: =+IFERROR(BY13/BZ13,0) -> 0 | CC13: =+Y13*$CC$5 -> 0 | CF13: =SUM(CC13:CE13) -> 0 | CH13: =+IFERROR(CF13/CG13,0) -> 0 | CJ13: =+Z13*$CJ$5 -> 0 | CM13: =SUM(CJ13:CL13) -> 0 | CO13: =+IFERROR(CM13/CN13,0) -> 0 | CQ13: =+AA13*$CQ$5 -> 0 | CT13: =SUM(CQ13:CS13) -> 0 | CV13: =+IFERROR(CT13/CU13,0) -> 0 | CX13: =+AB13*$CX$5 -> 0 | DA13: =SUM(CX13:CZ13) -> 0 | DC13: =+IFERROR(DA13/DB13,0) -> 0 | DE13: =+AC13*$DE$5 -> 0 | DH13: =SUM(DE13:DG13) -> 0 | DJ13: =+IFERROR(DH13/DI13,0) -> 0
A14: 91243520 | B14: Logística MN | C14: 9076860 0060 | P14: =SUM(D14:O14) -> 0 | R14: =+D14/R$5 -> 0 | S14: =+E14/S$5 -> 0 | T14: =+F14/T$5 -> 0 | U14: =+G14/U$5 -> 0 | V14: =+H14/V$5 -> 0 | W14: =+I14/W$5 -> 0 | X14: =+J14/X$5 -> 0 | Y14: =+K14/Y$5 -> 0 | ... AC14: =+O14/AC$5 -> 0 | AF14: =+R14*AG$5 -> #REF! | AI14: =SUM(AF14:AH14) -> #REF! | AK14: =+IFERROR(AI14/AJ14,0) -> 0 | AM14: =+S14*AM$5 -> #REF! | AP14: =SUM(AM14:AO14) -> #REF! | AR14: =+IFERROR(AP14/AQ14,0) -> 0 | AT14: =+T14*AT$5 -> #REF! | AW14: =SUM(AT14:AV14) -> #REF! | AY14: =+IFERROR(AW14/AX14,0) -> 0 | BA14: =+U14*$BA$5 -> #REF! | BD14: =SUM(BA14:BC14) -> #REF! | BF14: =+IFERROR(BD14/BE14,0) -> 0 | BH14: =+V14*$BH$5 -> 0 | BK14: =SUM(BH14:BJ14) -> 0 | BM14: =+IFERROR(BK14/BL14,0) -> 0 | BR14: =SUM(BO14:BQ14) -> 0 | BT14: =+IFERROR(BR14/BS14,0) -> 0 | BV14: =+X14*$BV$5 -> 0 | BY14: =SUM(BV14:BX14) -> 0 | CA14: =+IFERROR(BY14/BZ14,0) -> 0 | CC14: =+Y14*$CC$5 -> 0 | CF14: =SUM(CC14:CE14) -> 0 | CH14: =+IFERROR(CF14/CG14,0) -> 0 | CJ14: =+Z14*$CJ$5 -> 0 | CM14: =SUM(CJ14:CL14) -> 0 | CO14: =+IFERROR(CM14/CN14,0) -> 0 | CQ14: =+AA14*$CQ$5 -> 0 | CT14: =SUM(CQ14:CS14) -> 0 | CV14: =+IFERROR(CT14/CU14,0) -> 0 | CX14: =+AB14*$CX$5 -> 0 | DA14: =SUM(CX14:CZ14) -> 0 | DC14: =+IFERROR(DA14/DB14,0) -> 0 | DE14: =+AC14*$DE$5 -> 0 | DH14: =SUM(DE14:DG14) -> 0 | DJ14: =+IFERROR(DH14/DI14,0) -> 0
A15: 91243530 | B15: Logística ME | C15: 9076860 0070 | P15: =SUM(D15:O15) -> 0 | R15: =+D15/R$5 -> 0 | S15: =+E15/S$5 -> 0 | T15: =+F15/T$5 -> 0 | U15: =+G15/U$5 -> 0 | V15: =+H15/V$5 -> 0 | W15: =+I15/W$5 -> 0 | X15: =+J15/X$5 -> 0 | Y15: =+K15/Y$5 -> 0 | ... AC15: =+O15/AC$5 -> 0 | AF15: =+R15*AF$5 -> #REF! | AI15: =SUM(AF15:AH15) -> #REF! | AK15: =+IFERROR(AI15/AJ15,0) -> 0 | AM15: =+S15*AM$5 -> #REF! | AP15: =SUM(AM15:AO15) -> #REF! | AR15: =+IFERROR(AP15/AQ15,0) -> 0 | AT15: =+T15*AT$5 -> #REF! | AW15: =SUM(AT15:AV15) -> #REF! | AY15: =+IFERROR(AW15/AX15,0) -> 0 | BA15: =+U15*$BA$5 -> #REF! | BD15: =SUM(BA15:BC15) -> #REF! | BF15: =+IFERROR(BD15/BE15,0) -> 0 | BH15: =+V15*$BH$5 -> 0 | BK15: =SUM(BH15:BJ15) -> 0 | BM15: =+IFERROR(BK15/BL15,0) -> 0 | BR15: =SUM(BO15:BQ15) -> 0 | BT15: =+IFERROR(BR15/BS15,0) -> 0 | BV15: =+X15*$BV$5 -> 0 | BY15: =SUM(BV15:BX15) -> 0 | CA15: =+IFERROR(BY15/BZ15,0) -> 0 | CC15: =+Y15*$CC$5 -> 0 | CF15: =SUM(CC15:CE15) -> 0 | CH15: =+IFERROR(CF15/CG15,0) -> 0 | CJ15: =+Z15*$CJ$5 -> 0 | CM15: =SUM(CJ15:CL15) -> 0 | CO15: =+IFERROR(CM15/CN15,0) -> 0 | CQ15: =+AA15*$CQ$5 -> 0 | CT15: =SUM(CQ15:CS15) -> 0 | CV15: =+IFERROR(CT15/CU15,0) -> 0 | CX15: =+AB15*$CX$5 -> 0 | DA15: =SUM(CX15:CZ15) -> 0 | DC15: =+IFERROR(DA15/DB15,0) -> 0 | DE15: =+AC15*$DE$5 -> 0 | DH15: =SUM(DE15:DG15) -> 0 | DJ15: =+IFERROR(DH15/DI15,0) -> 0
A16: 91243540 | B16: Propiedad Minera | C16: 9076860 0080 | P16: =SUM(D16:O16) -> 0 | R16: =+D16/R$5 -> 0 | S16: =+E16/S$5 -> 0 | T16: =+F16/T$5 -> 0 | U16: =+G16/U$5 -> 0 | V16: =+H16/V$5 -> 0 | W16: =+I16/W$5 -> 0 | X16: =+J16/X$5 -> 0 | Y16: =+K16/Y$5 -> 0 | ... AC16: =+O16/AC$5 -> 0 | AF16: =+R16*AF$5 -> #REF! | AI16: =SUM(AF16:AH16) -> #REF! | AK16: =+IFERROR(AI16/AJ16,0) -> 0 | AM16: =+S16*AM$5 -> #REF! | AP16: =SUM(AM16:AO16) -> #REF! | AR16: =+IFERROR(AP16/AQ16,0) -> 0 | AT16: =+T16*AT$5 -> #REF! | AW16: =SUM(AT16:AV16) -> #REF! | AY16: =+IFERROR(AW16/AX16,0) -> 0 | BA16: =+U16*$BA$5 -> #REF! | BD16: =SUM(BA16:BC16) -> #REF! | BF16: =+IFERROR(BD16/BE16,0) -> 0 | BH16: =+V16*$BH$5 -> 0 | BK16: =SUM(BH16:BJ16) -> 0 | BM16: =+IFERROR(BK16/BL16,0) -> 0 | BR16: =SUM(BO16:BQ16) -> 0 | BT16: =+IFERROR(BR16/BS16,0) -> 0 | BV16: =+X16*$BV$5 -> 0 | BY16: =SUM(BV16:BX16) -> 0 | CA16: =+IFERROR(BY16/BZ16,0) -> 0 | CC16: =+Y16*$CC$5 -> 0 | CF16: =SUM(CC16:CE16) -> 0 | CH16: =+IFERROR(CF16/CG16,0) -> 0 | CJ16: =+Z16*$CJ$5 -> 0 | CM16: =SUM(CJ16:CL16) -> 0 | CO16: =+IFERROR(CM16/CN16,0) -> 0 | CQ16: =+AA16*$CQ$5 -> 0 | CT16: =SUM(CQ16:CS16) -> 0 | CV16: =+IFERROR(CT16/CU16,0) -> 0 | CX16: =+AB16*$CX$5 -> 0 | DA16: =SUM(CX16:CZ16) -> 0 | DC16: =+IFERROR(DA16/DB16,0) -> 0 | DE16: =+AC16*$DE$5 -> 0 | DH16: =SUM(DE16:DG16) -> 0 | DJ16: =+IFERROR(DH16/DI16,0) -> 0
A17: 91243550 | B17: Medio Ambiente MN | C17: 9076860 0090 | P17: =SUM(D17:O17) -> 0 | R17: =+D17/R$5 -> 0 | S17: =+E17/S$5 -> 0 | T17: =+F17/T$5 -> 0 | U17: =+G17/U$5 -> 0 | V17: =+H17/V$5 -> 0 | W17: =+I17/W$5 -> 0 | X17: =+J17/X$5 -> 0 | Y17: =+K17/Y$5 -> 0 | ... AC17: =+O17/AC$5 -> 0 | AF17: =+R17*AF$5 -> #REF! | AI17: =SUM(AF17:AH17) -> #REF! | AK17: =+IFERROR(AI17/AJ17,0) -> 0 | AM17: =+S17*AM$5 -> #REF! | AP17: =SUM(AM17:AO17) -> #REF! | AR17: =+IFERROR(AP17/AQ17,0) -> 0 | AT17: =+T17*AT$5 -> #REF! | AW17: =SUM(AT17:AV17) -> #REF! | AY17: =+IFERROR(AW17/AX17,0) -> 0 | BA17: =+U17*$BA$5 -> #REF! | BD17: =SUM(BA17:BC17) -> #REF! | BF17: =+IFERROR(BD17/BE17,0) -> 0 | BH17: =+V17*$BH$5 -> 0 | BK17: =SUM(BH17:BJ17) -> 0 | BM17: =+IFERROR(BK17/BL17,0) -> 0 | BR17: =SUM(BO17:BQ17) -> 0 | BT17: =+IFERROR(BR17/BS17,0) -> 0 | BV17: =+X17*$BV$5 -> 0 | BY17: =SUM(BV17:BX17) -> 0 | CA17: =+IFERROR(BY17/BZ17,0) -> 0 | CC17: =+Y17*$CC$5 -> 0 | CF17: =SUM(CC17:CE17) -> 0 | CH17: =+IFERROR(CF17/CG17,0) -> 0 | CJ17: =+Z17*$CJ$5 -> 0 | CM17: =SUM(CJ17:CL17) -> 0 | CO17: =+IFERROR(CM17/CN17,0) -> 0 | CQ17: =+AA17*$CQ$5 -> 0 | CT17: =SUM(CQ17:CS17) -> 0 | CV17: =+IFERROR(CT17/CU17,0) -> 0 | CX17: =+AB17*$CX$5 -> 0 | DA17: =SUM(CX17:CZ17) -> 0 | DC17: =+IFERROR(DA17/DB17,0) -> 0 | DE17: =+AC17*$DE$5 -> 0 | DH17: =SUM(DE17:DG17) -> 0 | DJ17: =+IFERROR(DH17/DI17,0) -> 0
A18: 91243560 | B18: Medio Ambiente ME | C18: 9076860 00100 | P18: =SUM(D18:O18) -> 0 | R18: =+D18/R$5 -> 0 | S18: =+E18/S$5 -> 0 | T18: =+F18/T$5 -> 0 | U18: =+G18/U$5 -> 0 | V18: =+H18/V$5 -> 0 | W18: =+I18/W$5 -> 0 | X18: =+J18/X$5 -> 0 | Y18: =+K18/Y$5 -> 0 | ... AC18: =+O18/AC$5 -> 0 | AF18: =+R18*AG$5 -> #REF! | AI18: =SUM(AF18:AH18) -> #REF! | AK18: =+IFERROR(AI18/AJ18,0) -> 0 | AM18: =+S18*AM$5 -> #REF! | AP18: =SUM(AM18:AO18) -> #REF! | AR18: =+IFERROR(AP18/AQ18,0) -> 0 | AT18: =+T18*AT$5 -> #REF! | AW18: =SUM(AT18:AV18) -> #REF! | AY18: =+IFERROR(AW18/AX18,0) -> 0 | BA18: =+U18*$BA$5 -> #REF! | BD18: =SUM(BA18:BC18) -> #REF! | BF18: =+IFERROR(BD18/BE18,0) -> 0 | BH18: =+V18*$BH$5 -> 0 | BK18: =SUM(BH18:BJ18) -> 0 | BM18: =+IFERROR(BK18/BL18,0) -> 0 | BR18: =SUM(BO18:BQ18) -> 0 | BT18: =+IFERROR(BR18/BS18,0) -> 0 | BV18: =+X18*$BV$5 -> 0 | BY18: =SUM(BV18:BX18) -> 0 | CA18: =+IFERROR(BY18/BZ18,0) -> 0 | CC18: =+Y18*$CC$5 -> 0 | CF18: =SUM(CC18:CE18) -> 0 | CH18: =+IFERROR(CF18/CG18,0) -> 0 | CJ18: =+Z18*$CJ$5 -> 0 | CM18: =SUM(CJ18:CL18) -> 0 | CO18: =+IFERROR(CM18/CN18,0) -> 0 | CQ18: =+AA18*$CQ$5 -> 0 | CT18: =SUM(CQ18:CS18) -> 0 | CV18: =+IFERROR(CT18/CU18,0) -> 0 | CX18: =+AB18*$CX$5 -> 0 | DA18: =SUM(CX18:CZ18) -> 0 | DC18: =+IFERROR(DA18/DB18,0) -> 0 | DE18: =+AC18*$DE$5 -> 0 | DH18: =SUM(DE18:DG18) -> 0 | DJ18: =+IFERROR(DH18/DI18,0) -> 0
A19: 91243570 | B19: Seguridad ME | C19: 9076860 00110 | P19: =SUM(D19:O19) -> 0 | R19: =+D19/R$5 -> 0 | S19: =+E19/S$5 -> 0 | T19: =+F19/T$5 -> 0 | U19: =+G19/U$5 -> 0 | V19: =+H19/V$5 -> 0 | W19: =+I19/W$5 -> 0 | X19: =+J19/X$5 -> 0 | Y19: =+K19/Y$5 -> 0 | ... AC19: =+O19/AC$5 -> 0 | AF19: =+R19*AG$5 -> #REF! | AI19: =SUM(AF19:AH19) -> #REF! | AK19: =+IFERROR(AI19/AJ19,0) -> 0 | AM19: =+S19*AM$5 -> #REF! | AP19: =SUM(AM19:AO19) -> #REF! | AR19: =+IFERROR(AP19/AQ19,0) -> 0 | AT19: =+T19*AT$5 -> #REF! | AW19: =SUM(AT19:AV19) -> #REF! | AY19: =+IFERROR(AW19/AX19,0) -> 0 | BA19: =+U19*$BA$5 -> #REF! | BD19: =SUM(BA19:BC19) -> #REF! | BF19: =+IFERROR(BD19/BE19,0) -> 0 | BH19: =+V19*$BH$5 -> 0 | BK19: =SUM(BH19:BJ19) -> 0 | BM19: =+IFERROR(BK19/BL19,0) -> 0 | BR19: =SUM(BO19:BQ19) -> 0 | BT19: =+IFERROR(BR19/BS19,0) -> 0 | BV19: =+X19*$BV$5 -> 0 | BY19: =SUM(BV19:BX19) -> 0 | CA19: =+IFERROR(BY19/BZ19,0) -> 0 | CC19: =+Y19*$CC$5 -> 0 | CF19: =SUM(CC19:CE19) -> 0 | CH19: =+IFERROR(CF19/CG19,0) -> 0 | CJ19: =+Z19*$CJ$5 -> 0 | CM19: =SUM(CJ19:CL19) -> 0 | CO19: =+IFERROR(CM19/CN19,0) -> 0 | CQ19: =+AA19*$CQ$5 -> 0 | CT19: =SUM(CQ19:CS19) -> 0 | CV19: =+IFERROR(CT19/CU19,0) -> 0 | CX19: =+AB19*$CX$5 -> 0 | DA19: =SUM(CX19:CZ19) -> 0 | DC19: =+IFERROR(DA19/DB19,0) -> 0 | DE19: =+AC19*$DE$5 -> 0 | DH19: =SUM(DE19:DG19) -> 0 | DJ19: =+IFERROR(DH19/DI19,0) -> 0
A20: 91243710 | B20: Comunidades ME | C20: 9076860 0120 | P20: =SUM(D20:O20) -> 0 | R20: =+D20/R$5 -> 0 | S20: =+E20/S$5 -> 0 | T20: =+F20/T$5 -> 0 | U20: =+G20/U$5 -> 0 | V20: =+H20/V$5 -> 0 | W20: =+I20/W$5 -> 0 | X20: =+J20/X$5 -> 0 | Y20: =+K20/Y$5 -> 0 | ... AC20: =+O20/AC$5 -> 0 | AF20: =+R20*AG$5 -> #REF! | AI20: =SUM(AF20:AH20) -> #REF! | AK20: =+IFERROR(AI20/AJ20,0) -> 0 | AM20: =+S20*AM$5 -> #REF! | AP20: =SUM(AM20:AO20) -> #REF! | AR20: =+IFERROR(AP20/AQ20,0) -> 0 | AT20: =+T20*AT$5 -> #REF! | AW20: =SUM(AT20:AV20) -> #REF! | AY20: =+IFERROR(AW20/AX20,0) -> 0 | BA20: =+U20*$BA$5 -> #REF! | BD20: =SUM(BA20:BC20) -> #REF! | BF20: =+IFERROR(BD20/BE20,0) -> 0 | BH20: =+V20*$BH$5 -> 0 | BK20: =SUM(BH20:BJ20) -> 0 | BM20: =+IFERROR(BK20/BL20,0) -> 0 | BR20: =SUM(BO20:BQ20) -> 0 | BT20: =+IFERROR(BR20/BS20,0) -> 0 | BV20: =+X20*$BV$5 -> 0 | BY20: =SUM(BV20:BX20) -> 0 | CA20: =+IFERROR(BY20/BZ20,0) -> 0 | CC20: =+Y20*$CC$5 -> 0 | CF20: =SUM(CC20:CE20) -> 0 | CH20: =+IFERROR(CF20/CG20,0) -> 0 | CJ20: =+Z20*$CJ$5 -> 0 | CM20: =SUM(CJ20:CL20) -> 0 | CO20: =+IFERROR(CM20/CN20,0) -> 0 | CQ20: =+AA20*$CQ$5 -> 0 | CT20: =SUM(CQ20:CS20) -> 0 | CV20: =+IFERROR(CT20/CU20,0) -> 0 | CX20: =+AB20*$CX$5 -> 0 | DA20: =SUM(CX20:CZ20) -> 0 | DC20: =+IFERROR(DA20/DB20,0) -> 0 | DE20: =+AC20*$DE$5 -> 0 | DH20: =SUM(DE20:DG20) -> 0 | DJ20: =+IFERROR(DH20/DI20,0) -> 0
A21: 91243720 | B21: Administración MN | C21: 9076860 0130 | P21: =SUM(D21:O21) -> 0 | R21: =+D21/R$5 -> 0 | S21: =+E21/S$5 -> 0 | T21: =+F21/T$5 -> 0 | U21: =+G21/U$5 -> 0 | V21: =+H21/V$5 -> 0 | W21: =+I21/W$5 -> 0 | X21: =+J21/X$5 -> 0 | Y21: =+K21/Y$5 -> 0 | ... AC21: =+O21/AC$5 -> 0 | AF21: =+R21*AF$5 -> #REF! | AI21: =SUM(AF21:AH21) -> #REF! | AK21: =+IFERROR(AI21/AJ21,0) -> 0 | AM21: =+S21*AM$5 -> #REF! | AP21: =SUM(AM21:AO21) -> #REF! | AR21: =+IFERROR(AP21/AQ21,0) -> 0 | AT21: =+T21*AT$5 -> #REF! | AW21: =SUM(AT21:AV21) -> #REF! | AY21: =+IFERROR(AW21/AX21,0) -> 0 | BA21: =+U21*$BA$5 -> #REF! | BD21: =SUM(BA21:BC21) -> #REF! | BF21: =+IFERROR(BD21/BE21,0) -> 0 | BH21: =+V21*$BH$5 -> 0 | BK21: =SUM(BH21:BJ21) -> 0 | BM21: =+IFERROR(BK21/BL21,0) -> 0 | BR21: =SUM(BO21:BQ21) -> 0 | BT21: =+IFERROR(BR21/BS21,0) -> 0 | BV21: =+X21*$BV$5 -> 0 | BY21: =SUM(BV21:BX21) -> 0 | CA21: =+IFERROR(BY21/BZ21,0) -> 0 | CC21: =+Y21*$CC$5 -> 0 | CF21: =SUM(CC21:CE21) -> 0 | CH21: =+IFERROR(CF21/CG21,0) -> 0 | CJ21: =+Z21*$CJ$5 -> 0 | CM21: =SUM(CJ21:CL21) -> 0 | CO21: =+IFERROR(CM21/CN21,0) -> 0 | CQ21: =+AA21*$CQ$5 -> 0 | CT21: =SUM(CQ21:CS21) -> 0 | CV21: =+IFERROR(CT21/CU21,0) -> 0 | CX21: =+AB21*$CX$5 -> 0 | DA21: =SUM(CX21:CZ21) -> 0 | DC21: =+IFERROR(DA21/DB21,0) -> 0 | DE21: =+AC21*$DE$5 -> 0 | DH21: =SUM(DE21:DG21) -> 0 | DJ21: =+IFERROR(DH21/DI21,0) -> 0
A22: 91243730 | B22: Contingencia MN | C22: 9076860 0140 | P22: =SUM(D22:O22) -> 0 | R22: =+D22/R$5 -> 0 | S22: =+E22/S$5 -> 0 | T22: =+F22/T$5 -> 0 | U22: =+G22/U$5 -> 0 | V22: =+H22/V$5 -> 0 | W22: =+I22/W$5 -> 0 | X22: =+J22/X$5 -> 0 | Y22: =+K22/Y$5 -> 0 | ... AC22: =+O22/AC$5 -> 0 | AF22: =+R22*AF$5 -> #REF! | AI22: =SUM(AF22:AH22) -> #REF! | AK22: =+IFERROR(AI22/AJ22,0) -> 0 | AM22: =+S22*AM$5 -> #REF! | AP22: =SUM(AM22:AO22) -> #REF! | AR22: =+IFERROR(AP22/AQ22,0) -> 0 | AT22: =+T22*AT$5 -> #REF! | AW22: =SUM(AT22:AV22) -> #REF! | AY22: =+IFERROR(AW22/AX22,0) -> 0 | BA22: =+U22*$BA$5 -> #REF! | BD22: =SUM(BA22:BC22) -> #REF! | BF22: =+IFERROR(BD22/BE22,0) -> 0 | BH22: =+V22*$BH$5 -> 0 | BK22: =SUM(BH22:BJ22) -> 0 | BM22: =+IFERROR(BK22/BL22,0) -> 0 | BR22: =SUM(BO22:BQ22) -> 0 | BT22: =+IFERROR(BR22/BS22,0) -> 0 | BV22: =+X22*$BV$5 -> 0 | BY22: =SUM(BV22:BX22) -> 0 | CA22: =+IFERROR(BY22/BZ22,0) -> 0 | CC22: =+Y22*$CC$5 -> 0 | CF22: =SUM(CC22:CE22) -> 0 | CH22: =+IFERROR(CF22/CG22,0) -> 0 | CJ22: =+Z22*$CJ$5 -> 0 | CM22: =SUM(CJ22:CL22) -> 0 | CO22: =+IFERROR(CM22/CN22,0) -> 0 | CQ22: =+AA22*$CQ$5 -> 0 | CT22: =SUM(CQ22:CS22) -> 0 | CV22: =+IFERROR(CT22/CU22,0) -> 0 | CX22: =+AB22*$CX$5 -> 0 | DA22: =SUM(CX22:CZ22) -> 0 | DC22: =+IFERROR(DA22/DB22,0) -> 0 | DE22: =+AC22*$DE$5 -> 0 | DH22: =SUM(DE22:DG22) -> 0 | DJ22: =+IFERROR(DH22/DI22,0) -> 0
A23: 912439 | B23: GESTIÓN EJECUCIÓN PROYECTO | D23: =+SUM(D24:D25) -> 0 | E23: =+SUM(E24:E25) -> 0 | F23: =+SUM(F24:F25) -> 0 | G23: =+SUM(G24:G25) -> 0 | H23: =+SUM(H24:H25) -> 0 | I23: =+SUM(I24:I25) -> 0 | J23: =+SUM(J24:J25) -> 0 | R23: =+SUM(R24:R25) -> 0 | AF23: =AF24+AF25 -> #REF! | AG23: =AG24+AG25 -> 0 | AH23: =AH24+AH25 -> 0 | AI23: =AI24+AI25 -> #REF! | AJ23: =AJ24+AJ25 -> 0 | AK23: =AK24+AK25 -> 0 | AL23: =AL24+AL25 -> 0 | AM23: =AM24+AM25 -> #REF! | ... DJ23: =DJ24+DJ25 -> 0
A24: 91243910 | B24:  FEE M.O. | C24: 9076860 0150 | H24: =SUMIF(S!$L:$L,$A24&UPPER(TEXT(H$4,"MMMMYYYY")),S!$AD:$AD) -> 0 | I24: =SUMIF(S!$L:$L,$A24&UPPER(TEXT(I$4,"MMMMYYYY")),S!$AD:$AD) -> 0 | J24: =SUMIF(S!$L:$L,$A24&UPPER(TEXT(J$4,"MMMMYYYY")),S!$AD:$AD) -> 0 | R24: =+D24/R$5 -> 0 | S24: =+E24/S$5 -> 0 | T24: =+F24/T$5 -> 0 | U24: =+G24/U$5 -> 0 | V24: =+H24/V$5 -> 0 | W24: =+I24/W$5 -> 0 | X24: =+J24/X$5 -> 0 | Y24: =+K24/Y$5 -> 0 | ... AC24: =+O24/AC$5 -> 0 | AF24: =+R24*AF$5 -> #REF! | AI24: =SUM(AF24:AH24) -> #REF! | AK24: =+IFERROR(AI24/AJ24,0) -> 0 | AM24: =+S24*AM$5 -> #REF! | AP24: =SUM(AM24:AO24) -> #REF! | AR24: =+IFERROR(AP24/AQ24,0) -> 0 | AT24: =+T24*AT$5 -> #REF! | AW24: =SUM(AT24:AV24) -> #REF! | AY24: =+IFERROR(AW24/AX24,0) -> 0 | BA24: =+U24*$BA$5 -> #REF! | BC24: =(#REF!+#REF!)/1000 -> #REF! | BD24: =SUM(BA24:BC24) -> #REF! | BF24: =+IFERROR(BD24/BE24,0) -> 0 | BH24: =+V24*$BH$5 -> 0 | BK24: =SUM(BH24:BJ24) -> 0 | BM24: =+IFERROR(BK24/BL24,0) -> 0 | BR24: =SUM(BO24:BQ24) -> 0 | BT24: =+IFERROR(BR24/BS24,0) -> 0 | BV24: =+X24*$BV$5 -> 0 | BY24: =SUM(BV24:BX24) -> 0 | CA24: =+IFERROR(BY24/BZ24,0) -> 0 | CC24: =+Y24*$CC$5 -> 0 | CF24: =SUM(CC24:CE24) -> 0 | CH24: =+IFERROR(CF24/CG24,0) -> 0 | CJ24: =+Z24*$CJ$5 -> 0 | CM24: =SUM(CJ24:CL24) -> 0 | CO24: =+IFERROR(CM24/CN24,0) -> 0 | CQ24: =+AA24*$CQ$5 -> 0 | CT24: =SUM(CQ24:CS24) -> 0 | CV24: =+IFERROR(CT24/CU24,0) -> 0 | CX24: =+AB24*$CX$5 -> 0 | DA24: =SUM(CX24:CZ24) -> 0 | DC24: =+IFERROR(DA24/DB24,0) -> 0 | DE24: =+AC24*$DE$5 -> 0 | DH24: =SUM(DE24:DG24) -> 0 | DJ24: =+IFERROR(DH24/DI24,0) -> 0
A25: 91243920 | B25:  FEE S.S. | C25: 9076860 0160 | H25: =SUMIF(S!$L:$L,$A25&UPPER(TEXT(H$4,"MMMMYYYY")),S!$AD:$AD) -> 0 | I25: =SUMIF(S!$L:$L,$A25&UPPER(TEXT(I$4,"MMMMYYYY")),S!$AD:$AD) -> 0 | J25: =SUMIF(S!$L:$L,$A25&UPPER(TEXT(J$4,"MMMMYYYY")),S!$AD:$AD) -> 0 | R25: =+D25/R$5 -> 0 | S25: =+E25/S$5 -> 0 | T25: =+F25/T$5 -> 0 | U25: =+G25/U$5 -> 0 | V25: =+H25/V$5 -> 0 | W25: =+I25/W$5 -> 0 | X25: =+J25/X$5 -> 0 | Y25: =+K25/Y$5 -> 0 | ... AC25: =+O25/AC$5 -> 0 | AF25: =+R25*AF$5 -> #REF! | AI25: =SUM(AF25:AH25) -> #REF! | AK25: =+IFERROR(AI25/AJ25,0) -> 0 | AM25: =+S25*AM$5 -> #REF! | AP25: =SUM(AM25:AO25) -> #REF! | AR25: =+IFERROR(AP25/AQ25,0) -> 0 | AT25: =+T25*AT$5 -> #REF! | AW25: =SUM(AT25:AV25) -> #REF! | AY25: =+IFERROR(AW25/AX25,0) -> 0 | BA25: =+U25*$BA$5 -> #REF! | BD25: =SUM(BA25:BC25) -> #REF! | BF25: =+IFERROR(BD25/BE25,0) -> 0 | BH25: =+V25*$BH$5 -> 0 | BK25: =SUM(BH25:BJ25) -> 0 | BM25: =+IFERROR(BK25/BL25,0) -> 0 | BR25: =SUM(BO25:BQ25) -> 0 | BT25: =+IFERROR(BR25/BS25,0) -> 0 | BV25: =+X25*$BV$5 -> 0 | BY25: =SUM(BV25:BX25) -> 0 | CA25: =+IFERROR(BY25/BZ25,0) -> 0 | CC25: =+Y25*$CC$5 -> 0 | CF25: =SUM(CC25:CE25) -> 0 | CH25: =+IFERROR(CF25/CG25,0) -> 0 | CJ25: =+Z25*$CJ$5 -> 0 | CM25: =SUM(CJ25:CL25) -> 0 | CO25: =+IFERROR(CM25/CN25,0) -> 0 | CQ25: =+AA25*$CQ$5 -> 0 | CT25: =SUM(CQ25:CS25) -> 0 | CV25: =+IFERROR(CT25/CU25,0) -> 0 | CX25: =+AB25*$CX$5 -> 0 | DA25: =SUM(CX25:CZ25) -> 0 | DC25: =+IFERROR(DA25/DB25,0) -> 0 | DE25: =+AC25*$DE$5 -> 0 | DH25: =SUM(DE25:DG25) -> 0 | DJ25: =+IFERROR(DH25/DI25,0) -> 0
A26: 912439 | B26: COSTOS DEL DUEÑO | D26: =+SUM(D27) -> 0 | E26: =+SUM(E27) -> 0 | F26: =+SUM(F27) -> 0 | G26: =+SUM(G27) -> 0 | H26: =+SUM(H27) -> 0 | I26: =+SUM(I27) -> 0 | J26: =+SUM(J27) -> 0 | K26: =+SUM(K27) -> 0 | ... O26: =+SUM(O27) -> 0 | R26: =+SUM(R27:R28) -> 37.254669 | AF26: =AF27+AF28 -> #REF! | AG26: =AG27+AG28 -> #REF! | AH26: =AH27+AH28 -> #REF! | AI26: =AI27+AI28 -> #REF! | AJ26: =AJ27+AJ28 -> #REF! | AK26: =AK27+AK28 -> #REF! | AL26: =AL27+AL28 -> 0 | AM26: =AM27+AM28 -> #REF! | ... DJ26: =DJ27+DJ28 -> #REF!
B27: COSTOS DEL DUEÑO | C27: 9076860 0170
A28: M18G005-1.1.2 | B28: Item Ii | D28: =+D29+D44 -> 45953008 | E28: =+E29+E44 -> 0 | F28: =+F29+F44 -> 0 | G28: =+G29+G44 -> 0 | H28: =+H29+H44 -> 0 | I28: =+I29+I44 -> 0 | J28: =+J29+J44 -> 0 | K28: =+K29+K44 -> 0 | ... P28: =+P29+P44 -> 29692266 | R28: =+R29+R44 -> 37.254669 | S28: =+S29+S44 -> 0 | T28: =+T29+T44 -> 0 | U28: =+U29+U44 -> 0 | V28: =+V29+V44 -> 0 | W28: =+W29+W44 -> 0 | X28: =+X29+X44 -> 0 | Y28: =+Y29+Y44 -> 0 | ... AC28: =+AC29+AC44 -> 0 | AD28: =+AD29+#REF!+AD44+#REF!+#REF!+#REF! -> #REF! | AF28: =+AF29+#REF!+#REF!+AF44+#REF!+#REF! -> #REF! | AG28: =+AG29+#REF!+#REF!+AG44+#REF!+#REF! -> #REF! | AH28: =+AH29+#REF!+#REF!+AH44+#REF!+#REF! -> #REF! | AI28: =+AI29+#REF!+#REF!+AI44+#REF!+#REF! -> #REF! | AJ28: =+AJ29+#REF!+#REF!+AJ44+#REF!+#REF! -> #REF! | AK28: =+AK29+#REF!+#REF!+AK44+#REF!+#REF! -> #REF! | AM28: =+AM29+#REF!+#REF!+AM44+#REF!+#REF! -> #REF! | AN28: =+AN29+#REF!+#REF!+AN44+#REF!+#REF! -> #REF! | AO28: =+AO29+#REF!+#REF!+AO44+#REF!+#REF! -> #REF! | AP28: =+AP29+#REF!+#REF!+AP44+#REF!+#REF! -> #REF! | AQ28: =+AQ29+#REF!+#REF!+AQ44+#REF!+#REF! -> #REF! | AR28: =+AR29+#REF!+#REF!+AR44+#REF!+#REF! -> #REF! | AT28: =+AT29+#REF!+#REF!+AT44+#REF!+#REF! -> #REF! | AU28: =+AU29+#REF!+#REF!+AU44+#REF!+#REF! -> #REF! | AV28: =+AV29+#REF!+#REF!+AV44+#REF!+#REF! -> #REF! | AW28: =+AW29+#REF!+#REF!+AW44+#REF!+#REF! -> #REF! | AX28: =+AX29+#REF!+#REF!+AX44+#REF!+#REF! -> #REF! | AY28: =+AY29+#REF!+#REF!+AY44+#REF!+#REF! -> #REF! | BA28: =+BA29+#REF!+#REF!+BA44+#REF!+#REF! -> #REF! | BB28: =+BB29+#REF!+#REF!+BB44+#REF!+#REF! -> #REF! | BC28: =+BC29+#REF!+#REF!+BC44+#REF!+#REF! -> #REF! | BD28: =+BD29+#REF!+#REF!+BD44+#REF!+#REF! -> #REF! | BE28: =+BE29+#REF!+#REF!+BE44+#REF!+#REF! -> #REF! | BF28: =+BF29+#REF!+#REF!+BF44+#REF!+#REF! -> #REF! | BH28: =+BH29+#REF!+#REF!+BH44+#REF!+#REF! -> #REF! | BI28: =+BI29+#REF!+#REF!+BI44+#REF!+#REF! -> #REF! | BJ28: =+BJ29+#REF!+#REF!+BJ44+#REF!+#REF! -> #REF! | BK28: =+BK29+#REF!+#REF!+BK44+#REF!+#REF! -> #REF! | BL28: =+BL29+#REF!+#REF!+BL44+#REF!+#REF! -> #REF! | BM28: =+BM29+#REF!+#REF!+BM44+#REF!+#REF! -> #REF! | BO28: =+BO29+#REF!+#REF!+BO44+#REF!+#REF! -> #REF! | BP28: =+BP29+#REF!+#REF!+BP44+#REF!+#REF! -> #REF! | BQ28: =+BQ29+#REF!+#REF!+BQ44+#REF!+#REF! -> #REF! | BR28: =+BR29+#REF!+#REF!+BR44+#REF!+#REF! -> #REF! | BS28: =+BS29+#REF!+#REF!+BS44+#REF!+#REF! -> #REF! | BT28: =+BT29+#REF!+#REF!+BT44+#REF!+#REF! -> #REF! | BV28: =+BV29+#REF!+#REF!+BV44+#REF!+#REF! -> #REF! | BW28: =+BW29+#REF!+#REF!+BW44+#REF!+#REF! -> #REF! | BX28: =+BX29+#REF!+#REF!+BX44+#REF!+#REF! -> #REF! | BY28: =+BY29+#REF!+#REF!+BY44+#REF!+#REF! -> #REF! | BZ28: =+BZ29+#REF!+#REF!+BZ44+#REF!+#REF! -> #REF! | CA28: =+CA29+#REF!+#REF!+CA44+#REF!+#REF! -> #REF! | CC28: =+CC29+#REF!+#REF!+CC44+#REF!+#REF! -> #REF! | CD28: =+CD29+#REF!+#REF!+CD44+#REF!+#REF! -> #REF! | CE28: =+CE29+#REF!+#REF!+CE44+#REF!+#REF! -> #REF! | CF28: =+CF29+#REF!+#REF!+CF44+#REF!+#REF! -> #REF! | CG28: =+CG29+#REF!+#REF!+CG44+#REF!+#REF! -> #REF! | CH28: =+CH29+#REF!+#REF!+CH44+#REF!+#REF! -> #REF! | CJ28: =+CJ29+#REF!+#REF!+CJ44+#REF!+#REF! -> #REF! | CK28: =+CK29+#REF!+#REF!+CK44+#REF!+#REF! -> #REF! | CL28: =+CL29+#REF!+#REF!+CL44+#REF!+#REF! -> #REF! | CM28: =+CM29+#REF!+#REF!+CM44+#REF!+#REF! -> #REF! | CN28: =+CN29+#REF!+#REF!+CN44+#REF!+#REF! -> #REF! | CO28: =+CO29+#REF!+#REF!+CO44+#REF!+#REF! -> #REF! | CQ28: =+CQ29+#REF!+#REF!+CQ44+#REF!+#REF! -> #REF! | CR28: =+CR29+#REF!+#REF!+CR44+#REF!+#REF! -> #REF! | CS28: =+CS29+#REF!+#REF!+CS44+#REF!+#REF! -> #REF! | CT28: =+CT29+#REF!+#REF!+CT44+#REF!+#REF! -> #REF! | CU28: =+CU29+#REF!+#REF!+CU44+#REF!+#REF! -> #REF! | CV28: =+CV29+#REF!+#REF!+CV44+#REF!+#REF! -> #REF! | CX28: =+CX29+#REF!+#REF!+CX44+#REF!+#REF! -> #REF! | CY28: =+CY29+#REF!+#REF!+CY44+#REF!+#REF! -> #REF! | CZ28: =+CZ29+#REF!+#REF!+CZ44+#REF!+#REF! -> #REF! | DA28: =+DA29+#REF!+#REF!+DA44+#REF!+#REF! -> #REF! | DB28: =+DB29+#REF!+#REF!+DB44+#REF!+#REF! -> #REF! | DC28: =+DC29+#REF!+#REF!+DC44+#REF!+#REF! -> #REF! | DE28: =+DE29+#REF!+#REF!+DE44+#REF!+#REF! -> #REF! | DF28: =+DF29+#REF!+#REF!+DF44+#REF!+#REF! -> #REF! | DG28: =+DG29+#REF!+#REF!+DG44+#REF!+#REF! -> #REF! | DH28: =+DH29+#REF!+#REF!+DH44+#REF!+#REF! -> #REF! | DI28: =+DI29+#REF!+#REF!+DI44+#REF!+#REF! -> #REF! | DJ28: =+DJ29+#REF!+#REF!+DJ44+#REF!+#REF! -> #REF!
A29: 912431 | B29: GEOLOGÍA | D29: =SUM(D30:D43) -> 44860251 | E29: =SUM(E30:E43) -> 0 | F29: =SUM(F30:F43) -> 0 | G29: =SUM(G30:G43) -> 0 | H29: =SUM(H30:H43) -> 0 | I29: =SUM(I30:I43) -> 0 | J29: =SUM(J30:J43) -> 0 | K29: =SUM(K30:K43) -> 0 | ... O29: =SUM(O30:O43) -> 0 | P29: =SUM(P30:P33) -> 29692266 | R29: =SUM(R30:R33) -> 35.932263 | S29: =SUM(S30:S33) -> 0 | T29: =SUM(T30:T33) -> 0 | U29: =SUM(U30:U33) -> 0 | V29: =SUM(V30:V33) -> 0 | W29: =SUM(W30:W33) -> 0 | X29: =SUM(X30:X33) -> 0 | Y29: =SUM(Y30:Y33) -> 0 | ... AD29: =SUM(AD30:AD33) -> 0 | AF29: =SUM(AF30:AF33) -> #REF! | AG29: =SUM(AG30:AG33) -> 0 | AH29: =SUM(AH30:AH33) -> 0 | AI29: =SUM(AI30:AI33) -> #REF! | AJ29: =SUM(AJ30:AJ33) -> 0 | AK29: =SUM(AK30:AK33) -> 0 | AM29: =SUM(AM30:AM33) -> #REF! | AN29: =SUM(AN30:AN33) -> 0 | AO29: =SUM(AO30:AO33) -> 0 | AP29: =SUM(AP30:AP33) -> #REF! | AQ29: =SUM(AQ30:AQ33) -> 0 | AR29: =SUM(AR30:AR33) -> 0 | AT29: =SUM(AT30:AT33) -> #REF! | AU29: =SUM(AU30:AU33) -> 0 | AV29: =SUM(AV30:AV33) -> 0 | AW29: =SUM(AW30:AW33) -> #REF! | AX29: =SUM(AX30:AX33) -> 0 | AY29: =SUM(AY30:AY33) -> 0 | BA29: =SUM(BA30:BA33) -> #REF! | BB29: =SUM(BB30:BB33) -> 0 | BC29: =SUM(BC30:BC33) -> 0 | BD29: =SUM(BD30:BD33) -> #REF! | BE29: =SUM(BE30:BE33) -> 0 | BF29: =SUM(BF30:BF33) -> 0 | BH29: =SUM(BH30:BH33) -> 0 | BI29: =SUM(BI30:BI33) -> 0 | BJ29: =SUM(BJ30:BJ33) -> 0 | BK29: =SUM(BK30:BK33) -> 0 | BL29: =SUM(BL30:BL33) -> 0 | BM29: =SUM(BM30:BM33) -> 0 | BO29: =SUM(BO30:BO33) -> 0 | BP29: =SUM(BP30:BP33) -> 0 | BQ29: =SUM(BQ30:BQ33) -> 0 | BR29: =SUM(BR30:BR33) -> 0 | BS29: =SUM(BS30:BS33) -> 0 | BT29: =SUM(BT30:BT33) -> 0 | BV29: =SUM(BV30:BV33) -> 0 | BW29: =SUM(BW30:BW33) -> 0 | BX29: =SUM(BX30:BX33) -> 0 | BY29: =SUM(BY30:BY33) -> 0 | BZ29: =SUM(BZ30:BZ33) -> 0 | CA29: =SUM(CA30:CA33) -> 0 | CC29: =SUM(CC30:CC33) -> 0 | CD29: =SUM(CD30:CD33) -> 0 | CE29: =SUM(CE30:CE33) -> 0 | CF29: =SUM(CF30:CF33) -> 0 | CG29: =SUM(CG30:CG33) -> 0 | CH29: =SUM(CH30:CH33) -> 0 | CJ29: =SUM(CJ30:CJ33) -> 0 | CK29: =SUM(CK30:CK33) -> 0 | CL29: =SUM(CL30:CL33) -> 0 | CM29: =SUM(CM30:CM33) -> 0 | CN29: =SUM(CN30:CN33) -> 0 | CO29: =SUM(CO30:CO33) -> 0 | CQ29: =SUM(CQ30:CQ33) -> 0 | CR29: =SUM(CR30:CR33) -> 0 | CS29: =SUM(CS30:CS33) -> 0 | CT29: =SUM(CT30:CT33) -> 0 | CU29: =SUM(CU30:CU33) -> 0 | CV29: =SUM(CV30:CV33) -> 0 | CX29: =SUM(CX30:CX33) -> 0 | CY29: =SUM(CY30:CY33) -> 0 | CZ29: =SUM(CZ30:CZ33) -> 0 | DA29: =SUM(DA30:DA33) -> 0 | DB29: =SUM(DB30:DB33) -> 0 | DC29: =SUM(DC30:DC33) -> 0 | DE29: =SUM(DE30:DE33) -> 0 | DF29: =SUM(DF30:DF33) -> 0 | DG29: =SUM(DG30:DG33) -> 0 | DH29: =SUM(DH30:DH33) -> 0 | DI29: =SUM(DI30:DI33) -> 0 | DJ29: =SUM(DJ30:DJ33) -> 0
A30: 91243110 | B30: Geología MN | C30: 9077127 0010 | D30: =SUMIF(S!$L:$L,$A30&UPPER(TEXT(D$4,"MMMMYYYY")),S!$AD:$AD) -> 20049041 | E30: =SUMIF(S!$L:$L,$A30&UPPER(TEXT(E$4,"MMMMYYYY")),S!$AD:$AD) -> 0 | F30: =SUMIF(S!$L:$L,$A30&UPPER(TEXT(F$4,"MMMMYYYY")),S!$AD:$AD) -> 0 | G30: =SUMIF(S!$L:$L,$A30&UPPER(TEXT(G$4,"MMMMYYYY")),S!$AD:$AD) -> 0 | H30: =SUMIF(S!$L:$L,$A30&UPPER(TEXT(H$4,"MMMMYYYY")),S!$AD:$AD) -> 0 | I30: =SUMIF(S!$L:$L,$A30&UPPER(TEXT(I$4,"MMMMYYYY")),S!$AD:$AD) -> 0 | J30: =SUMIF(S!$L:$L,$A30&UPPER(TEXT(J$4,"MMMMYYYY")),S!$AD:$AD) -> 0 | K30: =SUMIF(S!$L:$L,$A30&UPPER(TEXT(K$4,"MMMMYYYY")),S!$AD:$AD) -> 0 | ... O30: =SUMIF(S!$L:$L,$A30&UPPER(TEXT(O$4,"MMMMYYYY")),S!$AD:$AD) -> 0 | P30: =SUM(D30:O30) -> 20049041 | R30: =+D30/R$5 -> 24.26246 | S30: =+E30/S$5 -> 0 | T30: =+F30/T$5 -> 0 | U30: =+G30/U$5 -> 0 | V30: =+H30/V$5 -> 0 | W30: =+I30/W$5 -> 0 | X30: =+J30/X$5 -> 0 | Y30: =+K30/Y$5 -> 0 | ... AC30: =+O30/AC$5 -> 0 | AF30: =+R30*AF$5 -> #REF! | AI30: =SUM(AF30:AH30) -> #REF! | AK30: =+IFERROR(AI30/AJ30,0) -> 0 | AM30: =+S30*AM$5 -> #REF! | AP30: =SUM(AM30:AO30) -> #REF! | AR30: =+IFERROR(AP30/AQ30,0) -> 0 | AT30: =+T30*AT$5 -> #REF! | AW30: =SUM(AT30:AV30) -> #REF! | AY30: =+IFERROR(AW30/AX30,0) -> 0 | BA30: =+U30*$BA$5 -> #REF! | BD30: =SUM(BA30:BC30) -> #REF! | BF30: =+IFERROR(BD30/BE30,0) -> 0 | BH30: =+V30*$BH$5 -> 0 | BK30: =SUM(BH30:BJ30) -> 0 | BM30: =+IFERROR(BK30/BL30,0) -> 0 | BR30: =SUM(BO30:BQ30) -> 0 | BT30: =+IFERROR(BR30/BS30,0) -> 0 | BV30: =+X30*$BV$5 -> 0 | BY30: =SUM(BV30:BX30) -> 0 | CA30: =+IFERROR(BY30/BZ30,0) -> 0 | CC30: =+Y30*$CC$5 -> 0 | CF30: =SUM(CC30:CE30) -> 0 | CH30: =+IFERROR(CF30/CG30,0) -> 0 | CJ30: =+Z30*$CJ$5 -> 0 | CM30: =SUM(CJ30:CL30) -> 0 | CO30: =+IFERROR(CM30/CN30,0) -> 0 | CQ30: =+AA30*$CQ$5 -> 0 | CT30: =SUM(CQ30:CS30) -> 0 | CV30: =+IFERROR(CT30/CU30,0) -> 0 | CX30: =+AB30*$CX$5 -> 0 | DA30: =SUM(CX30:CZ30) -> 0 | DC30: =+IFERROR(DA30/DB30,0) -> 0 | DE30: =+AC30*$DE$5 -> 0 | DH30: =SUM(DE30:DG30) -> 0 | DJ30: =+IFERROR(DH30/DI30,0) -> 0
A31: 91243120 | B31: Geología ME | C31: 9077127 0020 | D31: =SUMIF(S!$L:$L,$A31&UPPER(TEXT(D$4,"MMMMYYYY")),S!$AD:$AD) -> 9643225 | E31: =SUMIF(S!$L:$L,$A31&UPPER(TEXT(E$4,"MMMMYYYY")),S!$AD:$AD) -> 0 | F31: =SUMIF(S!$L:$L,$A31&UPPER(TEXT(F$4,"MMMMYYYY")),S!$AD:$AD) -> 0 | G31: =SUMIF(S!$L:$L,$A31&UPPER(TEXT(G$4,"MMMMYYYY")),S!$AD:$AD) -> 0 | H31: =SUMIF(S!$L:$L,$A31&UPPER(TEXT(H$4,"MMMMYYYY")),S!$AD:$AD) -> 0 | I31: =SUMIF(S!$L:$L,$A31&UPPER(TEXT(I$4,"MMMMYYYY")),S!$AD:$AD) -> 0 | J31: =SUMIF(S!$L:$L,$A31&UPPER(TEXT(J$4,"MMMMYYYY")),S!$AD:$AD) -> 0 | K31: =SUMIF(S!$L:$L,$A31&UPPER(TEXT(K$4,"MMMMYYYY")),S!$AD:$AD) -> 0 | ... O31: =SUMIF(S!$L:$L,$A31&UPPER(TEXT(O$4,"MMMMYYYY")),S!$AD:$AD) -> 0 | P31: =SUM(D31:O31) -> 9643225 | R31: =+D31/R$5 -> 11.669803 | S31: =+E31/S$5 -> 0 | T31: =+F31/T$5 -> 0 | U31: =+G31/U$5 -> 0 | V31: =+H31/V$5 -> 0 | W31: =+I31/W$5 -> 0 | X31: =+J31/X$5 -> 0 | Y31: =+K31/Y$5 -> 0 | ... AC31: =+O31/AC$5 -> 0 | AF31: =+R31*AF$5 -> #REF! | AI31: =SUM(AF31:AH31) -> #REF! | AK31: =+IFERROR(AI31/AJ31,0) -> 0 | AM31: =+S31*AM$5 -> #REF! | AP31: =SUM(AM31:AO31) -> #REF! | AR31: =+IFERROR(AP31/AQ31,0) -> 0 | AT31: =+T31*AT$5 -> #REF! | AW31: =SUM(AT31:AV31) -> #REF! | AY31: =+IFERROR(AW31/AX31,0) -> 0 | BA31: =+U31*$BA$5 -> #REF! | BD31: =SUM(BA31:BC31) -> #REF! | BF31: =+IFERROR(BD31/BE31,0) -> 0 | BH31: =+V31*$BH$5 -> 0 | BK31: =SUM(BH31:BJ31) -> 0 | BM31: =+IFERROR(BK31/BL31,0) -> 0 | BR31: =SUM(BO31:BQ31) -> 0 | BT31: =+IFERROR(BR31/BS31,0) -> 0 | BV31: =+X31*$BV$5 -> 0 | BY31: =SUM(BV31:BX31) -> 0 | CA31: =+IFERROR(BY31/BZ31,0) -> 0 | CC31: =+Y31*$CC$5 -> 0 | CF31: =SUM(CC31:CE31) -> 0 | CH31: =+IFERROR(CF31/CG31,0) -> 0 | CJ31: =+Z31*$CJ$5 -> 0 | CM31: =SUM(CJ31:CL31) -> 0 | CO31: =+IFERROR(CM31/CN31,0) -> 0 | CQ31: =+AA31*$CQ$5 -> 0 | CT31: =SUM(CQ31:CS31) -> 0 | CV31: =+IFERROR(CT31/CU31,0) -> 0 | CX31: =+AB31*$CX$5 -> 0 | DA31: =SUM(CX31:CZ31) -> 0 | DC31: =+IFERROR(DA31/DB31,0) -> 0 | DE31: =+AC31*$DE$5 -> 0 | DH31: =SUM(DE31:DG31) -> 0 | DJ31: =+IFERROR(DH31/DI31,0) -> 0
A32: 91243220 | B32: Geoquímica ME | C32: 9077127 0030 | D32: =SUMIF(S!$L:$L,$A32&UPPER(TEXT(D$4,"MMMMYYYY")),S!$AD:$AD) -> 0 | E32: =SUMIF(S!$L:$L,$A32&UPPER(TEXT(E$4,"MMMMYYYY")),S!$AD:$AD) -> 0 | F32: =SUMIF(S!$L:$L,$A32&UPPER(TEXT(F$4,"MMMMYYYY")),S!$AD:$AD) -> 0 | G32: =SUMIF(S!$L:$L,$A32&UPPER(TEXT(G$4,"MMMMYYYY")),S!$AD:$AD) -> 0 | H32: =SUMIF(S!$L:$L,$A32&UPPER(TEXT(H$4,"MMMMYYYY")),S!$AD:$AD) -> 0 | I32: =SUMIF(S!$L:$L,$A32&UPPER(TEXT(I$4,"MMMMYYYY")),S!$AD:$AD) -> 0 | J32: =SUMIF(S!$L:$L,$A32&UPPER(TEXT(J$4,"MMMMYYYY")),S!$AD:$AD) -> 0 | K32: =SUMIF(S!$L:$L,$A32&UPPER(TEXT(K$4,"MMMMYYYY")),S!$AD:$AD) -> 0 | ... O32: =SUMIF(S!$L:$L,$A32&UPPER(TEXT(O$4,"MMMMYYYY")),S!$AD:$AD) -> 0 | P32: =SUM(D32:O32) -> 0 | R32: =+D32/R$5 -> 0 | S32: =+E32/S$5 -> 0 | T32: =+F32/T$5 -> 0 | U32: =+G32/U$5 -> 0 | V32: =+H32/V$5 -> 0 | W32: =+I32/W$5 -> 0 | X32: =+J32/X$5 -> 0 | Y32: =+K32/Y$5 -> 0 | ... AC32: =+O32/AC$5 -> 0 | AF32: =+R32*AF$5 -> #REF! | AI32: =SUM(AF32:AH32) -> #REF! | AK32: =+IFERROR(AI32/AJ32,0) -> 0 | AM32: =+S32*AM$5 -> #REF! | AP32: =SUM(AM32:AO32) -> #REF! | AR32: =+IFERROR(AP32/AQ32,0) -> 0 | AT32: =+T32*AT$5 -> #REF! | AW32: =SUM(AT32:AV32) -> #REF! | AY32: =+IFERROR(AW32/AX32,0) -> 0 | BA32: =+U32*$BA$5 -> #REF! | BD32: =SUM(BA32:BC32) -> #REF! | BF32: =+IFERROR(BD32/BE32,0) -> 0 | BH32: =+V32*$BH$5 -> 0 | BK32: =SUM(BH32:BJ32) -> 0 | BM32: =+IFERROR(BK32/BL32,0) -> 0 | BR32: =SUM(BO32:BQ32) -> 0 | BT32: =+IFERROR(BR32/BS32,0) -> 0 | BV32: =+X32*$BV$5 -> 0 | BY32: =SUM(BV32:BX32) -> 0 | CA32: =+IFERROR(BY32/BZ32,0) -> 0 | CC32: =+Y32*$CC$5 -> 0 | CF32: =SUM(CC32:CE32) -> 0 | CH32: =+IFERROR(CF32/CG32,0) -> 0 | CJ32: =+Z32*$CJ$5 -> 0 | CM32: =SUM(CJ32:CL32) -> 0 | CO32: =+IFERROR(CM32/CN32,0) -> 0 | CQ32: =+AA32*$CQ$5 -> 0 | CT32: =SUM(CQ32:CS32) -> 0 | CV32: =+IFERROR(CT32/CU32,0) -> 0 | CX32: =+AB32*$CX$5 -> 0 | DA32: =SUM(CX32:CZ32) -> 0 | DC32: =+IFERROR(DA32/DB32,0) -> 0 | DE32: =+AC32*$DE$5 -> 0 | DH32: =SUM(DE32:DG32) -> 0 | DJ32: =+IFERROR(DH32/DI32,0) -> 0
A33: 91243310 | B33: Geofísica ME | C33: 9077127 0040 | D33: =SUMIF(S!$L:$L,$A33&UPPER(TEXT(D$4,"MMMMYYYY")),S!$AD:$AD) -> 0 | E33: =SUMIF(S!$L:$L,$A33&UPPER(TEXT(E$4,"MMMMYYYY")),S!$AD:$AD) -> 0 | F33: =SUMIF(S!$L:$L,$A33&UPPER(TEXT(F$4,"MMMMYYYY")),S!$AD:$AD) -> 0 | G33: =SUMIF(S!$L:$L,$A33&UPPER(TEXT(G$4,"MMMMYYYY")),S!$AD:$AD) -> 0 | H33: =SUMIF(S!$L:$L,$A33&UPPER(TEXT(H$4,"MMMMYYYY")),S!$AD:$AD) -> 0 | I33: =SUMIF(S!$L:$L,$A33&UPPER(TEXT(I$4,"MMMMYYYY")),S!$AD:$AD) -> 0 | J33: =SUMIF(S!$L:$L,$A33&UPPER(TEXT(J$4,"MMMMYYYY")),S!$AD:$AD) -> 0 | K33: =SUMIF(S!$L:$L,$A33&UPPER(TEXT(K$4,"MMMMYYYY")),S!$AD:$AD) -> 0 | ... O33: =SUMIF(S!$L:$L,$A33&UPPER(TEXT(O$4,"MMMMYYYY")),S!$AD:$AD) -> 0 | P33: =SUM(D33:O33) -> 0 | R33: =+D33/R$5 -> 0 | S33: =+E33/S$5 -> 0 | T33: =+F33/T$5 -> 0 | U33: =+G33/U$5 -> 0 | V33: =+H33/V$5 -> 0 | W33: =+I33/W$5 -> 0 | X33: =+J33/X$5 -> 0 | Y33: =+K33/Y$5 -> 0 | ... AC33: =+O33/AC$5 -> 0 | AF33: =+R33*AF$5 -> #REF! | AI33: =SUM(AF33:AH33) -> #REF! | AK33: =+IFERROR(AI33/AJ33,0) -> 0 | AM33: =+S33*AM$5 -> #REF! | AP33: =SUM(AM33:AO33) -> #REF! | AR33: =+IFERROR(AP33/AQ33,0) -> 0 | AT33: =+T33*AT$5 -> #REF! | AW33: =SUM(AT33:AV33) -> #REF! | AY33: =+IFERROR(AW33/AX33,0) -> 0 | BA33: =+U33*$BA$5 -> #REF! | BD33: =SUM(BA33:BC33) -> #REF! | BF33: =+IFERROR(BD33/BE33,0) -> 0 | BH33: =+V33*$BH$5 -> 0 | BK33: =SUM(BH33:BJ33) -> 0 | BM33: =+IFERROR(BK33/BL33,0) -> 0 | BR33: =SUM(BO33:BQ33) -> 0 | BT33: =+IFERROR(BR33/BS33,0) -> 0 | BV33: =+X33*$BV$5 -> 0 | BY33: =SUM(BV33:BX33) -> 0 | CA33: =+IFERROR(BY33/BZ33,0) -> 0 | CC33: =+Y33*$CC$5 -> 0 | CF33: =SUM(CC33:CE33) -> 0 | CH33: =+IFERROR(CF33/CG33,0) -> 0 | CJ33: =+Z33*$CJ$5 -> 0 | CM33: =SUM(CJ33:CL33) -> 0 | CO33: =+IFERROR(CM33/CN33,0) -> 0 | CQ33: =+AA33*$CQ$5 -> 0 | CT33: =SUM(CQ33:CS33) -> 0 | CV33: =+IFERROR(CT33/CU33,0) -> 0 | CX33: =+AB33*$CX$5 -> 0 | DA33: =SUM(CX33:CZ33) -> 0 | DC33: =+IFERROR(DA33/DB33,0) -> 0 | DE33: =+AC33*$DE$5 -> 0 | DH33: =SUM(DE33:DG33) -> 0 | DJ33: =+IFERROR(DH33/DI33,0) -> 0
A34: 91243510 | B34: Sondajes ME | C34: 9077127 0050 | D34: =SUMIF(S!$L:$L,$A34&UPPER(TEXT(D$4,"MMMMYYYY")),S!$AD:$AD) -> 0 | E34: =SUMIF(S!$L:$L,$A34&UPPER(TEXT(E$4,"MMMMYYYY")),S!$AD:$AD) -> 0 | F34: =SUMIF(S!$L:$L,$A34&UPPER(TEXT(F$4,"MMMMYYYY")),S!$AD:$AD) -> 0 | G34: =SUMIF(S!$L:$L,$A34&UPPER(TEXT(G$4,"MMMMYYYY")),S!$AD:$AD) -> 0 | H34: =SUMIF(S!$L:$L,$A34&UPPER(TEXT(H$4,"MMMMYYYY")),S!$AD:$AD) -> 0 | I34: =SUMIF(S!$L:$L,$A34&UPPER(TEXT(I$4,"MMMMYYYY")),S!$AD:$AD) -> 0 | J34: =SUMIF(S!$L:$L,$A34&UPPER(TEXT(J$4,"MMMMYYYY")),S!$AD:$AD) -> 0 | K34: =SUMIF(S!$L:$L,$A34&UPPER(TEXT(K$4,"MMMMYYYY")),S!$AD:$AD) -> 0 | ... O34: =SUMIF(S!$L:$L,$A34&UPPER(TEXT(O$4,"MMMMYYYY")),S!$AD:$AD) -> 0 | P34: =SUM(D34:O34) -> 0 | R34: =+D34/R$5 -> 0 | S34: =+E34/S$5 -> 0 | T34: =+F34/T$5 -> 0 | U34: =+G34/U$5 -> 0 | V34: =+H34/V$5 -> 0 | W34: =+I34/W$5 -> 0 | X34: =+J34/X$5 -> 0 | Y34: =+K34/Y$5 -> 0 | ... AC34: =+O34/AC$5 -> 0 | AF34: =+R34*AF$5 -> #REF! | AI34: =SUM(AF34:AH34) -> #REF! | AK34: =+IFERROR(AI34/AJ34,0) -> 0 | AM34: =+S34*AM$5 -> #REF! | AP34: =SUM(AM34:AO34) -> #REF! | AR34: =+IFERROR(AP34/AQ34,0) -> 0 | AT34: =+T34*AT$5 -> #REF! | AW34: =SUM(AT34:AV34) -> #REF! | AY34: =+IFERROR(AW34/AX34,0) -> 0 | BA34: =+U34*$BA$5 -> #REF! | BD34: =SUM(BA34:BC34) -> #REF! | BF34: =+IFERROR(BD34/BE34,0) -> 0 | BH34: =+V34*$BH$5 -> 0 | BK34: =SUM(BH34:BJ34) -> 0 | BM34: =+IFERROR(BK34/BL34,0) -> 0 | BR34: =SUM(BO34:BQ34) -> 0 | BT34: =+IFERROR(BR34/BS34,0) -> 0 | BV34: =+X34*$BV$5 -> 0 | BY34: =SUM(BV34:BX34) -> 0 | CA34: =+IFERROR(BY34/BZ34,0) -> 0 | CC34: =+Y34*$CC$5 -> 0 | CF34: =SUM(CC34:CE34) -> 0 | CH34: =+IFERROR(CF34/CG34,0) -> 0 | CJ34: =+Z34*$CJ$5 -> 0 | CM34: =SUM(CJ34:CL34) -> 0 | CO34: =+IFERROR(CM34/CN34,0) -> 0 | CQ34: =+AA34*$CQ$5 -> 0 | CT34: =SUM(CQ34:CS34) -> 0 | CV34: =+IFERROR(CT34/CU34,0) -> 0 | CX34: =+AB34*$CX$5 -> 0 | DA34: =SUM(CX34:CZ34) -> 0 | DC34: =+IFERROR(DA34/DB34,0) -> 0 | DE34: =+AC34*$DE$5 -> 0 | DH34: =SUM(DE34:DG34) -> 0 | DJ34: =+IFERROR(DH34/DI34,0) -> 0
A35: 91243520 | B35: Logística MN | C35: 9077127 0060 | D35: =SUMIF(S!$L:$L,$A35&UPPER(TEXT(D$4,"MMMMYYYY")),S!$AD:$AD) -> 15167985 | E35: =SUMIF(S!$L:$L,$A35&UPPER(TEXT(E$4,"MMMMYYYY")),S!$AD:$AD) -> 0 | F35: =SUMIF(S!$L:$L,$A35&UPPER(TEXT(F$4,"MMMMYYYY")),S!$AD:$AD) -> 0 | G35: =SUMIF(S!$L:$L,$A35&UPPER(TEXT(G$4,"MMMMYYYY")),S!$AD:$AD) -> 0 | H35: =SUMIF(S!$L:$L,$A35&UPPER(TEXT(H$4,"MMMMYYYY")),S!$AD:$AD) -> 0 | I35: =SUMIF(S!$L:$L,$A35&UPPER(TEXT(I$4,"MMMMYYYY")),S!$AD:$AD) -> 0 | J35: =SUMIF(S!$L:$L,$A35&UPPER(TEXT(J$4,"MMMMYYYY")),S!$AD:$AD) -> 0 | K35: =SUMIF(S!$L:$L,$A35&UPPER(TEXT(K$4,"MMMMYYYY")),S!$AD:$AD) -> 0 | ... O35: =SUMIF(S!$L:$L,$A35&UPPER(TEXT(O$4,"MMMMYYYY")),S!$AD:$AD) -> 0 | P35: =SUM(D35:O35) -> 15167985 | R35: =+D35/R$5 -> 18.355622 | S35: =+E35/S$5 -> 0 | T35: =+F35/T$5 -> 0 | U35: =+G35/U$5 -> 0 | V35: =+H35/V$5 -> 0 | W35: =+I35/W$5 -> 0 | X35: =+J35/X$5 -> 0 | Y35: =+K35/Y$5 -> 0 | ... AC35: =+O35/AC$5 -> 0 | AF35: =+R35*AG$5 -> #REF! | AI35: =SUM(AF35:AH35) -> #REF! | AK35: =+IFERROR(AI35/AJ35,0) -> 0 | AM35: =+S35*AM$5 -> #REF! | AP35: =SUM(AM35:AO35) -> #REF! | AR35: =+IFERROR(AP35/AQ35,0) -> 0 | AT35: =+T35*AT$5 -> #REF! | AW35: =SUM(AT35:AV35) -> #REF! | AY35: =+IFERROR(AW35/AX35,0) -> 0 | BA35: =+U35*$BA$5 -> #REF! | BD35: =SUM(BA35:BC35) -> #REF! | BF35: =+IFERROR(BD35/BE35,0) -> 0 | BH35: =+V35*$BH$5 -> 0 | BK35: =SUM(BH35:BJ35) -> 0 | BM35: =+IFERROR(BK35/BL35,0) -> 0 | BR35: =SUM(BO35:BQ35) -> 0 | BT35: =+IFERROR(BR35/BS35,0) -> 0 | BV35: =+X35*$BV$5 -> 0 | BY35: =SUM(BV35:BX35) -> 0 | CA35: =+IFERROR(BY35/BZ35,0) -> 0 | CC35: =+Y35*$CC$5 -> 0 | CF35: =SUM(CC35:CE35) -> 0 | CH35: =+IFERROR(CF35/CG35,0) -> 0 | CJ35: =+Z35*$CJ$5 -> 0 | CM35: =SUM(CJ35:CL35) -> 0 | CO35: =+IFERROR(CM35/CN35,0) -> 0 | CQ35: =+AA35*$CQ$5 -> 0 | CT35: =SUM(CQ35:CS35) -> 0 | CV35: =+IFERROR(CT35/CU35,0) -> 0 | CX35: =+AB35*$CX$5 -> 0 | DA35: =SUM(CX35:CZ35) -> 0 | DC35: =+IFERROR(DA35/DB35,0) -> 0 | DE35: =+AC35*$DE$5 -> 0 | DH35: =SUM(DE35:DG35) -> 0 | DJ35: =+IFERROR(DH35/DI35,0) -> 0
A36: 91243530 | B36: Logística ME | C36: 9077127 0070 | D36: =SUMIF(S!$L:$L,$A36&UPPER(TEXT(D$4,"MMMMYYYY")),S!$AD:$AD) -> 0 | E36: =SUMIF(S!$L:$L,$A36&UPPER(TEXT(E$4,"MMMMYYYY")),S!$AD:$AD) -> 0 | F36: =SUMIF(S!$L:$L,$A36&UPPER(TEXT(F$4,"MMMMYYYY")),S!$AD:$AD) -> 0 | G36: =SUMIF(S!$L:$L,$A36&UPPER(TEXT(G$4,"MMMMYYYY")),S!$AD:$AD) -> 0 | H36: =SUMIF(S!$L:$L,$A36&UPPER(TEXT(H$4,"MMMMYYYY")),S!$AD:$AD) -> 0 | I36: =SUMIF(S!$L:$L,$A36&UPPER(TEXT(I$4,"MMMMYYYY")),S!$AD:$AD) -> 0 | J36: =SUMIF(S!$L:$L,$A36&UPPER(TEXT(J$4,"MMMMYYYY")),S!$AD:$AD) -> 0 | K36: =SUMIF(S!$L:$L,$A36&UPPER(TEXT(K$4,"MMMMYYYY")),S!$AD:$AD) -> 0 | ... O36: =SUMIF(S!$L:$L,$A36&UPPER(TEXT(O$4,"MMMMYYYY")),S!$AD:$AD) -> 0 | P36: =SUM(D36:O36) -> 0 | R36: =+D36/R$5 -> 0 | S36: =+E36/S$5 -> 0 | T36: =+F36/T$5 -> 0 | U36: =+G36/U$5 -> 0 | V36: =+H36/V$5 -> 0 | W36: =+I36/W$5 -> 0 | X36: =+J36/X$5 -> 0 | Y36: =+K36/Y$5 -> 0 | ... AC36: =+O36/AC$5 -> 0 | AF36: =+R36*AF$5 -> #REF! | AI36: =SUM(AF36:AH36) -> #REF! | AK36: =+IFERROR(AI36/AJ36,0) -> 0 | AM36: =+S36*AM$5 -> #REF! | AP36: =SUM(AM36:AO36) -> #REF! | AR36: =+IFERROR(AP36/AQ36,0) -> 0 | AT36: =+T36*AT$5 -> #REF! | AW36: =SUM(AT36:AV36) -> #REF! | AY36: =+IFERROR(AW36/AX36,0) -> 0 | BA36: =+U36*$BA$5 -> #REF! | BD36: =SUM(BA36:BC36) -> #REF! | BF36: =+IFERROR(BD36/BE36,0) -> 0 | BH36: =+V36*$BH$5 -> 0 | BK36: =SUM(BH36:BJ36) -> 0 | BM36: =+IFERROR(BK36/BL36,0) -> 0 | BR36: =SUM(BO36:BQ36) -> 0 | BT36: =+IFERROR(BR36/BS36,0) -> 0 | BV36: =+X36*$BV$5 -> 0 | BY36: =SUM(BV36:BX36) -> 0 | CA36: =+IFERROR(BY36/BZ36,0) -> 0 | CC36: =+Y36*$CC$5 -> 0 | CF36: =SUM(CC36:CE36) -> 0 | CH36: =+IFERROR(CF36/CG36,0) -> 0 | CJ36: =+Z36*$CJ$5 -> 0 | CM36: =SUM(CJ36:CL36) -> 0 | CO36: =+IFERROR(CM36/CN36,0) -> 0 | CQ36: =+AA36*$CQ$5 -> 0 | CT36: =SUM(CQ36:CS36) -> 0 | CV36: =+IFERROR(CT36/CU36,0) -> 0 | CX36: =+AB36*$CX$5 -> 0 | DA36: =SUM(CX36:CZ36) -> 0 | DC36: =+IFERROR(DA36/DB36,0) -> 0 | DE36: =+AC36*$DE$5 -> 0 | DH36: =SUM(DE36:DG36) -> 0 | DJ36: =+IFERROR(DH36/DI36,0) -> 0
A37: 91243540 | B37: Propiedad Minera | C37: 9077127 0080 | D37: =SUMIF(S!$L:$L,$A37&UPPER(TEXT(D$4,"MMMMYYYY")),S!$AD:$AD) -> 0 | E37: =SUMIF(S!$L:$L,$A37&UPPER(TEXT(E$4,"MMMMYYYY")),S!$AD:$AD) -> 0 | F37: =SUMIF(S!$L:$L,$A37&UPPER(TEXT(F$4,"MMMMYYYY")),S!$AD:$AD) -> 0 | G37: =SUMIF(S!$L:$L,$A37&UPPER(TEXT(G$4,"MMMMYYYY")),S!$AD:$AD) -> 0 | H37: =SUMIF(S!$L:$L,$A37&UPPER(TEXT(H$4,"MMMMYYYY")),S!$AD:$AD) -> 0 | I37: =SUMIF(S!$L:$L,$A37&UPPER(TEXT(I$4,"MMMMYYYY")),S!$AD:$AD) -> 0 | J37: =SUMIF(S!$L:$L,$A37&UPPER(TEXT(J$4,"MMMMYYYY")),S!$AD:$AD) -> 0 | K37: =SUMIF(S!$L:$L,$A37&UPPER(TEXT(K$4,"MMMMYYYY")),S!$AD:$AD) -> 0 | ... O37: =SUMIF(S!$L:$L,$A37&UPPER(TEXT(O$4,"MMMMYYYY")),S!$AD:$AD) -> 0 | P37: =SUM(D37:O37) -> 0 | R37: =+D37/R$5 -> 0 | S37: =+E37/S$5 -> 0 | T37: =+F37/T$5 -> 0 | U37: =+G37/U$5 -> 0 | V37: =+H37/V$5 -> 0 | W37: =+I37/W$5 -> 0 | X37: =+J37/X$5 -> 0 | Y37: =+K37/Y$5 -> 0 | ... AC37: =+O37/AC$5 -> 0 | AF37: =+R37*AF$5 -> #REF! | AI37: =SUM(AF37:AH37) -> #REF! | AK37: =+IFERROR(AI37/AJ37,0) -> 0 | AM37: =+S37*AM$5 -> #REF! | AP37: =SUM(AM37:AO37) -> #REF! | AR37: =+IFERROR(AP37/AQ37,0) -> 0 | AT37: =+T37*AT$5 -> #REF! | AW37: =SUM(AT37:AV37) -> #REF! | AY37: =+IFERROR(AW37/AX37,0) -> 0 | BA37: =+U37*$BA$5 -> #REF! | BD37: =SUM(BA37:BC37) -> #REF! | BF37: =+IFERROR(BD37/BE37,0) -> 0 | BH37: =+V37*$BH$5 -> 0 | BK37: =SUM(BH37:BJ37) -> 0 | BM37: =+IFERROR(BK37/BL37,0) -> 0 | BR37: =SUM(BO37:BQ37) -> 0 | BT37: =+IFERROR(BR37/BS37,0) -> 0 | BV37: =+X37*$BV$5 -> 0 | BY37: =SUM(BV37:BX37) -> 0 | CA37: =+IFERROR(BY37/BZ37,0) -> 0 | CC37: =+Y37*$CC$5 -> 0 | CF37: =SUM(CC37:CE37) -> 0 | CH37: =+IFERROR(CF37/CG37,0) -> 0 | CJ37: =+Z37*$CJ$5 -> 0 | CM37: =SUM(CJ37:CL37) -> 0 | CO37: =+IFERROR(CM37/CN37,0) -> 0 | CQ37: =+AA37*$CQ$5 -> 0 | CT37: =SUM(CQ37:CS37) -> 0 | CV37: =+IFERROR(CT37/CU37,0) -> 0 | CX37: =+AB37*$CX$5 -> 0 | DA37: =SUM(CX37:CZ37) -> 0 | DC37: =+IFERROR(DA37/DB37,0) -> 0 | DE37: =+AC37*$DE$5 -> 0 | DH37: =SUM(DE37:DG37) -> 0 | DJ37: =+IFERROR(DH37/DI37,0) -> 0
A38: 91243550 | B38: Medio Ambiente MN | C38: 9077127 0090 | D38: =SUMIF(S!$L:$L,$A38&UPPER(TEXT(D$4,"MMMMYYYY")),S!$AD:$AD) -> 0 | E38: =SUMIF(S!$L:$L,$A38&UPPER(TEXT(E$4,"MMMMYYYY")),S!$AD:$AD) -> 0 | F38: =SUMIF(S!$L:$L,$A38&UPPER(TEXT(F$4,"MMMMYYYY")),S!$AD:$AD) -> 0 | G38: =SUMIF(S!$L:$L,$A38&UPPER(TEXT(G$4,"MMMMYYYY")),S!$AD:$AD) -> 0 | H38: =SUMIF(S!$L:$L,$A38&UPPER(TEXT(H$4,"MMMMYYYY")),S!$AD:$AD) -> 0 | I38: =SUMIF(S!$L:$L,$A38&UPPER(TEXT(I$4,"MMMMYYYY")),S!$AD:$AD) -> 0 | J38: =SUMIF(S!$L:$L,$A38&UPPER(TEXT(J$4,"MMMMYYYY")),S!$AD:$AD) -> 0 | K38: =SUMIF(S!$L:$L,$A38&UPPER(TEXT(K$4,"MMMMYYYY")),S!$AD:$AD) -> 0 | ... O38: =SUMIF(S!$L:$L,$A38&UPPER(TEXT(O$4,"MMMMYYYY")),S!$AD:$AD) -> 0 | P38: =SUM(D38:O38) -> 0 | R38: =+D38/R$5 -> 0 | S38: =+E38/S$5 -> 0 | T38: =+F38/T$5 -> 0 | U38: =+G38/U$5 -> 0 | V38: =+H38/V$5 -> 0 | W38: =+I38/W$5 -> 0 | X38: =+J38/X$5 -> 0 | Y38: =+K38/Y$5 -> 0 | ... AC38: =+O38/AC$5 -> 0 | AF38: =+R38*AF$5 -> #REF! | AI38: =SUM(AF38:AH38) -> #REF! | AK38: =+IFERROR(AI38/AJ38,0) -> 0 | AM38: =+S38*AM$5 -> #REF! | AP38: =SUM(AM38:AO38) -> #REF! | AR38: =+IFERROR(AP38/AQ38,0) -> 0 | AT38: =+T38*AT$5 -> #REF! | AW38: =SUM(AT38:AV38) -> #REF! | AY38: =+IFERROR(AW38/AX38,0) -> 0 | BA38: =+U38*$BA$5 -> #REF! | BD38: =SUM(BA38:BC38) -> #REF! | BF38: =+IFERROR(BD38/BE38,0) -> 0 | BH38: =+V38*$BH$5 -> 0 | BK38: =SUM(BH38:BJ38) -> 0 | BM38: =+IFERROR(BK38/BL38,0) -> 0 | BR38: =SUM(BO38:BQ38) -> 0 | BT38: =+IFERROR(BR38/BS38,0) -> 0 | BV38: =+X38*$BV$5 -> 0 | BY38: =SUM(BV38:BX38) -> 0 | CA38: =+IFERROR(BY38/BZ38,0) -> 0 | CC38: =+Y38*$CC$5 -> 0 | CF38: =SUM(CC38:CE38) -> 0 | CH38: =+IFERROR(CF38/CG38,0) -> 0 | CJ38: =+Z38*$CJ$5 -> 0 | CM38: =SUM(CJ38:CL38) -> 0 | CO38: =+IFERROR(CM38/CN38,0) -> 0 | CQ38: =+AA38*$CQ$5 -> 0 | CT38: =SUM(CQ38:CS38) -> 0 | CV38: =+IFERROR(CT38/CU38,0) -> 0 | CX38: =+AB38*$CX$5 -> 0 | DA38: =SUM(CX38:CZ38) -> 0 | DC38: =+IFERROR(DA38/DB38,0) -> 0 | DE38: =+AC38*$DE$5 -> 0 | DH38: =SUM(DE38:DG38) -> 0 | DJ38: =+IFERROR(DH38/DI38,0) -> 0
A39: 91243560 | B39: Medio Ambiente ME | C39: 9077127 00100 | D39: =SUMIF(S!$L:$L,$A39&UPPER(TEXT(D$4,"MMMMYYYY")),S!$AD:$AD) -> 0 | E39: =SUMIF(S!$L:$L,$A39&UPPER(TEXT(E$4,"MMMMYYYY")),S!$AD:$AD) -> 0 | F39: =SUMIF(S!$L:$L,$A39&UPPER(TEXT(F$4,"MMMMYYYY")),S!$AD:$AD) -> 0 | G39: =SUMIF(S!$L:$L,$A39&UPPER(TEXT(G$4,"MMMMYYYY")),S!$AD:$AD) -> 0 | H39: =SUMIF(S!$L:$L,$A39&UPPER(TEXT(H$4,"MMMMYYYY")),S!$AD:$AD) -> 0 | I39: =SUMIF(S!$L:$L,$A39&UPPER(TEXT(I$4,"MMMMYYYY")),S!$AD:$AD) -> 0 | J39: =SUMIF(S!$L:$L,$A39&UPPER(TEXT(J$4,"MMMMYYYY")),S!$AD:$AD) -> 0 | K39: =SUMIF(S!$L:$L,$A39&UPPER(TEXT(K$4,"MMMMYYYY")),S!$AD:$AD) -> 0 | ... O39: =SUMIF(S!$L:$L,$A39&UPPER(TEXT(O$4,"MMMMYYYY")),S!$AD:$AD) -> 0 | P39: =SUM(D39:O39) -> 0 | R39: =+D39/R$5 -> 0 | S39: =+E39/S$5 -> 0 | T39: =+F39/T$5 -> 0 | U39: =+G39/U$5 -> 0 | V39: =+H39/V$5 -> 0 | W39: =+I39/W$5 -> 0 | X39: =+J39/X$5 -> 0 | Y39: =+K39/Y$5 -> 0 | ... AC39: =+O39/AC$5 -> 0 | AF39: =+R39*AG$5 -> #REF! | AI39: =SUM(AF39:AH39) -> #REF! | AK39: =+IFERROR(AI39/AJ39,0) -> 0 | AM39: =+S39*AM$5 -> #REF! | AP39: =SUM(AM39:AO39) -> #REF! | AR39: =+IFERROR(AP39/AQ39,0) -> 0 | AT39: =+T39*AT$5 -> #REF! | AW39: =SUM(AT39:AV39) -> #REF! | AY39: =+IFERROR(AW39/AX39,0) -> 0 | BA39: =+U39*$BA$5 -> #REF! | BD39: =SUM(BA39:BC39) -> #REF! | BF39: =+IFERROR(BD39/BE39,0) -> 0 | BH39: =+V39*$BH$5 -> 0 | BK39: =SUM(BH39:BJ39) -> 0 | BM39: =+IFERROR(BK39/BL39,0) -> 0 | BR39: =SUM(BO39:BQ39) -> 0 | BT39: =+IFERROR(BR39/BS39,0) -> 0 | BV39: =+X39*$BV$5 -> 0 | BY39: =SUM(BV39:BX39) -> 0 | CA39: =+IFERROR(BY39/BZ39,0) -> 0 | CC39: =+Y39*$CC$5 -> 0 | CF39: =SUM(CC39:CE39) -> 0 | CH39: =+IFERROR(CF39/CG39,0) -> 0 | CJ39: =+Z39*$CJ$5 -> 0 | CM39: =SUM(CJ39:CL39) -> 0 | CO39: =+IFERROR(CM39/CN39,0) -> 0 | CQ39: =+AA39*$CQ$5 -> 0 | CT39: =SUM(CQ39:CS39) -> 0 | CV39: =+IFERROR(CT39/CU39,0) -> 0 | CX39: =+AB39*$CX$5 -> 0 | DA39: =SUM(CX39:CZ39) -> 0 | DC39: =+IFERROR(DA39/DB39,0) -> 0 | DE39: =+AC39*$DE$5 -> 0 | DH39: =SUM(DE39:DG39) -> 0 | DJ39: =+IFERROR(DH39/DI39,0) -> 0
A40: 91243570 | B40: Seguridad ME | C40: 9077127 00110 | D40: =SUMIF(S!$L:$L,$A40&UPPER(TEXT(D$4,"MMMMYYYY")),S!$AD:$AD) -> 0 | E40: =SUMIF(S!$L:$L,$A40&UPPER(TEXT(E$4,"MMMMYYYY")),S!$AD:$AD) -> 0 | F40: =SUMIF(S!$L:$L,$A40&UPPER(TEXT(F$4,"MMMMYYYY")),S!$AD:$AD) -> 0 | G40: =SUMIF(S!$L:$L,$A40&UPPER(TEXT(G$4,"MMMMYYYY")),S!$AD:$AD) -> 0 | H40: =SUMIF(S!$L:$L,$A40&UPPER(TEXT(H$4,"MMMMYYYY")),S!$AD:$AD) -> 0 | I40: =SUMIF(S!$L:$L,$A40&UPPER(TEXT(I$4,"MMMMYYYY")),S!$AD:$AD) -> 0 | J40: =SUMIF(S!$L:$L,$A40&UPPER(TEXT(J$4,"MMMMYYYY")),S!$AD:$AD) -> 0 | K40: =SUMIF(S!$L:$L,$A40&UPPER(TEXT(K$4,"MMMMYYYY")),S!$AD:$AD) -> 0 | ... O40: =SUMIF(S!$L:$L,$A40&UPPER(TEXT(O$4,"MMMMYYYY")),S!$AD:$AD) -> 0 | P40: =SUM(D40:O40) -> 0 | R40: =+D40/R$5 -> 0 | S40: =+E40/S$5 -> 0 | T40: =+F40/T$5 -> 0 | U40: =+G40/U$5 -> 0 | V40: =+H40/V$5 -> 0 | W40: =+I40/W$5 -> 0 | X40: =+J40/X$5 -> 0 | Y40: =+K40/Y$5 -> 0 | ... AC40: =+O40/AC$5 -> 0 | AF40: =+R40*AG$5 -> #REF! | AI40: =SUM(AF40:AH40) -> #REF! | AK40: =+IFERROR(AI40/AJ40,0) -> 0 | AM40: =+S40*AM$5 -> #REF! | AP40: =SUM(AM40:AO40) -> #REF! | AR40: =+IFERROR(AP40/AQ40,0) -> 0 | AT40: =+T40*AT$5 -> #REF! | AW40: =SUM(AT40:AV40) -> #REF! | AY40: =+IFERROR(AW40/AX40,0) -> 0 | BA40: =+U40*$BA$5 -> #REF! | BD40: =SUM(BA40:BC40) -> #REF! | BF40: =+IFERROR(BD40/BE40,0) -> 0 | BH40: =+V40*$BH$5 -> 0 | BK40: =SUM(BH40:BJ40) -> 0 | BM40: =+IFERROR(BK40/BL40,0) -> 0 | BR40: =SUM(BO40:BQ40) -> 0 | BT40: =+IFERROR(BR40/BS40,0) -> 0 | BV40: =+X40*$BV$5 -> 0 | BY40: =SUM(BV40:BX40) -> 0 | CA40: =+IFERROR(BY40/BZ40,0) -> 0 | CC40: =+Y40*$CC$5 -> 0 | CF40: =SUM(CC40:CE40) -> 0 | CH40: =+IFERROR(CF40/CG40,0) -> 0 | CJ40: =+Z40*$CJ$5 -> 0 | CM40: =SUM(CJ40:CL40) -> 0 | CO40: =+IFERROR(CM40/CN40,0) -> 0 | CQ40: =+AA40*$CQ$5 -> 0 | CT40: =SUM(CQ40:CS40) -> 0 | CV40: =+IFERROR(CT40/CU40,0) -> 0 | CX40: =+AB40*$CX$5 -> 0 | DA40: =SUM(CX40:CZ40) -> 0 | DC40: =+IFERROR(DA40/DB40,0) -> 0 | DE40: =+AC40*$DE$5 -> 0 | DH40: =SUM(DE40:DG40) -> 0 | DJ40: =+IFERROR(DH40/DI40,0) -> 0
A41: 91243710 | B41: Comunidades ME | C41: 9077127 00120 | D41: =SUMIF(S!$L:$L,$A41&UPPER(TEXT(D$4,"MMMMYYYY")),S!$AD:$AD) -> 0 | E41: =SUMIF(S!$L:$L,$A41&UPPER(TEXT(E$4,"MMMMYYYY")),S!$AD:$AD) -> 0 | F41: =SUMIF(S!$L:$L,$A41&UPPER(TEXT(F$4,"MMMMYYYY")),S!$AD:$AD) -> 0 | G41: =SUMIF(S!$L:$L,$A41&UPPER(TEXT(G$4,"MMMMYYYY")),S!$AD:$AD) -> 0 | H41: =SUMIF(S!$L:$L,$A41&UPPER(TEXT(H$4,"MMMMYYYY")),S!$AD:$AD) -> 0 | I41: =SUMIF(S!$L:$L,$A41&UPPER(TEXT(I$4,"MMMMYYYY")),S!$AD:$AD) -> 0 | J41: =SUMIF(S!$L:$L,$A41&UPPER(TEXT(J$4,"MMMMYYYY")),S!$AD:$AD) -> 0 | K41: =SUMIF(S!$L:$L,$A41&UPPER(TEXT(K$4,"MMMMYYYY")),S!$AD:$AD) -> 0 | ... O41: =SUMIF(S!$L:$L,$A41&UPPER(TEXT(O$4,"MMMMYYYY")),S!$AD:$AD) -> 0 | P41: =SUM(D41:O41) -> 0 | R41: =+D41/R$5 -> 0 | S41: =+E41/S$5 -> 0 | T41: =+F41/T$5 -> 0 | U41: =+G41/U$5 -> 0 | V41: =+H41/V$5 -> 0 | W41: =+I41/W$5 -> 0 | X41: =+J41/X$5 -> 0 | Y41: =+K41/Y$5 -> 0 | ... AC41: =+O41/AC$5 -> 0 | AF41: =+R41*AG$5 -> #REF! | AI41: =SUM(AF41:AH41) -> #REF! | AK41: =+IFERROR(AI41/AJ41,0) -> 0 | AM41: =+S41*AM$5 -> #REF! | AP41: =SUM(AM41:AO41) -> #REF! | AR41: =+IFERROR(AP41/AQ41,0) -> 0 | AT41: =+T41*AT$5 -> #REF! | AW41: =SUM(AT41:AV41) -> #REF! | AY41: =+IFERROR(AW41/AX41,0) -> 0 | BA41: =+U41*$BA$5 -> #REF! | BD41: =SUM(BA41:BC41) -> #REF! | BF41: =+IFERROR(BD41/BE41,0) -> 0 | BH41: =+V41*$BH$5 -> 0 | BK41: =SUM(BH41:BJ41) -> 0 | BM41: =+IFERROR(BK41/BL41,0) -> 0 | BR41: =SUM(BO41:BQ41) -> 0 | BT41: =+IFERROR(BR41/BS41,0) -> 0 | BV41: =+X41*$BV$5 -> 0 | BY41: =SUM(BV41:BX41) -> 0 | CA41: =+IFERROR(BY41/BZ41,0) -> 0 | CC41: =+Y41*$CC$5 -> 0 | CF41: =SUM(CC41:CE41) -> 0 | CH41: =+IFERROR(CF41/CG41,0) -> 0 | CJ41: =+Z41*$CJ$5 -> 0 | CM41: =SUM(CJ41:CL41) -> 0 | CO41: =+IFERROR(CM41/CN41,0) -> 0 | CQ41: =+AA41*$CQ$5 -> 0 | CT41: =SUM(CQ41:CS41) -> 0 | CV41: =+IFERROR(CT41/CU41,0) -> 0 | CX41: =+AB41*$CX$5 -> 0 | DA41: =SUM(CX41:CZ41) -> 0 | DC41: =+IFERROR(DA41/DB41,0) -> 0 | DE41: =+AC41*$DE$5 -> 0 | DH41: =SUM(DE41:DG41) -> 0 | DJ41: =+IFERROR(DH41/DI41,0) -> 0
A42: 91243720 | B42: Administración MN | C42: 9077127 00130 | D42: =SUMIF(S!$L:$L,$A42&UPPER(TEXT(D$4,"MMMMYYYY")),S!$AD:$AD) -> 0 | E42: =SUMIF(S!$L:$L,$A42&UPPER(TEXT(E$4,"MMMMYYYY")),S!$AD:$AD) -> 0 | F42: =SUMIF(S!$L:$L,$A42&UPPER(TEXT(F$4,"MMMMYYYY")),S!$AD:$AD) -> 0 | G42: =SUMIF(S!$L:$L,$A42&UPPER(TEXT(G$4,"MMMMYYYY")),S!$AD:$AD) -> 0 | H42: =SUMIF(S!$L:$L,$A42&UPPER(TEXT(H$4,"MMMMYYYY")),S!$AD:$AD) -> 0 | I42: =SUMIF(S!$L:$L,$A42&UPPER(TEXT(I$4,"MMMMYYYY")),S!$AD:$AD) -> 0 | J42: =SUMIF(S!$L:$L,$A42&UPPER(TEXT(J$4,"MMMMYYYY")),S!$AD:$AD) -> 0 | K42: =SUMIF(S!$L:$L,$A42&UPPER(TEXT(K$4,"MMMMYYYY")),S!$AD:$AD) -> 0 | ... O42: =SUMIF(S!$L:$L,$A42&UPPER(TEXT(O$4,"MMMMYYYY")),S!$AD:$AD) -> 0 | P42: =SUM(D42:O42) -> 0 | R42: =+D42/R$5 -> 0 | S42: =+E42/S$5 -> 0 | T42: =+F42/T$5 -> 0 | U42: =+G42/U$5 -> 0 | V42: =+H42/V$5 -> 0 | W42: =+I42/W$5 -> 0 | X42: =+J42/X$5 -> 0 | Y42: =+K42/Y$5 -> 0 | ... AC42: =+O42/AC$5 -> 0 | AF42: =+R42*AF$5 -> #REF! | AI42: =SUM(AF42:AH42) -> #REF! | AK42: =+IFERROR(AI42/AJ42,0) -> 0 | AM42: =+S42*AM$5 -> #REF! | AP42: =SUM(AM42:AO42) -> #REF! | AR42: =+IFERROR(AP42/AQ42,0) -> 0 | AT42: =+T42*AT$5 -> #REF! | AW42: =SUM(AT42:AV42) -> #REF! | AY42: =+IFERROR(AW42/AX42,0) -> 0 | BA42: =+U42*$BA$5 -> #REF! | BD42: =SUM(BA42:BC42) -> #REF! | BF42: =+IFERROR(BD42/BE42,0) -> 0 | BH42: =+V42*$BH$5 -> 0 | BK42: =SUM(BH42:BJ42) -> 0 | BM42: =+IFERROR(BK42/BL42,0) -> 0 | BR42: =SUM(BO42:BQ42) -> 0 | BT42: =+IFERROR(BR42/BS42,0) -> 0 | BV42: =+X42*$BV$5 -> 0 | BY42: =SUM(BV42:BX42) -> 0 | CA42: =+IFERROR(BY42/BZ42,0) -> 0 | CC42: =+Y42*$CC$5 -> 0 | CF42: =SUM(CC42:CE42) -> 0 | CH42: =+IFERROR(CF42/CG42,0) -> 0 | CJ42: =+Z42*$CJ$5 -> 0 | CM42: =SUM(CJ42:CL42) -> 0 | CO42: =+IFERROR(CM42/CN42,0) -> 0 | CQ42: =+AA42*$CQ$5 -> 0 | CT42: =SUM(CQ42:CS42) -> 0 | CV42: =+IFERROR(CT42/CU42,0) -> 0 | CX42: =+AB42*$CX$5 -> 0 | DA42: =SUM(CX42:CZ42) -> 0 | DC42: =+IFERROR(DA42/DB42,0) -> 0 | DE42: =+AC42*$DE$5 -> 0 | DH42: =SUM(DE42:DG42) -> 0 | DJ42: =+IFERROR(DH42/DI42,0) -> 0
A43: 91243730 | B43: Contingencia MN | C43: 9077127 00140 | D43: =SUMIF(S!$L:$L,$A43&UPPER(TEXT(D$4,"MMMMYYYY")),S!$AD:$AD) -> 0 | E43: =SUMIF(S!$L:$L,$A43&UPPER(TEXT(E$4,"MMMMYYYY")),S!$AD:$AD) -> 0 | F43: =SUMIF(S!$L:$L,$A43&UPPER(TEXT(F$4,"MMMMYYYY")),S!$AD:$AD) -> 0 | G43: =SUMIF(S!$L:$L,$A43&UPPER(TEXT(G$4,"MMMMYYYY")),S!$AD:$AD) -> 0 | H43: =SUMIF(S!$L:$L,$A43&UPPER(TEXT(H$4,"MMMMYYYY")),S!$AD:$AD) -> 0 | I43: =SUMIF(S!$L:$L,$A43&UPPER(TEXT(I$4,"MMMMYYYY")),S!$AD:$AD) -> 0 | J43: =SUMIF(S!$L:$L,$A43&UPPER(TEXT(J$4,"MMMMYYYY")),S!$AD:$AD) -> 0 | K43: =SUMIF(S!$L:$L,$A43&UPPER(TEXT(K$4,"MMMMYYYY")),S!$AD:$AD) -> 0 | ... O43: =SUMIF(S!$L:$L,$A43&UPPER(TEXT(O$4,"MMMMYYYY")),S!$AD:$AD) -> 0 | P43: =SUM(D43:O43) -> 0 | R43: =+D43/R$5 -> 0 | S43: =+E43/S$5 -> 0 | T43: =+F43/T$5 -> 0 | U43: =+G43/U$5 -> 0 | V43: =+H43/V$5 -> 0 | W43: =+I43/W$5 -> 0 | X43: =+J43/X$5 -> 0 | Y43: =+K43/Y$5 -> 0 | ... AC43: =+O43/AC$5 -> 0 | AF43: =+R43*AF$5 -> #REF! | AI43: =SUM(AF43:AH43) -> #REF! | AK43: =+IFERROR(AI43/AJ43,0) -> 0 | AM43: =+S43*AM$5 -> #REF! | AP43: =SUM(AM43:AO43) -> #REF! | AR43: =+IFERROR(AP43/AQ43,0) -> 0 | AT43: =+T43*AT$5 -> #REF! | AW43: =SUM(AT43:AV43) -> #REF! | AY43: =+IFERROR(AW43/AX43,0) -> 0 | BA43: =+U43*$BA$5 -> #REF! | BD43: =SUM(BA43:BC43) -> #REF! | BF43: =+IFERROR(BD43/BE43,0) -> 0 | BH43: =+V43*$BH$5 -> 0 | BK43: =SUM(BH43:BJ43) -> 0 | BM43: =+IFERROR(BK43/BL43,0) -> 0 | BR43: =SUM(BO43:BQ43) -> 0 | BT43: =+IFERROR(BR43/BS43,0) -> 0 | BV43: =+X43*$BV$5 -> 0 | BY43: =SUM(BV43:BX43) -> 0 | CA43: =+IFERROR(BY43/BZ43,0) -> 0 | CC43: =+Y43*$CC$5 -> 0 | CF43: =SUM(CC43:CE43) -> 0 | CH43: =+IFERROR(CF43/CG43,0) -> 0 | CJ43: =+Z43*$CJ$5 -> 0 | CM43: =SUM(CJ43:CL43) -> 0 | CO43: =+IFERROR(CM43/CN43,0) -> 0 | CQ43: =+AA43*$CQ$5 -> 0 | CT43: =SUM(CQ43:CS43) -> 0 | CV43: =+IFERROR(CT43/CU43,0) -> 0 | CX43: =+AB43*$CX$5 -> 0 | DA43: =SUM(CX43:CZ43) -> 0 | DC43: =+IFERROR(DA43/DB43,0) -> 0 | DE43: =+AC43*$DE$5 -> 0 | DH43: =SUM(DE43:DG43) -> 0 | DJ43: =+IFERROR(DH43/DI43,0) -> 0
A44: 912439 | B44: GESTIÓN EJECUCIÓN PROYECTO | D44: =+SUM(D45:D46) -> 1092757 | E44: =+SUM(E45:E46) -> 0 | F44: =+SUM(F45:F46) -> 0 | G44: =+SUM(G45:G46) -> 0 | H44: =+SUM(H45:H46) -> 0 | I44: =+SUM(I45:I46) -> 0 | J44: =+SUM(J45:J46) -> 0 | K44: =+SUM(K45:K46) -> 0 | ... O44: =+SUM(O45:O46) -> 0 | R44: =+SUM(R45:R46) -> 1.322406 | AF44: =AF45+AF46 -> #REF! | AG44: =AG45+AG46 -> 0 | AH44: =AH45+AH46 -> 0 | AI44: =AI45+AI46 -> #REF! | AJ44: =AJ45+AJ46 -> 0 | AK44: =AK45+AK46 -> 0 | AL44: =AL45+AL46 -> 0 | AM44: =AM45+AM46 -> #REF! | ... DJ44: =DJ45+DJ46 -> 0
A45: 91243910 | B45:  FEE M.O. | C45: 9077127 00150 | D45: =SUMIF(S!$L:$L,$A45&UPPER(TEXT(D$4,"MMMMYYYY")),S!$AD:$AD) -> 499293 | E45: =SUMIF(S!$L:$L,$A45&UPPER(TEXT(E$4,"MMMMYYYY")),S!$AD:$AD) -> 0 | F45: =SUMIF(S!$L:$L,$A45&UPPER(TEXT(F$4,"MMMMYYYY")),S!$AD:$AD) -> 0 | G45: =SUMIF(S!$L:$L,$A45&UPPER(TEXT(G$4,"MMMMYYYY")),S!$AD:$AD) -> 0 | H45: =SUMIF(S!$L:$L,$A45&UPPER(TEXT(H$4,"MMMMYYYY")),S!$AD:$AD) -> 0 | I45: =SUMIF(S!$L:$L,$A45&UPPER(TEXT(I$4,"MMMMYYYY")),S!$AD:$AD) -> 0 | J45: =SUMIF(S!$L:$L,$A45&UPPER(TEXT(J$4,"MMMMYYYY")),S!$AD:$AD) -> 0 | K45: =SUMIF(S!$L:$L,$A45&UPPER(TEXT(K$4,"MMMMYYYY")),S!$AD:$AD) -> 0 | ... O45: =SUMIF(S!$L:$L,$A45&UPPER(TEXT(O$4,"MMMMYYYY")),S!$AD:$AD) -> 0 | R45: =+D45/R$5 -> 0.60422223 | S45: =+E45/S$5 -> 0 | T45: =+F45/T$5 -> 0 | U45: =+G45/U$5 -> 0 | V45: =+H45/V$5 -> 0 | W45: =+I45/W$5 -> 0 | X45: =+J45/X$5 -> 0 | Y45: =+K45/Y$5 -> 0 | ... AC45: =+O45/AC$5 -> 0 | AF45: =+R45*AF$5 -> #REF! | AI45: =SUM(AF45:AH45) -> #REF! | AK45: =+IFERROR(AI45/AJ45,0) -> 0 | AM45: =+S45*AM$5 -> #REF! | AP45: =SUM(AM45:AO45) -> #REF! | AR45: =+IFERROR(AP45/AQ45,0) -> 0 | AT45: =+T45*AT$5 -> #REF! | AW45: =SUM(AT45:AV45) -> #REF! | AY45: =+IFERROR(AW45/AX45,0) -> 0 | BA45: =+U45*$BA$5 -> #REF! | BC45: =(#REF!+#REF!)/1000 -> #REF! | BD45: =SUM(BA45:BC45) -> #REF! | BF45: =+IFERROR(BD45/BE45,0) -> 0 | BH45: =+V45*$BH$5 -> 0 | BK45: =SUM(BH45:BJ45) -> 0 | BM45: =+IFERROR(BK45/BL45,0) -> 0 | BR45: =SUM(BO45:BQ45) -> 0 | BT45: =+IFERROR(BR45/BS45,0) -> 0 | BV45: =+X45*$BV$5 -> 0 | BY45: =SUM(BV45:BX45) -> 0 | CA45: =+IFERROR(BY45/BZ45,0) -> 0 | CC45: =+Y45*$CC$5 -> 0 | CF45: =SUM(CC45:CE45) -> 0 | CH45: =+IFERROR(CF45/CG45,0) -> 0 | CJ45: =+Z45*$CJ$5 -> 0 | CM45: =SUM(CJ45:CL45) -> 0 | CO45: =+IFERROR(CM45/CN45,0) -> 0 | CQ45: =+AA45*$CQ$5 -> 0 | CT45: =SUM(CQ45:CS45) -> 0 | CV45: =+IFERROR(CT45/CU45,0) -> 0 | CX45: =+AB45*$CX$5 -> 0 | DA45: =SUM(CX45:CZ45) -> 0 | DC45: =+IFERROR(DA45/DB45,0) -> 0 | DE45: =+AC45*$DE$5 -> 0 | DH45: =SUM(DE45:DG45) -> 0 | DJ45: =+IFERROR(DH45/DI45,0) -> 0
A46: 91243920 | B46:  FEE S.S. | C46: 9077127 00160 | D46: =SUMIF(S!$L:$L,$A46&UPPER(TEXT(D$4,"MMMMYYYY")),S!$AD:$AD) -> 593464 | E46: =SUMIF(S!$L:$L,$A46&UPPER(TEXT(E$4,"MMMMYYYY")),S!$AD:$AD) -> 0 | F46: =SUMIF(S!$L:$L,$A46&UPPER(TEXT(F$4,"MMMMYYYY")),S!$AD:$AD) -> 0 | G46: =SUMIF(S!$L:$L,$A46&UPPER(TEXT(G$4,"MMMMYYYY")),S!$AD:$AD) -> 0 | H46: =SUMIF(S!$L:$L,$A46&UPPER(TEXT(H$4,"MMMMYYYY")),S!$AD:$AD) -> 0 | I46: =SUMIF(S!$L:$L,$A46&UPPER(TEXT(I$4,"MMMMYYYY")),S!$AD:$AD) -> 0 | J46: =SUMIF(S!$L:$L,$A46&UPPER(TEXT(J$4,"MMMMYYYY")),S!$AD:$AD) -> 0 | K46: =SUMIF(S!$L:$L,$A46&UPPER(TEXT(K$4,"MMMMYYYY")),S!$AD:$AD) -> 0 | ... O46: =SUMIF(S!$L:$L,$A46&UPPER(TEXT(O$4,"MMMMYYYY")),S!$AD:$AD) -> 0 | R46: =+D46/R$5 -> 0.7181838 | S46: =+E46/S$5 -> 0 | T46: =+F46/T$5 -> 0 | U46: =+G46/U$5 -> 0 | V46: =+H46/V$5 -> 0 | W46: =+I46/W$5 -> 0 | X46: =+J46/X$5 -> 0 | Y46: =+K46/Y$5 -> 0 | ... AC46: =+O46/AC$5 -> 0 | AF46: =+R46*AF$5 -> #REF! | AI46: =SUM(AF46:AH46) -> #REF! | AK46: =+IFERROR(AI46/AJ46,0) -> 0 | AM46: =+S46*AM$5 -> #REF! | AP46: =SUM(AM46:AO46) -> #REF! | AR46: =+IFERROR(AP46/AQ46,0) -> 0 | AT46: =+T46*AT$5 -> #REF! | AW46: =SUM(AT46:AV46) -> #REF! | AY46: =+IFERROR(AW46/AX46,0) -> 0 | BA46: =+U46*$BA$5 -> #REF! | BD46: =SUM(BA46:BC46) -> #REF! | BF46: =+IFERROR(BD46/BE46,0) -> 0 | BH46: =+V46*$BH$5 -> 0 | BK46: =SUM(BH46:BJ46) -> 0 | BM46: =+IFERROR(BK46/BL46,0) -> 0 | BR46: =SUM(BO46:BQ46) -> 0 | BT46: =+IFERROR(BR46/BS46,0) -> 0 | BV46: =+X46*$BV$5 -> 0 | BY46: =SUM(BV46:BX46) -> 0 | CA46: =+IFERROR(BY46/BZ46,0) -> 0 | CC46: =+Y46*$CC$5 -> 0 | CF46: =SUM(CC46:CE46) -> 0 | CH46: =+IFERROR(CF46/CG46,0) -> 0 | CJ46: =+Z46*$CJ$5 -> 0 | CM46: =SUM(CJ46:CL46) -> 0 | CO46: =+IFERROR(CM46/CN46,0) -> 0 | CQ46: =+AA46*$CQ$5 -> 0 | CT46: =SUM(CQ46:CS46) -> 0 | CV46: =+IFERROR(CT46/CU46,0) -> 0 | CX46: =+AB46*$CX$5 -> 0 | DA46: =SUM(CX46:CZ46) -> 0 | DC46: =+IFERROR(DA46/DB46,0) -> 0 | DE46: =+AC46*$DE$5 -> 0 | DH46: =SUM(DE46:DG46) -> 0 | DJ46: =+IFERROR(DH46/DI46,0) -> 0
A47: 912439 | B47: COSTOS DEL DUEÑO | R47: =+SUM(R48:R49) -> 0 | AF47: =AF48+AF49 -> #REF! | AG47: =AG48+AG49 -> #REF! | AH47: =AH48+AH49 -> #REF! | AI47: =AI48+AI49 -> #REF! | AJ47: =AJ48+AJ49 -> #REF! | AK47: =AK48+AK49 -> #REF! | AL47: =AL48+AL49 -> 0 | AM47: =AM48+AM49 -> #REF! | ... DJ47: =DJ48+DJ49 -> #REF!
B48: COSTOS DEL DUEÑO | C48: 9077127 00170
A49: TOTAL EXPLORACIONES MINERAS S.A. | D49: =+D6 -> 45953008 | E49: =+E6 -> 0 | F49: =+F6 -> 0 | G49: =+G6 -> 0 | H49: =+H6 -> 0 | I49: =+I6 -> 0 | J49: =+J6 -> 0 | K49: =+K6 -> 0 | ... P49: =+P6 -> 45953008 | R49: =R6 -> 0 | S49: =S6 -> 0 | T49: =T6 -> 0 | U49: =U6 -> 0 | V49: =V6 -> 0 | W49: =W6 -> 0 | X49: =X6 -> 0 | Y49: =Y6 -> 0 | ... AD49: =AD6 -> 0 | AF49: =AF6 -> #REF! | AG49: =AG6 -> #REF! | AH49: =AH6 -> #REF! | AI49: =AI6 -> #REF! | AJ49: =AJ6 -> #REF! | AK49: =AK6 -> #REF! | AL49: =AL6 -> 0 | AM49: =AM6 -> #REF! | ... DJ49: =DJ6 -> #REF!
Y50: =Y49*1000 -> 0
M54: 1249526
M55: 221589
M57: =#REF!-M54 -> #REF!
M58: 409055
D62: 63564933 | E62: 46611541 | F62: 174953036 | G62: 61050594 | H62: 113651262 | I62: 47252442 | J62: 34676407 | K62: 38542361 | L62: 59839634 | M62: 40435947 | N62: 39920966 | P62: =SUM(D62:O62) -> 720499123
D63: =D49-D62 -> -17611925 | E63: =E49-E62 -> -46611541 | F63: =F49-F62 -> -174953036 | G63: =G49-G62 -> -61050594 | H63: =H49-H62 -> -113651262 | I63: =I49-I62 -> -47252442 | J63: =J49-J62 -> -34676407 | K63: =K49-K62 -> -38542361 | ... N63: =N49-N62 -> -39920966

Sheet Hoja2
A2: TOTAL API | B2: TOTAL REPORTADO
A3: ='REPORTE GEX'!P6 -> 45953008 | B3: 239363205

Sheet Hoja1
A3: Etiquetas de fila | B3: Suma de ago-24 | C3: Suma de sept-24 | D3: Suma de oct-24 | E3: Suma de nov-24 | F3: Suma de dic-24 | G3: Suma de ene-25 | H3: Suma de feb-25 | I3: Suma de mar-25 | J3: Suma de abr-25
A4: 91243110 | B4: 12414.414 | C4: 10211.977 | D4: 23583.225 | E4: 31835.244 | F4: 28423.264 | G4: 36868.958 | H4: 17477.908 | I4: 47377.053 | J4: 9906.7081
A5: 91243120 | B5: 0 | C5: 0 | D5: 11578.894 | E5: 38660.914 | F5: 9755.9367 | G5: 4261.2298 | H5: 0 | I5: 1888.5338 | J5: 3301.947
A6: 91243310 | B6: 0 | C6: 0 | D6: 0 | E6: 0 | F6: 0 | G6: 0 | H6: 0 | I6: 0 | J6: 0
A7: 91243510 | B7: 0 | C7: 0 | D7: 0 | E7: 0 | F7: 0 | G7: 0 | H7: 0 | I7: 0 | J7: 0
A8: 91243520 | B8: 8918.5656 | C8: 13731.982 | D8: 15531.106 | E8: 2841.9902 | F8: 3394.5186 | G8: 0 | H8: 0 | I8: 8092.6685 | J8: 0
A9: 91243530 | B9: 0 | C9: 0 | D9: 4713.5532 | E9: -4538.8262 | F9: 0 | G9: 0 | H9: 0 | I9: 0 | J9: 0
A10: 91243910 | B10: 472.44271 | C10: 547.89513 | D10: 1435.8927 | E10: 914.86894 | F10: 1830.1247 | G10: 1701.545 | H10: 504.81272 | I10: 424.6829 | J10: 224.55224
A11: 91243920 | B11: 6.7152632 | C11: 333.5616 | D11: 1245.0757 | E11: 847.77935 | F11: 923.06434 | G11: 538.82419 | H11: 207.90363 | I11: 116.5929 | J11: 227.48231
A12: 91243720 | B12: 0 | C12: 0 | D12: 0 | E12: 0 | F12: 0 | G12: 0 | H12: 2935.1506 | I12: 77.168442 | J12: 0
A13: 91243730 | B13: 0 | C13: 0 | D13: 0 | E13: 0 | F13: 0 | G13: 0 | H13: 0 | I13: 0 | J13: 0
A14: 91243710 | B14: 0 | C14: 0 | D14: 0 | E14: 0 | F14: 0 | G14: 0 | H14: 0 | I14: 0 | J14: 0
A15: 91243540 | B15: 0 | C15: 0 | D15: 0 | E15: 0 | F15: 0 | G15: 0 | H15: 0 | I15: 0 | J15: 0
A16: (en blanco) | B16: 0 | C16: 0 | D16: 0 | E16: 0 | F16: 0 | G16: 0 | H16: 0 | I16: 0 | J16: 0
A17: Total general | B17: 21812.137 | C17: 24825.416 | D17: 58087.746 | E17: 70561.97 | F17: 44326.908 | G17: 43370.557 | H17: 21125.775 | I17: 57976.7 | J17: 13660.69
M22: =SUM(B22:J22) -> 0
B26: 91243110 | C26: =VLOOKUP(B26,'G (G.C)'!$B$29:$C$44,2,0) -> #N/A | D26: =SUM(B4:J4) -> 218098.75 | F26: Geología MN | H26: 390036.18 | I26: =VLOOKUP(F26,$C$26:$D$41,2,0)+D36+D37 -> #N/A | J26: =I26-H26 -> #N/A | K26: -200 | L26: Ahorro en HH Gabinete
B27: 91243120 | C27: =VLOOKUP(B27,'G (G.C)'!$B$29:$C$44,2,0) -> #N/A | D27: =SUM(B5:J5) -> 69447.455 | F27: Geología ME | H27: 199663.82 | I27: =VLOOKUP(F27,$C$26:$D$41,2,0) -> #N/A | J27: =I27-H27 -> #N/A | K27: -130 | L27: Eficiencia en modelamiento y evaluacion, HH + RRM
B28: 91243310 | C28: =VLOOKUP(B28,'G (G.C)'!$B$29:$C$44,2,0) -> #N/A | D28: =SUM(B6:J6) -> 0 | F28: Geoquímica ME | H28: 0 | J28: =I28-H28 -> 0
B29: 91243510 | C29: =VLOOKUP(B29,'G (G.C)'!$B$29:$C$44,2,0) -> #N/A | D29: =SUM(B7:J7) -> 0 | F29: Geofísica ME | H29: 0 | I29: =VLOOKUP(F29,$C$26:$D$41,2,0) -> #N/A | J29: =I29-H29 -> #N/A
B30: 91243520 | C30: =VLOOKUP(B30,'G (G.C)'!$B$29:$C$44,2,0) -> #N/A | D30: =SUM(B8:J8) -> 52510.83 | F30: Sondajes ME | H30: 0 | I30: =VLOOKUP(F30,$C$26:$D$41,2,0) -> #N/A | J30: =I30-H30 -> #N/A
B31: 91243530 | C31: =VLOOKUP(B31,'G (G.C)'!$B$29:$C$44,2,0) -> #N/A | D31: =SUM(B9:J9) -> 174.72702 | F31: Logística MN | H31: 92889.873 | I31: =VLOOKUP(F31,$C$26:$D$41,2,0) -> #N/A | J31: =I31-H31 -> #N/A | K31: -59 | L31: Ahorro en Licencias de Software y contigencias de materiales
B32: 91243720 | C32: =VLOOKUP(B32,'G (G.C)'!$B$29:$C$44,2,0) -> Administración MN | D32: =SUM(B12:J12) -> 3012.3191 | F32: Logística ME | H32: 120097.55 | I32: =VLOOKUP(F32,$C$26:$D$41,2,0) -> #N/A | J32: =I32-H32 -> #N/A | L32: Ahorro en Viajes, menos personas por menos dias y tarifas mas bajas
B33: 91243730 | C33: =VLOOKUP(B33,'G (G.C)'!$B$29:$C$44,2,0) -> #N/A | D33: =SUM(B13:J13) -> 0 | F33: Propiedad Minera | H33: 0 | I33: =VLOOKUP(F33,$C$26:$D$41,2,0) -> #N/A | J33: =I33-H33 -> #N/A
B34: 91243710 | C34: =VLOOKUP(B34,'G (G.C)'!$B$29:$C$44,2,0) -> #N/A | D34: =SUM(B14:J14) -> 0 | F34: Medio Ambiente MN | H34: 0 | J34: =I34-H34 -> 0
B35: 91243540 | C35: =VLOOKUP(B35,'G (G.C)'!$B$29:$C$44,2,0) -> #N/A | D35: =SUM(B15:J15) -> 0 | F35: Medio Ambiente ME | H35: 0 | J35: =I35-H35 -> 0
B36: 91243910 | C36: =VLOOKUP(B36,'G (G.C)'!$B$29:$C$44,2,0) -> #N/A | D36: =SUM(B10:J10) -> 8056.817 | F36: Seguridad ME | H36: 0 | J36: =I36-H36 -> 0
B37: 91243920 | C37: =VLOOKUP(B37,'G (G.C)'!$B$29:$C$44,2,0) -> #N/A | D37: =SUM(B11:J11) -> 4446.9992 | F37: Comunidades ME | H37: 0 | I37: =VLOOKUP(F37,$C$26:$D$41,2,0) -> #N/A | J37: =I37-H37 -> #N/A
F38: Administración MN | H38: 0 | I38: =VLOOKUP(F38,$C$26:$D$41,2,0) -> 3012.3191 | J38: =I38-H38 -> 3012.3191
F39: Contingencia MN | H39: 58622.369 | I39: =VLOOKUP(F39,$C$26:$D$41,2,0) -> #N/A | J39: =I39-H39 -> #N/A | K39: -58
D40: =SUM(D26:D39) -> 355747.9 | I40: =SUM(I26:I39) -> #N/A | J40: =SUM(J26:J39) -> #N/A | K40: =SUM(K26:K39) -> -447
E46: =865-390 -> 475

Sheet Hoja3
A3: Etiquetas de fila | B3: Suma de ago-24 | C3: Suma de sept-24 | D3: Suma de oct-24 | E3: Suma de nov-24 | F3: Suma de dic-24 | G3: Suma de ene-25 | H3: Suma de feb-25 | I3: Suma de mar-25 | J3: Suma de abr-25
A4: 91243110
A5: Delta Api Ítem II | B5: 0 | C5: 0 | D5: 0 | E5: 0 | F5: 0 | G5: 0 | H5: 0 | I5: 0 | J5: 0 | L5: Delta Api Ítem II | M5: =SUM(B5:J5) -> 0
A6: Director Proyecto (JCT) 2% | B6: 0 | C6: 0 | D6: 0 | E6: 0 | F6: 0 | G6: 0 | H6: 0 | I6: 0 | J6: 0 | L6: Director Proyecto (JCT) 2% | M6: =SUM(B6:J6) -> 0
A7: Evaluación Caso de Negocio Externo SRK AUS | B7: 0 | C7: 0 | D7: 0 | E7: 0 | F7: 0 | G7: 0 | H7: 0 | I7: 0 | J7: 0 | L7: Evaluación Caso de Negocio Externo SRK AUS | M7: =SUM(B7:J7) -> 0
A8: Geología Australia | B8: 0 | C8: 0 | D8: 26059.761 | E8: 8715.3164 | F8: 10530.063 | G8: 10887.682 | H8: 5499.6805 | I8: 5043.4074 | J8: 0 | L8: Geología Australia | M8: =SUM(B8:J8) -> 66735.91
A9: Geólogo Juan R. | B9: 3571.5332 | C9: -0.050175256 | D9: -2742.3225 | E9: 8668.4787 | F9: 6361.0345 | G9: 6717.1933 | H9: 5112.2451 | I9: 5121.5351 | J9: 5539.8288 | L9: Geólogo Juan R. | M9: =SUM(B9:J9) -> 38349.476
A10: Geólogos Proyecto (x2) Ítem II | B10: 0 | C10: 0 | D10: 0 | E10: 0 | F10: 0 | G10: 0 | H10: 0 | I10: 0 | J10: 0 | L10: Geólogos Proyecto (x2) Ítem II | M10: =SUM(B10:J10) -> 0
A11: Geólogos Proyecto (x3) Ítem II | B11: 0 | C11: 0 | D11: 0 | E11: 0 | F11: 0 | G11: 0 | H11: 0 | I11: 0 | J11: 0 | L11: Geólogos Proyecto (x3) Ítem II | M11: =SUM(B11:J11) -> 0
A12: Impuesto (Valor Antes Impuesto)/(1-15%))*15% | B12: 0 | C12: 0 | D12: 0 | E12: 0 | F12: 0 | G12: 0 | H12: 0 | I12: 0 | J12: 0 | L12: Impuesto (Valor Antes Impuesto)/(1-15%))*15% | M12: =SUM(B12:J12) -> 0
A13: Ingeniero P&C 5% | B13: 0 | C13: 0 | D13: 0 | E13: 0 | F13: 0 | G13: 0 | H13: 0 | I13: 0 | J13: 0 | L13: Ingeniero P&C 5% | M13: =SUM(B13:J13) -> 0
A14: NELSON RAUL CORTES CABEZAS | B14: 0 | C14: 0 | D14: 0 | E14: 0 | F14: 0 | G14: 1404.0253 | H14: 3547.1111 | I14: 2871.5617 | J14: 0 | L14: NELSON RAUL CORTES CABEZAS | M14: =SUM(B14:J14) -> 7822.6981
A15: Peter Pollar Aus | B15: 0 | C15: 0 | D15: 0 | E15: 5037.2462 | F15: 916.09661 | G15: 6614.1684 | H15: 0 | I15: 0 | J15: 0 | L15: Peter Pollar Aus | M15: =SUM(B15:J15) -> 12567.511
A16: Recursos Y Reservas Mineras Consultores Limitada | B16: 0 | C16: 0 | D16: 0 | E16: 0 | F16: 0 | G16: 0 | H16: 0 | I16: 30768.674 | J16: 0 | L16: Recursos Y Reservas Mineras Consultores Limitada | M16: =SUM(B16:J16) -> 30768.674
... A19: SERVICIOS DE INGENIERÍA ASESORÍAS Y OBRAS CIVILES LIMITADA | B19: 0 | C19: 0 | D19: 0 | E19: 1260.6296 | F19: 631.56687 | G19: 1260.515 | H19: -627.78615 | I19: 624.6396 | J19: 0 | L19: SERVICIOS DE INGENIERÍA ASESORÍAS Y OBRAS CIVILES LIMITADA | M19: =SUM(B19:J19) -> 3149.5649
A20: 91243120 | L20: 91243120 | M20: =SUM(B20:J20) -> 0
A21: Darren Obrian Cad | B21: 0 | C21: 0 | D21: 9875.8623 | E21: 1244.2175 | F21: 4777.1185 | G21: 1769.7287 | H21: 0 | I21: 1888.5338 | J21: 3301.947 | L21: Darren Obrian Cad | M21: =SUM(B21:J21) -> 22857.408
A22: Evaluación Caso de Negocio Externo SRK AUS | B22: 0 | C22: 0 | D22: 0 | E22: 0 | F22: 0 | G22: 0 | H22: 0 | I22: 0 | J22: 0 | L22: Evaluación Caso de Negocio Externo SRK AUS | M22: =SUM(B22:J22) -> 0
A23: Evaluación Caso de Negocio Externo SRK Cad | B23: 0 | C23: 0 | D23: 0 | E23: 0 | F23: 0 | G23: 0 | H23: 0 | I23: 0 | J23: 0 | L23: Evaluación Caso de Negocio Externo SRK Cad | M23: =SUM(B23:J23) -> 0
A24: Evaluación de proyecto CAD AUS | B24: 0 | C24: 0 | D24: 0 | E24: 0 | F24: 0 | G24: 0 | H24: 0 | I24: 0 | J24: 0 | L24: Evaluación de proyecto CAD AUS | M24: =SUM(B24:J24) -> 0
A25: Evaluación de proyecto RRM CAD AUS | B25: 0 | C25: 0 | D25: 0 | E25: 0 | F25: 0 | G25: 0 | H25: 0 | I25: 0 | J25: 0 | L25: Evaluación de proyecto RRM CAD AUS | M25: =SUM(B25:J25) -> 0
A26: Impuesto (Valor Antes Impuesto)/(1-15%))*15% | B26: 0 | C26: 0 | D26: 0 | E26: 0 | F26: 0 | G26: 0 | H26: 0 | I26: 0 | J26: 0 | L26: Impuesto (Valor Antes Impuesto)/(1-15%))*15% | M26: =SUM(B26:J26) -> 0
A27: Peter Pollar Aus | B27: 0 | C27: 0 | D27: 2831.9398 | E27: 13338.38 | F27: 0 | G27: 0 | H27: 0 | I27: 0 | J27: 0 | L27: Peter Pollar Aus | M27: =SUM(B27:J27) -> 16170.319
A28: TERRA | B28: 0 | C28: 0 | D28: -1128.9084 | E28: 24078.317 | F28: 4978.8182 | G28: 2491.501 | H28: 0 | I28: 0 | J28: 0 | L28: TERRA | M28: =SUM(B28:J28) -> 30419.727
A29: 91243310 | L29: 91243310 | M29: =SUM(B29:J29) -> 0
A30: IP Profundo | B30: 0 | C30: 0 | D30: 0 | E30: 0 | F30: 0 | G30: 0 | H30: 0 | I30: 0 | J30: 0 | L30: IP Profundo | M30: =SUM(B30:J30) -> 0
A31: MINDAS | B31: 0 | C31: 0 | D31: 0 | E31: 0 | F31: 0 | G31: 0 | H31: 0 | I31: 0 | J31: 0 | L31: MINDAS | M31: =SUM(B31:J31) -> 0
A32: 91243510 | L32: 91243510 | M32: =SUM(B32:J32) -> 0
A33: Arriendo Implementos de Mapeo | B33: 0 | C33: 0 | D33: 0 | E33: 0 | F33: 0 | G33: 0 | H33: 0 | I33: 0 | J33: 0 | L33: Arriendo Implementos de Mapeo | M33: =SUM(B33:J33) -> 0
A34: Contingencia apoyo en terreno AUS | B34: 0 | C34: 0 | D34: 0 | E34: 0 | F34: 0 | G34: 0 | H34: 0 | I34: 0 | J34: 0 | L34: Contingencia apoyo en terreno AUS | M34: =SUM(B34:J34) -> 0
A35: Contingencia en arriendo de materiales CAD | B35: 0 | C35: 0 | D35: 0 | E35: 0 | F35: 0 | G35: 0 | H35: 0 | I35: 0 | J35: 0 | L35: Contingencia en arriendo de materiales CAD | M35: =SUM(B35:J35) -> 0
A36: LeapFrog Geo - Subscription - Shared | B36: 0 | C36: 0 | D36: 0 | E36: 0 | F36: 0 | G36: 0 | H36: 0 | I36: 0 | J36: 0 | L36: LeapFrog Geo - Subscription - Shared | M36: =SUM(B36:J36) -> 0
A37: Licencias Software | B37: 0 | C37: 0 | D37: 0 | E37: 0 | F37: 0 | G37: 0 | H37: 0 | I37: 0 | J37: 0 | L37: Licencias Software | M37: =SUM(B37:J37) -> 0
A38: Licencias Software delta | B38: 0 | C38: 0 | D38: 0 | E38: 0 | F38: 0 | G38: 0 | H38: 0 | I38: 0 | J38: 0 | L38: Licencias Software delta | M38: =SUM(B38:J38) -> 0
A39: Perforación DDH (costo total por metro) | B39: 0 | C39: 0 | D39: 0 | E39: 0 | F39: 0 | G39: 0 | H39: 0 | I39: 0 | J39: 0 | L39: Perforación DDH (costo total por metro) | M39: =SUM(B39:J39) -> 0
A40: 91243520 | L40: 91243520 | M40: =SUM(B40:J40) -> 0
A41: Alimentación Consultores AUS | B41: 0 | C41: 0 | D41: 0 | E41: 0 | F41: 0 | G41: 0 | H41: 0 | I41: 0 | J41: 0 | L41: Alimentación Consultores AUS | M41: =SUM(B41:J41) -> 0
A42: Alimentación Consultores CAD | B42: 0 | C42: 0 | D42: 0 | E42: 0 | F42: 0 | G42: 0 | H42: 0 | I42: 0 | J42: 0 | L42: Alimentación Consultores CAD | M42: =SUM(B42:J42) -> 0
A43: Alimentación Personal EMSA AUS | B43: 0 | C43: 0 | D43: 0 | E43: 0 | F43: 0 | G43: 0 | H43: 0 | I43: 0 | J43: 0 | L43: Alimentación Personal EMSA AUS | M43: =SUM(B43:J43) -> 0
A44: Alimentación Personal EMSA CAD | B44: 0 | C44: 0 | D44: 0 | E44: 0 | F44: 0 | G44: 0 | H44: 0 | I44: 0 | J44: 0 | L44: Alimentación Personal EMSA CAD | M44: =SUM(B44:J44) -> 0
A45: Arriendo Implementos de Mapeo | B45: 0 | C45: 0 | D45: 0 | E45: 0 | F45: 0 | G45: 0 | H45: 0 | I45: 0 | J45: 0 | L45: Arriendo Implementos de Mapeo | M45: =SUM(B45:J45) -> 0
A46: Camioneta Consultor AUS | B46: 0 | C46: 0 | D46: 0 | E46: 0 | F46: 0 | G46: 0 | H46: 0 | I46: 0 | J46: 0 | L46: Camioneta Consultor AUS | M46: =SUM(B46:J46) -> 0
A47: Camioneta Consultor CAD | B47: 0 | C47: 0 | D47: 0 | E47: 0 | F47: 0 | G47: 0 | H47: 0 | I47: 0 | J47: 0 | L47: Camioneta Consultor CAD | M47: =SUM(B47:J47) -> 0
A48: Contingencia en arriendo de materiales AUS | B48: 0 | C48: 0 | D48: 0 | E48: 0 | F48: 0 | G48: 0 | H48: 0 | I48: 0 | J48: 0 | L48: Contingencia en arriendo de materiales AUS | M48: =SUM(B48:J48) -> 0
A49: Contingencia en arriendo de materiales CAD | B49: 0 | C49: 0 | D49: 0 | E49: 0 | F49: 0 | G49: 0 | H49: 0 | I49: 0 | J49: 0 | L49: Contingencia en arriendo de materiales CAD | M49: =SUM(B49:J49) -> 0
A50: Darren Obrian Cad | B50: 0 | C50: 7946.3604 | D50: -7998.2254 | E50: 0 | F50: 0 | G50: 0 | H50: 0 | I50: 0 | J50: 0 | L50: Darren Obrian Cad | M50: =SUM(B50:J50) -> -51.864973
A51: Hotel Consultores AUS | B51: 0 | C51: 0 | D51: 0 | E51: 0 | F51: 0 | G51: 0 | H51: 0 | I51: 0 | J51: 0 | L51: Hotel Consultores AUS | M51: =SUM(B51:J51) -> 0
A52: Hotel Consultores CAD | B52: 0 | C52: 0 | D52: 0 | E52: 0 | F52: 0 | G52: 0 | H52: 0 | I52: 0 | J52: 0 | L52: Hotel Consultores CAD | M52: =SUM(B52:J52) -> 0
... A78:  VEHÍCULOS LIVIANOS Y OTROS MEDIOS DE TRANSPORTE | B78: 0 | C78: 0 | D78: 0 | E78: 0 | F78: 0 | G78: 0 | H78: 0 | I78: 0 | J78: 0 | L78:  VEHÍCULOS LIVIANOS Y OTROS MEDIOS DE TRANSPORTE | M78: =SUM(B78:J78) -> 0
A79: 91243530 | L79: 91243530 | M79: =SUM(B79:J79) -> 0
A80: Hotel Personal EMSA AUS | B80: 0 | C80: 0 | D80: 2071.5616 | E80: -1994.7707 | F80: 0 | G80: 0 | H80: 0 | I80: 0 | J80: 0 | L80: Hotel Personal EMSA AUS | M80: =SUM(B80:J80) -> 76.790858
A81: LeapFrog Geo - Subscription - Shared | B81: 0 | C81: 0 | D81: 0 | E81: 0 | F81: 0 | G81: 0 | H81: 0 | I81: 0 | J81: 0 | L81: LeapFrog Geo - Subscription - Shared | M81: =SUM(B81:J81) -> 0
A82: Vuelo Avión CHI-AUS | B82: 0 | C82: 0 | D82: 2641.9916 | E82: -2544.0554 | F82: 0 | G82: 0 | H82: 0 | I82: 0 | J82: 0 | L82: Vuelo Avión CHI-AUS | M82: =SUM(B82:J82) -> 97.936166
A83: 91243540 | L83: 91243540 | M83: =SUM(B83:J83) -> 0
A84: Consultor Especialista en Medio Ambiente | B84: 0 | C84: 0 | D84: 0 | E84: 0 | F84: 0 | G84: 0 | H84: 0 | I84: 0 | J84: 0 | L84: Consultor Especialista en Medio Ambiente | M84: =SUM(B84:J84) -> 0
A85: Gastos Asociados a la Constitución o Adquisición de Por. Minera (abogados, notarios, etc.) ME | B85: 0 | C85: 0 | D85: 0 | E85: 0 | F85: 0 | G85: 0 | H85: 0 | I85: 0 | J85: 0 | L85: Gastos Asociados a la Constitución o Adquisición de Por. Minera (abogados, notarios, etc.) ME | M85: =SUM(B85:J85) -> 0
A86: Pago de Opción de Compra/servidumbre ME | B86: 0 | C86: 0 | D86: 0 | E86: 0 | F86: 0 | G86: 0 | H86: 0 | I86: 0 | J86: 0 | L86: Pago de Opción de Compra/servidumbre ME | M86: =SUM(B86:J86) -> 0
A87: 91243710 | L87: 91243710 | M87: =SUM(B87:J87) -> 0
A88: G_SAP comunidades | B88: 0 | C88: 0 | D88: 0 | E88: 0 | F88: 0 | G88: 0 | H88: 0 | I88: 0 | J88: 0 | L88: G_SAP comunidades | M88: =SUM(B88:J88) -> 0
A89: G_SAP Adm | B89: 0 | C89: 0 | D89: 0 | E89: 0 | F89: 0 | G89: 0 | H89: 0 | I89: 0 | J89: 0 | L89: G_SAP Adm | M89: =SUM(B89:J89) -> 0
A90: G_SAP MN | B90: 0 | C90: 0 | D90: 0 | E90: 0 | F90: 0 | G90: 0 | H90: 0 | I90: 0 | J90: 0 | L90: G_SAP MN | M90: =SUM(B90:J90) -> 0
A91: 91243720 | L91: 91243720 | M91: =SUM(B91:J91) -> 0
A92: Costos del Dueño MN | B92: 0 | C92: 0 | D92: 0 | E92: 0 | F92: 0 | G92: 0 | H92: 2935.1506 | I92: 77.168442 | J92: 0 | L92: Costos del Dueño MN | M92: =SUM(B92:J92) -> 3012.3191
A93: 91243730 | L93: 91243730 | M93: =SUM(B93:J93) -> 0
A94: Contingencia MN | B94: 0 | C94: 0 | D94: 0 | E94: 0 | F94: 0 | G94: 0 | H94: 0 | I94: 0 | J94: 0 | L94: Contingencia MN | M94: =SUM(B94:J94) -> 0
A95: Contingencias | B95: 0 | C95: 0 | D95: 0 | E95: 0 | F95: 0 | G95: 0 | H95: 0 | I95: 0 | J95: 0 | L95: Contingencias | M95: =SUM(B95:J95) -> 0
A96: Contingencias Ítem III 27 | B96: 0 | C96: 0 | D96: 0 | E96: 0 | F96: 0 | G96: 0 | H96: 0 | I96: 0 | J96: 0 | L96: Contingencias Ítem III 27 | M96: =SUM(B96:J96) -> 0
A97: 91243910 | L97: 91243910 | M97: =SUM(B97:J97) -> 0
A98: FEE MO | B98: 472.44271 | C98: 547.89513 | D98: 1435.8927 | E98: 914.86894 | F98: 1830.1247 | G98: 1701.545 | H98: 504.81272 | I98: 424.6829 | J98: 224.55224 | L98: FEE MO | M98: =SUM(B98:J98) -> 8056.817
A99: 91243920 | L99: 91243920 | M99: =SUM(B99:J99) -> 0
A100: FEE SS | B100: 6.7152632 | C100: 333.5616 | D100: 1245.0757 | E100: 847.77935 | F100: 923.06434 | G100: 538.82419 | H100: 207.90363 | I100: 116.5929 | J100: 227.48231 | L100: FEE SS | M100: =SUM(B100:J100) -> 4446.9992
A101: (en blanco) | L101: (en blanco) | M101: =SUM(B101:J101) -> 0
A102: Administración MN | B102: 0 | C102: 0 | D102: 0 | E102: 0 | F102: 0 | G102: 0 | H102: 0 | I102: 0 | J102: 0 | L102: Administración MN | M102: =SUM(B102:J102) -> 0
A103: ADMINISTRACIÓN, DSUST Y DSSO | B103: 0 | C103: 0 | D103: 0 | E103: 0 | F103: 0 | G103: 0 | H103: 0 | I103: 0 | J103: 0 | L103: ADMINISTRACIÓN, DSUST Y DSSO | M103: =SUM(B103:J103) -> 0
A104: Contingencias | B104: 0 | C104: 0 | D104: 0 | E104: 0 | F104: 0 | G104: 0 | H104: 0 | I104: 0 | J104: 0 | L104: Contingencias | M104: =SUM(B104:J104) -> 0
A105: COSTO DEL DUEÑO - PATROCINANTE | B105: 0 | C105: 0 | D105: 0 | E105: 0 | F105: 0 | G105: 0 | H105: 0 | I105: 0 | J105: 0 | L105: COSTO DEL DUEÑO - PATROCINANTE | M105: =SUM(B105:J105) -> 0
A106: Dirección Prospección y Evaluación | B106: 0 | C106: 0 | D106: 0 | E106: 0 | F106: 0 | G106: 0 | H106: 0 | I106: 0 | J106: 0 | L106: Dirección Prospección y Evaluación | M106: =SUM(B106:J106) -> 0
A107: Geofísica | B107: 0 | C107: 0 | D107: 0 | E107: 0 | F107: 0 | G107: 0 | H107: 0 | I107: 0 | J107: 0 | L107: Geofísica | M107: =SUM(B107:J107) -> 0
A108: GEOLOGÍA | B108: 0 | C108: 0 | D108: 0 | E108: 0 | F108: 0 | G108: 0 | H108: 0 | I108: 0 | J108: 0 | L108: GEOLOGÍA | M108: =SUM(B108:J108) -> 0
A109: Geología Australia | B109: 0 | C109: 0 | D109: 0 | E109: 0 | F109: 0 | G109: 0 | H109: 0 | I109: 0 | J109: 0 | L109: Geología Australia | M109: =SUM(B109:J109) -> 0
A110: Geología Canadá | B110: 0 | C110: 0 | D110: 0 | E110: 0 | F110: 0 | G110: 0 | H110: 0 | I110: 0 | J110: 0 | L110: Geología Canadá | M110: =SUM(B110:J110) -> 0
A111: Geología Gabinete Chile | B111: 0 | C111: 0 | D111: 0 | E111: 0 | F111: 0 | G111: 0 | H111: 0 | I111: 0 | J111: 0 | L111: Geología Gabinete Chile | M111: =SUM(B111:J111) -> 0
A112: GESTIÓN EJECUCIÓN PROYECTO | B112: 0 | C112: 0 | D112: 0 | E112: 0 | F112: 0 | G112: 0 | H112: 0 | I112: 0 | J112: 0 | L112: GESTIÓN EJECUCIÓN PROYECTO | M112: =SUM(B112:J112) -> 0
A113: ITEM II | B113: 0 | C113: 0 | D113: 0 | E113: 0 | F113: 0 | G113: 0 | H113: 0 | I113: 0 | J113: 0 | L113: ITEM II | M113: =SUM(B113:J113) -> 0
... A129:  VEHÍCULOS LIVIANOS Y OTROS MEDIOS DE TRANSPORTE | B129: 0 | C129: 0 | D129: 0 | E129: 0 | F129: 0 | G129: 0 | H129: 0 | I129: 0 | J129: 0 | L129:  VEHÍCULOS LIVIANOS Y OTROS MEDIOS DE TRANSPORTE | M129: =SUM(B129:J129) -> 0
A130: Total general | B130: 21812.137 | C130: 24825.416 | D130: 58087.746 | E130: 70561.97 | F130: 44326.908 | G130: 43370.557 | H130: 21125.775 | I130: 57976.7 | J130: 13660.69 | M130: =SUM(B130:J130) -> 355747.9

Sheet Hoja7
A3: Etiquetas de fila | B3: Suma de TOTAL (US$)
A4: 91243110 | B4: 1640057.5
A5: 91243120 | B5: 1078225.3
A6: 91243310 | B6: 1657397.3
A7: 91243510 | B7: 884062.6
A8: 91243520 | B8: 233450.49
A9: 91243530 | B9: 177261.35
A10: 91243540 | B10: 382194.53
A11: 91243560 | B11: 70323
A12: 91243710 | B12: 0
A13: 91243720 | B13: 106490.75
A14: 91243730 | B14: 133558.82
A15: 91243910 | B15: 71963.017
A16: 91243920 | B16: 45889.855
A17: 91243520 | B17: 77655.549
A18: (en blanco) | B18: 0
A19: Total general | B19: 6558530

Sheet Hoja6
A3: Etiquetas de fila | B3: Suma de TOTAL (US$)
A4: 91243110 | B4: 1430938.2
A5: 91243120 | B5: 1410558.2
A6: 91243310 | B6: 1703101.1
A7: 91243510 | B7: 908441.2
A8: 91243520 | B8: 237056.11
A9: 91243530 | B9: 204497.06
A10: 91243540 | B10: 340692
A11: 91243560 | B11: 72262.202
A12: 91243710 | B12: 87841.21
A13: 91243720 | B13: 20190.793
A14: 91243730 | B14: 137241.79
A15: 91243910 | B15: 57438.36
A16: 91243920 | B16: 56221.983
A17: 91243520 | B17: 77571.344
A18: (en blanco) | B18: 0
A19: Total general | B19: 6744051.6

Sheet D2
G1: 2025 | H1: 108.2 | I1: 887 | J1: 261.1 | M1: =H2/H1 -> 1.0341959 | N1: =(I2/I1)*(J2/J1) -> 1.0658056 | Q1: 2024 | R1: 2025 | S1: 2026 | T1: 2027 | U1: 2028 | W1: Dólar MB US$ | X1: Financiero | Y1: 6692580 | Z1: =SUM(AB1:DX1) -> 2017523.6 | BR1: * | BS1: =SUMIF($L$6:$L$337,"MN",BS6:BS337) -> 21748.877 | BT1: =SUMIF($L$6:$L$337,"MN",BT6:BT337) -> 16830.102 | BU1: =SUMIF($L$6:$L$337,"MN",BU6:BU337) -> 49604.279 | BV1: =SUMIF($L$6:$L$337,"MN",BV6:BV337) -> 36334.199 | BW1: =SUMIF($L$6:$L$337,"MN",BW6:BW337) -> 41747.11 | BX1: =SUMIF($L$6:$L$337,"MN",BX6:BX337) -> 39247.064 | BY1: =SUMIF($L$6:$L$337,"MN",BY6:BY337) -> 21064.505 | BZ1: =SUMIF($L$6:$L$337,"MN",BZ6:BZ337) -> 55925.498 | ... DK1: =SUMIF($L$6:$L$337,"MN",DK6:DK337) -> 159467.18
G2: 2026 | H2: 111.9 | I2: 920 | J2: 268.3 | Q2: =SUM(BL3:BW3) -> 228189.96 | R2: =SUM(BX3:CI3) -> 476667.45 | S2: =SUM(CJ3:CU3) -> 1674600.4 | T2: =SUM(CV3:DG3) -> 2034249.7 | U2: =SUM(DH3:DS3) -> 2331209 | Y2: =Z3-Y3 -> -177558.56 | Z2: =SUM(AB2:DX2) -> 4727392.9 | BS2: =SUMIF($L$6:$L$337,"ME",BS6:BS337) -> 0 | BT2: =SUMIF($L$6:$L$337,"ME",BT6:BT337) -> 7923.3141 | BU2: =SUMIF($L$6:$L$337,"ME",BU6:BU337) -> 8644.6473 | BV2: =SUMIF($L$6:$L$337,"ME",BV6:BV337) -> 35063.026 | BW2: =SUMIF($L$6:$L$337,"ME",BW6:BW337) -> 10294.403 | BX2: =SUMIF($L$6:$L$337,"ME",BX6:BX337) -> 4379.1953 | BY2: =SUMIF($L$6:$L$337,"ME",BY6:BY337) -> 0 | BZ2: =SUMIF($L$6:$L$337,"ME",BZ6:BZ337) -> 1942.9534 | ... DK2: =SUMIF($L$6:$L$337,"ME",DK6:DK337) -> 266969.2 | DL2: =SUMIF($L$6:$L$337,$L$174,DL5:DL337) -> 0 | DM2: =SUMIF($L$6:$L$337,$L$174,DM5:DM337) -> 0 | DN2: =SUMIF($L$6:$L$337,$L$174,DN5:DN337) -> 0 | DO2: =SUMIF($L$6:$L$337,$L$174,DO5:DO337) -> 0 | DP2: =SUMIF($L$6:$L$337,$L$174,DP5:DP337) -> 0 | DQ2: =SUMIF($L$6:$L$337,$L$174,DO6:DO337) -> 0 | DR2: =SUMIF($L$6:$L$337,$L$174,DP6:DP337) -> 0 | DS2: =SUMIF($L$6:$L$337,$L$174,DQ6:DQ337) -> 0 | DT2: =SUMIF($L$6:$L$337,$L$174,DR6:DR337) -> 0 | DU2: =SUMIF($L$6:$L$337,$L$174,DS6:DS337) -> 0 | DV2: =SUMIF($L$6:$L$337,$L$174,DT6:DT337) -> 0 | DW2: =SUMIF($L$6:$L$337,$L$174,DU6:DU337) -> 0
Q3: 226.88398 | R3: 730.553 | S3: 1650.841 | T3: 1967.766 | U3: 1991.318 | Y3: =SUM(AA3:DW3) -> 6744916.6 | Z3: 6567358 | BR3: =SUM(BR7:BR337) -> 0 | BS3: =SUM(BS7:BS337) -> 21748.877 | BT3: =SUM(BT7:BT337) -> 24753.417 | BU3: =SUM(BU7:BU337) -> 58248.926 | BV3: =SUM(BV7:BV337) -> 71397.225 | BW3: =SUM(BW7:BW337) -> 52041.513 | BX3: =SUM(BX7:BX337) -> 43626.259 | BY3: =SUM(BY7:BY337) -> 21064.505 | ... DM3: =SUM(DM7:DM337) -> 0 | DN3: =SUM(DL7:DL337) -> 0 | DO3: =SUM(DM7:DM337) -> 0 | DP3: =SUM(DN7:DN337) -> 0 | DQ3: =SUM(DO7:DO337) -> 0 | DR3: =SUM(DP7:DP337) -> 0 | DS3: =SUM(DQ7:DQ337) -> 0 | DT3: =SUM(DR7:DR337) -> 0 | DU3: =SUM(DS7:DS337) -> 0 | ... DW3: =SUM(DU7:DU337) -> 0 | DX3: 45808
A4: AUXILIAR_1 | B4: AUXILIAR_2 | C4: AUXILIAR_3 | D4: AUXILIAR_4 | E4: AUXILIAR_5 | F4: AUXILIAR_6 | G4: Llave S | H4: MONEDA BASE | I4: GASTO / PPT | J4: FEE | K4: ARTÍCULO | L4: MONEDA | M4: KEY | N4: DESCRIPCION | O4: CODIGO PROVEEDOR | P4: NOMBRE PROVEEDOR | Q4: ID_BLANCO | R4: UN | S4: CTD | T4: FE_INI | U4: FE_FIN | V4: MES | W4: PRECIO UNITARIO (CLP $) | X4: =IF(W2="Pesos CLP","PRECIO UNITARIO (CLP $)","PRECIO UNITARIO (US$)") -> PRECIO UNITARIO (US$) | Y4: =IF(W1="Pesos CLP","TOTAL (CLP $)","TOTAL (US$)") -> TOTAL (US$) | Z4: GRAFO | AA4: 44196 | AB4: 44227 | AC4: 44255 | AD4: 44286 | AE4: 44316 | AF4: 44347 | AG4: 44377 | AH4: 44408 | AI4: 44439 | AJ4: 44469 | AK4: 44500 | AL4: 44530 | AM4: 44561 | AN4: 44592 | AO4: 44620 | AP4: 44651 | AQ4: 44681 | AR4: 44712 | AS4: 44742 | AT4: 44773 | AU4: 44804 | AV4: 44834 | AW4: 44865 | AX4: 44895 | AY4: 44926 | AZ4: 44957 | BA4: 44985 | BB4: 45016 | BC4: 45046 | BD4: 45077 | BE4: 45107 | BF4: 45138 | BG4: 45169 | BH4: 45199 | BI4: 45230 | BJ4: 45260 | BK4: 45291 | BL4: 45322 | BM4: 45351 | BN4: 45382 | BO4: 45412 | BP4: 45443 | BQ4: 45473 | BR4: 45504 | BS4: 45535 | BT4: 45565 | BU4: 45596 | BV4: 45626 | BW4: 45657 | BX4: 45688 | BY4: 45716 | BZ4: 45747 | CA4: 45777 | CB4: 45808 | CC4: 45838 | CD4: 45869 | CE4: 45900 | CF4: 45930 | CG4: 45961 | CH4: 45991 | CI4: 46022 | CJ4: 46053 | CK4: 46081 | CL4: 46112 | CM4: 46142 | CN4: 46173 | CO4: 46203 | CP4: 46234 | CQ4: 46265 | CR4: 46295 | CS4: 46326 | CT4: 46356 | CU4: 46387 | CV4: 46418 | CW4: 46446 | CX4: 46477 | CY4: 46507 | CZ4: 46538 | DA4: 46568 | DB4: 46599 | DC4: 46630 | DD4: 46660 | DE4: 46691 | DF4: 46721 | DG4: 46752 | DH4: 46783 | DI4: 46812 | DJ4: 46843 | DK4: 46873 | DL4: 46904 | DM4: 46934 | DN4: 46965 | DO4: 46996 | DP4: 47026 | DQ4: 47057 | DR4: 47087 | DS4: 47118 | DT4: 47149 | DU4: 47177 | DV4: 47208 | DW4: 47238 | DX4: 47269 | DY4: 47299 | DZ4: 47330 | EA4: 47361 | EB4: 47391 | EC4: 47422 | ED4: 47452 | EE4: 47483 | EF4: 47514 | EG4: 47542 | EH4: 47573 | EI4: 47603 | EJ4: 47634 | EK4: 47664 | EL4: 47695 | EM4: 47726 | EN4: 47756 | EO4: 47787 | EP4: 47817 | EQ4: 47848
A5: - | N5: GEOLOGÍA | X5: 0 | AA5: 0 | AB5: 0 | AC5: 0 | AD5: 0 | AE5: 0 | AF5: 0 | AG5: 0 | AH5: 0 | AI5: 0 | AJ5: 0 | AK5: 0 | AL5: 0 | AM5: 0 | AN5: 0 | AO5: 0 | AP5: 0 | AQ5: 0 | AR5: 0 | AS5: 0 | AT5: 0 | AU5: 0 | AV5: 0 | AW5: 0 | AX5: 0 | AY5: 0 | AZ5: 0 | BA5: 0 | BB5: 0 | BC5: 0 | BD5: 0 | BE5: 0 | BF5: 0 | BG5: 0 | BH5: 0 | BI5: 0 | BJ5: 0 | BK5: 0 | BL5: 0 | BM5: 0 | BN5: 0 | BO5: 0 | BP5: 0 | BQ5: 0 | BR5: 0 | BS5: 0 | BT5: 0 | BU5: 0 | BV5: 0 | BW5: 0 | BX5: 0 | BY5: 0 | BZ5: 0 | CA5: 0 | CB5: 0 | CC5: 0 | CD5: 0 | CF5: 0 | CK5: 0 | CL5: 0 | CM5: 0 | CN5: 0 | CO5: 0 | CP5: 0 | CQ5: 0 | CR5: 0 | CS5: 0 | CT5: 0 | CU5: 0 | CV5: 0 | CW5: 0 | CX5: 0 | CY5: 0 | CZ5: 0 | DA5: 0 | DB5: 0 | DC5: 0 | DD5: 0 | DE5: 0 | DF5: 0 | DG5: 0 | DH5: 0 | DI5: 0 | DJ5: 0 | DK5: 0 | DL5: 0 | DM5: 0 | DN5: 0 | DO5: 0 | DP5: 0 | DQ5: 0 | DR5: 0 | DS5: 0 | DT5: 0 | DU5: 0 | DV5: 0 | DW5: 0 | DX5: 0 | DY5: 0 | DZ5: 0 | EA5: 0 | EB5: 0 | EC5: 0 | ED5: 0 | EE5: 0 | EF5: 0 | EG5: 0 | EH5: 0 | EI5: 0 | EJ5: 0 | EK5: 0 | EL5: 0 | EM5: 0 | EN5: 0 | EO5: 0 | EP5: 0 | EQ5: 0
A6: - | G6: =H6-Z6 -> 0 | N6:  REMUNERACIÓN PROYECTO GEOLOGÍA | X6: 0 | AA6: 0 | AB6: 0 | AC6: 0 | AD6: 0 | AE6: 0 | AF6: 0 | AG6: 0 | AH6: 0 | AI6: 0 | AJ6: 0 | AK6: 0 | AL6: 0 | AM6: 0 | AN6: 0 | AO6: 0 | AP6: 0 | AQ6: 0 | AR6: 0 | AS6: 0 | AT6: 0 | AU6: 0 | AV6: 0 | AW6: 0 | AX6: 0 | AY6: 0 | AZ6: 0 | BA6: 0 | BB6: 0 | BC6: 0 | BD6: 0 | BE6: 0 | BF6: 0 | BG6: 0 | BH6: 0 | BI6: 0 | BJ6: 0 | BK6: 0 | BL6: 0 | BM6: 0 | BN6: 0 | BO6: 0 | BP6: 0 | BQ6: 0 | BR6: 0 | BS6: 0 | BT6: 0 | BU6: 0 | BV6: 0 | BX6: 0 | BY6: 0 | BZ6: 0 | CA6: 0 | CB6: 0 | CC6: 0 | CK6: 0 | CL6: 0 | CM6: 0 | CN6: 0 | CO6: 0 | CP6: 0 | CQ6: 0 | CR6: 0 | CS6: 0 | CT6: 0 | CU6: 0 | CV6: 0 | CW6: 0 | CX6: 0 | CY6: 0 | CZ6: 0 | DA6: 0 | DB6: 0 | DC6: 0 | DD6: 0 | DE6: 0 | DF6: 0 | DG6: 0 | DH6: 0 | DI6: 0 | DJ6: 0 | DK6: 0 | DL6: 0 | DM6: 0 | DN6: 0 | DO6: 0 | DP6: 0 | DQ6: 0 | DR6: 0 | DS6: 0 | DT6: 0 | DU6: 0 | DV6: 0 | DW6: 0 | DX6: 0 | DY6: 0 | DZ6: 0 | EA6: 0 | EB6: 0 | EC6: 0 | ED6: 0 | EE6: 0 | EF6: 0 | EG6: 0 | EH6: 0 | EI6: 0 | EJ6: 0 | EK6: 0 | EL6: 0 | EM6: 0 | EN6: 0 | EO6: 0 | EP6: 0 | EQ6: 0
D7: =IF(E7=$L$7,$M$1,$N$1) -> 1.0341959 | E7: =VLOOKUP(TEXT(Z7,0),'G2'!B:D,3,0) -> MN | F7: =SUM(BS7:CB7) -> 34290.642 | G7: =IF(OR($I7="REAL",$I7="INCURRIDO"),$I7&" "&$Z7&" "&O7&" "&Q7,) -> REAL 91243110 CO-H-007/2024 BERG_CAD | H7: MB-2025 | I7: REAL | J7: FEE SS | K7: 510102 | L7: =IFERROR(VLOOKUP(TEXT(Z7,0),'G2'!$B$5:$D$21,3,0),"") -> MN | N7: Geólogo Juan R. | O7: CO-H-007/2024 | Q7: BERG_CAD | R7: mes | T7: 45505 | U7: 45777 | V7: =(U7-T7)/30 -> 9.0666667 | W7: 0 | X7: {=+IF($W$1="Pesos CLP",W7,W7/TC)*MB_24A25} -> 0 | Y7: =SUM(BH7:DU7) -> 34290.642 | Z7: 91243110 | AA7: =IF(OR($I7="REAL",$I7="INCURRIDO"),SUMIF(S!$O:$O,$I7&$O7&$Q7&UPPER(TEXT(AA$4,"MMMMYYYY"))&$Z7,IF($W$1="Pesos CLP",S!$AD:$AD,S!$AO:$AO)),0) -> 0 | AB7: =IF(OR($I7="REAL",$I7="INCURRIDO"),SUMIF(S!$O:$O,$I7&$O7&$Q7&UPPER(TEXT(AB$4,"MMMMYYYY"))&$Z7,IF($W$1="Pesos CLP",S!$AD:$AD,S!$AO:$AO)),0) -> 0 | AC7: =IF(OR($I7="REAL",$I7="INCURRIDO"),SUMIF(S!$O:$O,$I7&$O7&$Q7&UPPER(TEXT(AC$4,"MMMMYYYY"))&$Z7,IF($W$1="Pesos CLP",S!$AD:$AD,S!$AO:$AO)),0) -> 0 | AD7: =IF(OR($I7="REAL",$I7="INCURRIDO"),SUMIF(S!$O:$O,$I7&$O7&$Q7&UPPER(TEXT(AD$4,"MMMMYYYY"))&$Z7,IF($W$1="Pesos CLP",S!$AD:$AD,S!$AO:$AO)),0) -> 0 | AE7: =IF(OR($I7="REAL",$I7="INCURRIDO"),SUMIF(S!$O:$O,$I7&$O7&$Q7&UPPER(TEXT(AE$4,"MMMMYYYY"))&$Z7,IF($W$1="Pesos CLP",S!$AD:$AD,S!$AO:$AO)),0) -> 0 | AF7: =IF(OR($I7="REAL",$I7="INCURRIDO"),SUMIF(S!$O:$O,$I7&$O7&$Q7&UPPER(TEXT(AF$4,"MMMMYYYY"))&$Z7,IF($W$1="Pesos CLP",S!$AD:$AD,S!$AO:$AO)),0) -> 0 | AG7: =IF(OR($I7="REAL",$I7="INCURRIDO"),SUMIF(S!$O:$O,$I7&$O7&$Q7&UPPER(TEXT(AG$4,"MMMMYYYY"))&$Z7,IF($W$1="Pesos CLP",S!$AD:$AD,S!$AO:$AO)),0) -> 0 | AH7: =IF(OR($I7="REAL",$I7="INCURRIDO"),SUMIF(S!$O:$O,$I7&$O7&$Q7&UPPER(TEXT(AH$4,"MMMMYYYY"))&$Z7,IF($W$1="Pesos CLP",S!$AD:$AD,S!$AO:$AO)),0) -> 0 | ... CJ7: =IF(OR($I7="REAL",$I7="INCURRIDO"),SUMIF(S!$O:$O,$I7&$O7&$Q7&UPPER(TEXT(CJ$4,"MMMMYYYY"))&$Z7,IF($W$1="Pesos CLP",S!$AD:$AD,S!$AO:$AO)),0) -> 0 | CK7: =(IF(AND(AND($T7>=(CK$4-DAY(CK$4)+1),$T7<=CK$4),AND($U7>=(CK$4-DAY(CK$4)+1),$U7<=CK$4)),$U7-$T7+1,IF(AND($T7>=(CK$4-DAY(CK$4)+1),$T7<=CK$4),CK$4-$T7+1,IF(AND($U7>=(CK$4-DAY(CK$4)+1),$U7<=CK$4),$U7-(CK$4-DAY(CK$4)+1)+1,IF(OR(AND((CK$4-DAY(CK$4)+1)>=$T7,(CK$4-DAY(CK$4)+1)<=$U7),AND((CK$4>=$T7),(CK$4<=$U7))),CK$4-(CK$4-DAY(CK$4)+1)+1,0))))/IF($R7="mes",_xlfn.DAYS(CK$4,(CK$4-DAY(CK$4)+1))+1,(_xlfn.DAYS($U7,$T7)+1))*$S7)*IF($X$1="Físico",1,$X7) -> 0 | CL7: =(IF(AND(AND($T7>=(CL$4-DAY(CL$4)+1),$T7<=CL$4),AND($U7>=(CL$4-DAY(CL$4)+1),$U7<=CL$4)),$U7-$T7+1,IF(AND($T7>=(CL$4-DAY(CL$4)+1),$T7<=CL$4),CL$4-$T7+1,IF(AND($U7>=(CL$4-DAY(CL$4)+1),$U7<=CL$4),$U7-(CL$4-DAY(CL$4)+1)+1,IF(OR(AND((CL$4-DAY(CL$4)+1)>=$T7,(CL$4-DAY(CL$4)+1)<=$U7),AND((CL$4>=$T7),(CL$4<=$U7))),CL$4-(CL$4-DAY(CL$4)+1)+1,0))))/IF($R7="mes",_xlfn.DAYS(CL$4,(CL$4-DAY(CL$4)+1))+1,(_xlfn.DAYS($U7,$T7)+1))*$S7)*IF($X$1="Físico",1,$X7) -> 0 | CM7: =(IF(AND(AND($T7>=(CM$4-DAY(CM$4)+1),$T7<=CM$4),AND($U7>=(CM$4-DAY(CM$4)+1),$U7<=CM$4)),$U7-$T7+1,IF(AND($T7>=(CM$4-DAY(CM$4)+1),$T7<=CM$4),CM$4-$T7+1,IF(AND($U7>=(CM$4-DAY(CM$4)+1),$U7<=CM$4),$U7-(CM$4-DAY(CM$4)+1)+1,IF(OR(AND((CM$4-DAY(CM$4)+1)>=$T7,(CM$4-DAY(CM$4)+1)<=$U7),AND((CM$4>=$T7),(CM$4<=$U7))),CM$4-(CM$4-DAY(CM$4)+1)+1,0))))/IF($R7="mes",_xlfn.DAYS(CM$4,(CM$4-DAY(CM$4)+1))+1,(_xlfn.DAYS($U7,$T7)+1))*$S7)*IF($X$1="Físico",1,$X7) -> 0 | CN7: =(IF(AND(AND($T7>=(CN$4-DAY(CN$4)+1),$T7<=CN$4),AND($U7>=(CN$4-DAY(CN$4)+1),$U7<=CN$4)),$U7-$T7+1,IF(AND($T7>=(CN$4-DAY(CN$4)+1),$T7<=CN$4),CN$4-$T7+1,IF(AND($U7>=(CN$4-DAY(CN$4)+1),$U7<=CN$4),$U7-(CN$4-DAY(CN$4)+1)+1,IF(OR(AND((CN$4-DAY(CN$4)+1)>=$T7,(CN$4-DAY(CN$4)+1)<=$U7),AND((CN$4>=$T7),(CN$4<=$U7))),CN$4-(CN$4-DAY(CN$4)+1)+1,0))))/IF($R7="mes",_xlfn.DAYS(CN$4,(CN$4-DAY(CN$4)+1))+1,(_xlfn.DAYS($U7,$T7)+1))*$S7)*IF($X$1="Físico",1,$X7) -> 0 | CO7: =(IF(AND(AND($T7>=(CO$4-DAY(CO$4)+1),$T7<=CO$4),AND($U7>=(CO$4-DAY(CO$4)+1),$U7<=CO$4)),$U7-$T7+1,IF(AND($T7>=(CO$4-DAY(CO$4)+1),$T7<=CO$4),CO$4-$T7+1,IF(AND($U7>=(CO$4-DAY(CO$4)+1),$U7<=CO$4),$U7-(CO$4-DAY(CO$4)+1)+1,IF(OR(AND((CO$4-DAY(CO$4)+1)>=$T7,(CO$4-DAY(CO$4)+1)<=$U7),AND((CO$4>=$T7),(CO$4<=$U7))),CO$4-(CO$4-DAY(CO$4)+1)+1,0))))/IF($R7="mes",_xlfn.DAYS(CO$4,(CO$4-DAY(CO$4)+1))+1,(_xlfn.DAYS($U7,$T7)+1))*$S7)*IF($X$1="Físico",1,$X7) -> 0 | CP7: =(IF(AND(AND($T7>=(CP$4-DAY(CP$4)+1),$T7<=CP$4),AND($U7>=(CP$4-DAY(CP$4)+1),$U7<=CP$4)),$U7-$T7+1,IF(AND($T7>=(CP$4-DAY(CP$4)+1),$T7<=CP$4),CP$4-$T7+1,IF(AND($U7>=(CP$4-DAY(CP$4)+1),$U7<=CP$4),$U7-(CP$4-DAY(CP$4)+1)+1,IF(OR(AND((CP$4-DAY(CP$4)+1)>=$T7,(CP$4-DAY(CP$4)+1)<=$U7),AND((CP$4>=$T7),(CP$4<=$U7))),CP$4-(CP$4-DAY(CP$4)+1)+1,0))))/IF($R7="mes",_xlfn.DAYS(CP$4,(CP$4-DAY(CP$4)+1))+1,(_xlfn.DAYS($U7,$T7)+1))*$S7)*IF($X$1="Físico",1,$X7) -> 0 | CQ7: =(IF(AND(AND($T7>=(CQ$4-DAY(CQ$4)+1),$T7<=CQ$4),AND($U7>=(CQ$4-DAY(CQ$4)+1),$U7<=CQ$4)),$U7-$T7+1,IF(AND($T7>=(CQ$4-DAY(CQ$4)+1),$T7<=CQ$4),CQ$4-$T7+1,IF(AND($U7>=(CQ$4-DAY(CQ$4)+1),$U7<=CQ$4),$U7-(CQ$4-DAY(CQ$4)+1)+1,IF(OR(AND((CQ$4-DAY(CQ$4)+1)>=$T7,(CQ$4-DAY(CQ$4)+1)<=$U7),AND((CQ$4>=$T7),(CQ$4<=$U7))),CQ$4-(CQ$4-DAY(CQ$4)+1)+1,0))))/IF($R7="mes",_xlfn.DAYS(CQ$4,(CQ$4-DAY(CQ$4)+1))+1,(_xlfn.DAYS($U7,$T7)+1))*$S7)*IF($X$1="Físico",1,$X7) -> 0 | CR7: =(IF(AND(AND($T7>=(CR$4-DAY(CR$4)+1),$T7<=CR$4),AND($U7>=(CR$4-DAY(CR$4)+1),$U7<=CR$4)),$U7-$T7+1,IF(AND($T7>=(CR$4-DAY(CR$4)+1),$T7<=CR$4),CR$4-$T7+1,IF(AND($U7>=(CR$4-DAY(CR$4)+1),$U7<=CR$4),$U7-(CR$4-DAY(CR$4)+1)+1,IF(OR(AND((CR$4-DAY(CR$4)+1)>=$T7,(CR$4-DAY(CR$4)+1)<=$U7),AND((CR$4>=$T7),(CR$4<=$U7))),CR$4-(CR$4-DAY(CR$4)+1)+1,0))))/IF($R7="mes",_xlfn.DAYS(CR$4,(CR$4-DAY(CR$4)+1))+1,(_xlfn.DAYS($U7,$T7)+1))*$S7)*IF($X$1="Físico",1,$X7) -> 0 | ... EQ7: =(IF(AND(AND($T7>=(EQ$4-DAY(EQ$4)+1),$T7<=EQ$4),AND($U7>=(EQ$4-DAY(EQ$4)+1),$U7<=EQ$4)),$U7-$T7+1,IF(AND($T7>=(EQ$4-DAY(EQ$4)+1),$T7<=EQ$4),EQ$4-$T7+1,IF(AND($U7>=(EQ$4-DAY(EQ$4)+1),$U7<=EQ$4),$U7-(EQ$4-DAY(EQ$4)+1)+1,IF(OR(AND((EQ$4-DAY(EQ$4)+1)>=$T7,(EQ$4-DAY(EQ$4)+1)<=$U7),AND((EQ$4>=$T7),(EQ$4<=$U7))),EQ$4-(EQ$4-DAY(EQ$4)+1)+1,0))))/IF($R7="mes",_xlfn.DAYS(EQ$4,(EQ$4-DAY(EQ$4)+1))+1,(_xlfn.DAYS($U7,$T7)+1))*$S7)*IF($X$1="Físico",1,$X7) -> 0
D8: =IF(E8=$L$7,$M$1,$N$1) -> 1.0341959 | E8: =VLOOKUP(TEXT(Z8,0),'G2'!B:D,3,0) -> MN | F8: =SUM(BS8:CB8) -> 3.0658671 | G8: =IF(OR($I8="REAL",$I8="INCURRIDO"),$I8&" "&$Z8&" "&O8&" "&Q8,) -> INCURRIDO 91243110 CO-H-007/2024 BERG_CAD | H8: MB-2025 | I8: INCURRIDO | J8: FEE SS | K8: 510109 | L8: =IFERROR(VLOOKUP(TEXT(Z8,0),'G2'!$B$5:$D$21,3,0),"") -> MN | N8: Geólogo Juan R. | O8: CO-H-007/2024 | Q8: BERG_CAD | R8: mes | T8: 45505 | U8: 45777 | V8: =(U8-T8)/30 -> 9.0666667 | W8: 0 | X8: {=+IF($W$1="Pesos CLP",W8,W8/TC)*MB_24A25} -> 0 | Y8: =SUM(BH8:DU8) -> 3.0658671 | Z8: 91243110 | AA8: =IF(OR($I8="REAL",$I8="INCURRIDO"),SUMIF(S!$O:$O,$I8&$O8&$Q8&UPPER(TEXT(AA$4,"MMMMYYYY"))&$Z8,IF($W$1="Pesos CLP",S!$AD:$AD,S!$AO:$AO)),0) -> 0 | AB8: =IF(OR($I8="REAL",$I8="INCURRIDO"),SUMIF(S!$O:$O,$I8&$O8&$Q8&UPPER(TEXT(AB$4,"MMMMYYYY"))&$Z8,IF($W$1="Pesos CLP",S!$AD:$AD,S!$AO:$AO)),0) -> 0 | AC8: =IF(OR($I8="REAL",$I8="INCURRIDO"),SUMIF(S!$O:$O,$I8&$O8&$Q8&UPPER(TEXT(AC$4,"MMMMYYYY"))&$Z8,IF($W$1="Pesos CLP",S!$AD:$AD,S!$AO:$AO)),0) -> 0 | AD8: =IF(OR($I8="REAL",$I8="INCURRIDO"),SUMIF(S!$O:$O,$I8&$O8&$Q8&UPPER(TEXT(AD$4,"MMMMYYYY"))&$Z8,IF($W$1="Pesos CLP",S!$AD:$AD,S!$AO:$AO)),0) -> 0 | AE8: =IF(OR($I8="REAL",$I8="INCURRIDO"),SUMIF(S!$O:$O,$I8&$O8&$Q8&UPPER(TEXT(AE$4,"MMMMYYYY"))&$Z8,IF($W$1="Pesos CLP",S!$AD:$AD,S!$AO:$AO)),0) -> 0 | AF8: =IF(OR($I8="REAL",$I8="INCURRIDO"),SUMIF(S!$O:$O,$I8&$O8&$Q8&UPPER(TEXT(AF$4,"MMMMYYYY"))&$Z8,IF($W$1="Pesos CLP",S!$AD:$AD,S!$AO:$AO)),0) -> 0 | AG8: =IF(OR($I8="REAL",$I8="INCURRIDO"),SUMIF(S!$O:$O,$I8&$O8&$Q8&UPPER(TEXT(AG$4,"MMMMYYYY"))&$Z8,IF($W$1="Pesos CLP",S!$AD:$AD,S!$AO:$AO)),0) -> 0 | AH8: =IF(OR($I8="REAL",$I8="INCURRIDO"),SUMIF(S!$O:$O,$I8&$O8&$Q8&UPPER(TEXT(AH$4,"MMMMYYYY"))&$Z8,IF($W$1="Pesos CLP",S!$AD:$AD,S!$AO:$AO)),0) -> 0 | ... CJ8: =IF(OR($I8="REAL",$I8="INCURRIDO"),SUMIF(S!$O:$O,$I8&$O8&$Q8&UPPER(TEXT(CJ$4,"MMMMYYYY"))&$Z8,IF($W$1="Pesos CLP",S!$AD:$AD,S!$AO:$AO)),0) -> 0 | CK8: =(IF(AND(AND($T8>=(CK$4-DAY(CK$4)+1),$T8<=CK$4),AND($U8>=(CK$4-DAY(CK$4)+1),$U8<=CK$4)),$U8-$T8+1,IF(AND($T8>=(CK$4-DAY(CK$4)+1),$T8<=CK$4),CK$4-$T8+1,IF(AND($U8>=(CK$4-DAY(CK$4)+1),$U8<=CK$4),$U8-(CK$4-DAY(CK$4)+1)+1,IF(OR(AND((CK$4-DAY(CK$4)+1)>=$T8,(CK$4-DAY(CK$4)+1)<=$U8),AND((CK$4>=$T8),(CK$4<=$U8))),CK$4-(CK$4-DAY(CK$4)+1)+1,0))))/IF($R8="mes",_xlfn.DAYS(CK$4,(CK$4-DAY(CK$4)+1))+1,(_xlfn.DAYS($U8,$T8)+1))*$S8)*IF($X$1="Físico",1,$X8) -> 0 | CL8: =(IF(AND(AND($T8>=(CL$4-DAY(CL$4)+1),$T8<=CL$4),AND($U8>=(CL$4-DAY(CL$4)+1),$U8<=CL$4)),$U8-$T8+1,IF(AND($T8>=(CL$4-DAY(CL$4)+1),$T8<=CL$4),CL$4-$T8+1,IF(AND($U8>=(CL$4-DAY(CL$4)+1),$U8<=CL$4),$U8-(CL$4-DAY(CL$4)+1)+1,IF(OR(AND((CL$4-DAY(CL$4)+1)>=$T8,(CL$4-DAY(CL$4)+1)<=$U8),AND((CL$4>=$T8),(CL$4<=$U8))),CL$4-(CL$4-DAY(CL$4)+1)+1,0))))/IF($R8="mes",_xlfn.DAYS(CL$4,(CL$4-DAY(CL$4)+1))+1,(_xlfn.DAYS($U8,$T8)+1))*$S8)*IF($X$1="Físico",1,$X8) -> 0 | CM8: =(IF(AND(AND($T8>=(CM$4-DAY(CM$4)+1),$T8<=CM$4),AND($U8>=(CM$4-DAY(CM$4)+1),$U8<=CM$4)),$U8-$T8+1,IF(AND($T8>=(CM$4-DAY(CM$4)+1),$T8<=CM$4),CM$4-$T8+1,IF(AND($U8>=(CM$4-DAY(CM$4)+1),$U8<=CM$4),$U8-(CM$4-DAY(CM$4)+1)+1,IF(OR(AND((CM$4-DAY(CM$4)+1)>=$T8,(CM$4-DAY(CM$4)+1)<=$U8),AND((CM$4>=$T8),(CM$4<=$U8))),CM$4-(CM$4-DAY(CM$4)+1)+1,0))))/IF($R8="mes",_xlfn.DAYS(CM$4,(CM$4-DAY(CM$4)+1))+1,(_xlfn.DAYS($U8,$T8)+1))*$S8)*IF($X$1="Físico",1,$X8) -> 0 | CN8: =(IF(AND(AND($T8>=(CN$4-DAY(CN$4)+1),$T8<=CN$4),AND($U8>=(CN$4-DAY(CN$4)+1),$U8<=CN$4)),$U8-$T8+1,IF(AND($T8>=(CN$4-DAY(CN$4)+1),$T8<=CN$4),CN$4-$T8+1,IF(AND($U8>=(CN$4-DAY(CN$4)+1),$U8<=CN$4),$U8-(CN$4-DAY(CN$4)+1)+1,IF(OR(AND((CN$4-DAY(CN$4)+1)>=$T8,(CN$4-DAY(CN$4)+1)<=$U8),AND((CN$4>=$T8),(CN$4<=$U8))),CN$4-(CN$4-DAY(CN$4)+1)+1,0))))/IF($R8="mes",_xlfn.DAYS(CN$4,(CN$4-DAY(CN$4)+1))+1,(_xlfn.DAYS($U8,$T8)+1))*$S8)*IF($X$1="Físico",1,$X8) -> 0 | CO8: =(IF(AND(AND($T8>=(CO$4-DAY(CO$4)+1),$T8<=CO$4),AND($U8>=(CO$4-DAY(CO$4)+1),$U8<=CO$4)),$U8-$T8+1,IF(AND($T8>=(CO$4-DAY(CO$4)+1),$T8<=CO$4),CO$4-$T8+1,IF(AND($U8>=(CO$4-DAY(CO$4)+1),$U8<=CO$4),$U8-(CO$4-DAY(CO$4)+1)+1,IF(OR(AND((CO$4-DAY(CO$4)+1)>=$T8,(CO$4-DAY(CO$4)+1)<=$U8),AND((CO$4>=$T8),(CO$4<=$U8))),CO$4-(CO$4-DAY(CO$4)+1)+1,0))))/IF($R8="mes",_xlfn.DAYS(CO$4,(CO$4-DAY(CO$4)+1))+1,(_xlfn.DAYS($U8,$T8)+1))*$S8)*IF($X$1="Físico",1,$X8) -> 0 | CP8: =(IF(AND(AND($T8>=(CP$4-DAY(CP$4)+1),$T8<=CP$4),AND($U8>=(CP$4-DAY(CP$4)+1),$U8<=CP$4)),$U8-$T8+1,IF(AND($T8>=(CP$4-DAY(CP$4)+1),$T8<=CP$4),CP$4-$T8+1,IF(AND($U8>=(CP$4-DAY(CP$4)+1),$U8<=CP$4),$U8-(CP$4-DAY(CP$4)+1)+1,IF(OR(AND((CP$4-DAY(CP$4)+1)>=$T8,(CP$4-DAY(CP$4)+1)<=$U8),AND((CP$4>=$T8),(CP$4<=$U8))),CP$4-(CP$4-DAY(CP$4)+1)+1,0))))/IF($R8="mes",_xlfn.DAYS(CP$4,(CP$4-DAY(CP$4)+1))+1,(_xlfn.DAYS($U8,$T8)+1))*$S8)*IF($X$1="Físico",1,$X8) -> 0 | CQ8: =(IF(AND(AND($T8>=(CQ$4-DAY(CQ$4)+1),$T8<=CQ$4),AND($U8>=(CQ$4-DAY(CQ$4)+1),$U8<=CQ$4)),$U8-$T8+1,IF(AND($T8>=(CQ$4-DAY(CQ$4)+1),$T8<=CQ$4),CQ$4-$T8+1,IF(AND($U8>=(CQ$4-DAY(CQ$4)+1),$U8<=CQ$4),$U8-(CQ$4-DAY(CQ$4)+1)+1,IF(OR(AND((CQ$4-DAY(CQ$4)+1)>=$T8,(CQ$4-DAY(CQ$4)+1)<=$U8),AND((CQ$4>=$T8),(CQ$4<=$U8))),CQ$4-(CQ$4-DAY(CQ$4)+1)+1,0))))/IF($R8="mes",_xlfn.DAYS(CQ$4,(CQ$4-DAY(CQ$4)+1))+1,(_xlfn.DAYS($U8,$T8)+1))*$S8)*IF($X$1="Físico",1,$X8) -> 0 | CR8: =(IF(AND(AND($T8>=(CR$4-DAY(CR$4)+1),$T8<=CR$4),AND($U8>=(CR$4-DAY(CR$4)+1),$U8<=CR$4)),$U8-$T8+1,IF(AND($T8>=(CR$4-DAY(CR$4)+1),$T8<=CR$4),CR$4-$T8+1,IF(AND($U8>=(CR$4-DAY(CR$4)+1),$U8<=CR$4),$U8-(CR$4-DAY(CR$4)+1)+1,IF(OR(AND((CR$4-DAY(CR$4)+1)>=$T8,(CR$4-DAY(CR$4)+1)<=$U8),AND((CR$4>=$T8),(CR$4<=$U8))),CR$4-(CR$4-DAY(CR$4)+1)+1,0))))/IF($R8="mes",_xlfn.DAYS(CR$4,(CR$4-DAY(CR$4)+1))+1,(_xlfn.DAYS($U8,$T8)+1))*$S8)*IF($X$1="Físico",1,$X8) -> 0 | ... EQ8: =(IF(AND(AND($T8>=(EQ$4-DAY(EQ$4)+1),$T8<=EQ$4),AND($U8>=(EQ$4-DAY(EQ$4)+1),$U8<=EQ$4)),$U8-$T8+1,IF(AND($T8>=(EQ$4-DAY(EQ$4)+1),$T8<=EQ$4),EQ$4-$T8+1,IF(AND($U8>=(EQ$4-DAY(EQ$4)+1),$U8<=EQ$4),$U8-(EQ$4-DAY(EQ$4)+1)+1,IF(OR(AND((EQ$4-DAY(EQ$4)+1)>=$T8,(EQ$4-DAY(EQ$4)+1)<=$U8),AND((EQ$4>=$T8),(EQ$4<=$U8))),EQ$4-(EQ$4-DAY(EQ$4)+1)+1,0))))/IF($R8="mes",_xlfn.DAYS(EQ$4,(EQ$4-DAY(EQ$4)+1))+1,(_xlfn.DAYS($U8,$T8)+1))*$S8)*IF($X$1="Físico",1,$X8) -> 0
D9: =IF(E9=$L$7,$M$1,$N$1) -> 1.0341959 | E9: =VLOOKUP(TEXT(Z9,0),'G2'!B:D,3,0) -> MN | F9: =SUM(BS9:CB9) -> 3532.3038 | G9: =IF(OR($I9="REAL",$I9="INCURRIDO"),$I9&" "&$Z9&" "&O9&" "&Q9,) -> INCURRIDO 91243110 CO-H-007/2024 CANN_AUS | H9: MB-2025 | I9: INCURRIDO | J9: FEE SS | K9: 510109 | L9: =IFERROR(VLOOKUP(TEXT(Z9,0),'G2'!$B$5:$D$21,3,0),"") -> MN | N9: Geólogo Juan R. | O9: CO-H-007/2024 | Q9: CANN_AUS | R9: mes | T9: 45505 | U9: 45777 | V9: =(U9-T9)/30 -> 9.0666667 | W9: 0 | X9: {=+IF($W$1="Pesos CLP",W9,W9/TC)*MB_24A25} -> 0 | Y9: =SUM(BH9:DU9) -> 3532.3038 | Z9: 91243110 | AA9: =IF(OR($I9="REAL",$I9="INCURRIDO"),SUMIF(S!$O:$O,$I9&$O9&$Q9&UPPER(TEXT(AA$4,"MMMMYYYY"))&$Z9,IF($W$1="Pesos CLP",S!$AD:$AD,S!$AO:$AO)),0) -> 0 | AB9: =IF(OR($I9="REAL",$I9="INCURRIDO"),SUMIF(S!$O:$O,$I9&$O9&$Q9&UPPER(TEXT(AB$4,"MMMMYYYY"))&$Z9,IF($W$1="Pesos CLP",S!$AD:$AD,S!$AO:$AO)),0) -> 0 | AC9: =IF(OR($I9="REAL",$I9="INCURRIDO"),SUMIF(S!$O:$O,$I9&$O9&$Q9&UPPER(TEXT(AC$4,"MMMMYYYY"))&$Z9,IF($W$1="Pesos CLP",S!$AD:$AD,S!$AO:$AO)),0) -> 0 | AD9: =IF(OR($I9="REAL",$I9="INCURRIDO"),SUMIF(S!$O:$O,$I9&$O9&$Q9&UPPER(TEXT(AD$4,"MMMMYYYY"))&$Z9,IF($W$1="Pesos CLP",S!$AD:$AD,S!$AO:$AO)),0) -> 0 | AE9: =IF(OR($I9="REAL",$I9="INCURRIDO"),SUMIF(S!$O:$O,$I9&$O9&$Q9&UPPER(TEXT(AE$4,"MMMMYYYY"))&$Z9,IF($W$1="Pesos CLP",S!$AD:$AD,S!$AO:$AO)),0) -> 0 | AF9: =IF(OR($I9="REAL",$I9="INCURRIDO"),SUMIF(S!$O:$O,$I9&$O9&$Q9&UPPER(TEXT(AF$4,"MMMMYYYY"))&$Z9,IF($W$1="Pesos CLP",S!$AD:$AD,S!$AO:$AO)),0) -> 0 | AG9: =IF(OR($I9="REAL",$I9="INCURRIDO"),SUMIF(S!$O:$O,$I9&$O9&$Q9&UPPER(TEXT(AG$4,"MMMMYYYY"))&$Z9,IF($W$1="Pesos CLP",S!$AD:$AD,S!$AO:$AO)),0) -> 0 | AH9: =IF(OR($I9="REAL",$I9="INCURRIDO"),SUMIF(S!$O:$O,$I9&$O9&$Q9&UPPER(TEXT(AH$4,"MMMMYYYY"))&$Z9,IF($W$1="Pesos CLP",S!$AD:$AD,S!$AO:$AO)),0) -> 0 | ... CJ9: =IF(OR($I9="REAL",$I9="INCURRIDO"),SUMIF(S!$O:$O,$I9&$O9&$Q9&UPPER(TEXT(CJ$4,"MMMMYYYY"))&$Z9,IF($W$1="Pesos CLP",S!$AD:$AD,S!$AO:$AO)),0) -> 0 | CK9: =(IF(AND(AND($T9>=(CK$4-DAY(CK$4)+1),$T9<=CK$4),AND($U9>=(CK$4-DAY(CK$4)+1),$U9<=CK$4)),$U9-$T9+1,IF(AND($T9>=(CK$4-DAY(CK$4)+1),$T9<=CK$4),CK$4-$T9+1,IF(AND($U9>=(CK$4-DAY(CK$4)+1),$U9<=CK$4),$U9-(CK$4-DAY(CK$4)+1)+1,IF(OR(AND((CK$4-DAY(CK$4)+1)>=$T9,(CK$4-DAY(CK$4)+1)<=$U9),AND((CK$4>=$T9),(CK$4<=$U9))),CK$4-(CK$4-DAY(CK$4)+1)+1,0))))/IF($R9="mes",_xlfn.DAYS(CK$4,(CK$4-DAY(CK$4)+1))+1,(_xlfn.DAYS($U9,$T9)+1))*$S9)*IF($X$1="Físico",1,$X9) -> 0 | CL9: =(IF(AND(AND($T9>=(CL$4-DAY(CL$4)+1),$T9<=CL$4),AND($U9>=(CL$4-DAY(CL$4)+1),$U9<=CL$4)),$U9-$T9+1,IF(AND($T9>=(CL$4-DAY(CL$4)+1),$T9<=CL$4),CL$4-$T9+1,IF(AND($U9>=(CL$4-DAY(CL$4)+1),$U9<=CL$4),$U9-(CL$4-DAY(CL$4)+1)+1,IF(OR(AND((CL$4-DAY(CL$4)+1)>=$T9,(CL$4-DAY(CL$4)+1)<=$U9),AND((CL$4>=$T9),(CL$4<=$U9))),CL$4-(CL$4-DAY(CL$4)+1)+1,0))))/IF($R9="mes",_xlfn.DAYS(CL$4,(CL$4-DAY(CL$4)+1))+1,(_xlfn.DAYS($U9,$T9)+1))*$S9)*IF($X$1="Físico",1,$X9) -> 0 | CM9: =(IF(AND(AND($T9>=(CM$4-DAY(CM$4)+1),$T9<=CM$4),AND($U9>=(CM$4-DAY(CM$4)+1),$U9<=CM$4)),$U9-$T9+1,IF(AND($T9>=(CM$4-DAY(CM$4)+1),$T9<=CM$4),CM$4-$T9+1,IF(AND($U9>=(CM$4-DAY(CM$4)+1),$U9<=CM$4),$U9-(CM$4-DAY(CM$4)+1)+1,IF(OR(AND((CM$4-DAY(CM$4)+1)>=$T9,(CM$4-DAY(CM$4)+1)<=$U9),AND((CM$4>=$T9),(CM$4<=$U9))),CM$4-(CM$4-DAY(CM$4)+1)+1,0))))/IF($R9="mes",_xlfn.DAYS(CM$4,(CM$4-DAY(CM$4)+1))+1,(_xlfn.DAYS($U9,$T9)+1))*$S9)*IF($X$1="Físico",1,$X9) -> 0 | CN9: =(IF(AND(AND($T9>=(CN$4-DAY(CN$4)+1),$T9<=CN$4),AND($U9>=(CN$4-DAY(CN$4)+1),$U9<=CN$4)),$U9-$T9+1,IF(AND($T9>=(CN$4-DAY(CN$4)+1),$T9<=CN$4),CN$4-$T9+1,IF(AND($U9>=(CN$4-DAY(CN$4)+1),$U9<=CN$4),$U9-(CN$4-DAY(CN$4)+1)+1,IF(OR(AND((CN$4-DAY(CN$4)+1)>=$T9,(CN$4-DAY(CN$4)+1)<=$U9),AND((CN$4>=$T9),(CN$4<=$U9))),CN$4-(CN$4-DAY(CN$4)+1)+1,0))))/IF($R9="mes",_xlfn.DAYS(CN$4,(CN$4-DAY(CN$4)+1))+1,(_xlfn.DAYS($U9,$T9)+1))*$S9)*IF($X$1="Físico",1,$X9) -> 0 | CO9: =(IF(AND(AND($T9>=(CO$4-DAY(CO$4)+1),$T9<=CO$4),AND($U9>=(CO$4-DAY(CO$4)+1),$U9<=CO$4)),$U9-$T9+1,IF(AND($T9>=(CO$4-DAY(CO$4)+1),$T9<=CO$4),CO$4-$T9+1,IF(AND($U9>=(CO$4-DAY(CO$4)+1),$U9<=CO$4),$U9-(CO$4-DAY(CO$4)+1)+1,IF(OR(AND((CO$4-DAY(CO$4)+1)>=$T9,(CO$4-DAY(CO$4)+1)<=$U9),AND((CO$4>=$T9),(CO$4<=$U9))),CO$4-(CO$4-DAY(CO$4)+1)+1,0))))/IF($R9="mes",_xlfn.DAYS(CO$4,(CO$4-DAY(CO$4)+1))+1,(_xlfn.DAYS($U9,$T9)+1))*$S9)*IF($X$1="Físico",1,$X9) -> 0 | CP9: =(IF(AND(AND($T9>=(CP$4-DAY(CP$4)+1),$T9<=CP$4),AND($U9>=(CP$4-DAY(CP$4)+1),$U9<=CP$4)),$U9-$T9+1,IF(AND($T9>=(CP$4-DAY(CP$4)+1),$T9<=CP$4),CP$4-$T9+1,IF(AND($U9>=(CP$4-DAY(CP$4)+1),$U9<=CP$4),$U9-(CP$4-DAY(CP$4)+1)+1,IF(OR(AND((CP$4-DAY(CP$4)+1)>=$T9,(CP$4-DAY(CP$4)+1)<=$U9),AND((CP$4>=$T9),(CP$4<=$U9))),CP$4-(CP$4-DAY(CP$4)+1)+1,0))))/IF($R9="mes",_xlfn.DAYS(CP$4,(CP$4-DAY(CP$4)+1))+1,(_xlfn.DAYS($U9,$T9)+1))*$S9)*IF($X$1="Físico",1,$X9) -> 0 | CQ9: =(IF(AND(AND($T9>=(CQ$4-DAY(CQ$4)+1),$T9<=CQ$4),AND($U9>=(CQ$4-DAY(CQ$4)+1),$U9<=CQ$4)),$U9-$T9+1,IF(AND($T9>=(CQ$4-DAY(CQ$4)+1),$T9<=CQ$4),CQ$4-$T9+1,IF(AND($U9>=(CQ$4-DAY(CQ$4)+1),$U9<=CQ$4),$U9-(CQ$4-DAY(CQ$4)+1)+1,IF(OR(AND((CQ$4-DAY(CQ$4)+1)>=$T9,(CQ$4-DAY(CQ$4)+1)<=$U9),AND((CQ$4>=$T9),(CQ$4<=$U9))),CQ$4-(CQ$4-DAY(CQ$4)+1)+1,0))))/IF($R9="mes",_xlfn.DAYS(CQ$4,(CQ$4-DAY(CQ$4)+1))+1,(_xlfn.DAYS($U9,$T9)+1))*$S9)*IF($X$1="Físico",1,$X9) -> 0 | CR9: =(IF(AND(AND($T9>=(CR$4-DAY(CR$4)+1),$T9<=CR$4),AND($U9>=(CR$4-DAY(CR$4)+1),$U9<=CR$4)),$U9-$T9+1,IF(AND($T9>=(CR$4-DAY(CR$4)+1),$T9<=CR$4),CR$4-$T9+1,IF(AND($U9>=(CR$4-DAY(CR$4)+1),$U9<=CR$4),$U9-(CR$4-DAY(CR$4)+1)+1,IF(OR(AND((CR$4-DAY(CR$4)+1)>=$T9,(CR$4-DAY(CR$4)+1)<=$U9),AND((CR$4>=$T9),(CR$4<=$U9))),CR$4-(CR$4-DAY(CR$4)+1)+1,0))))/IF($R9="mes",_xlfn.DAYS(CR$4,(CR$4-DAY(CR$4)+1))+1,(_xlfn.DAYS($U9,$T9)+1))*$S9)*IF($X$1="Físico",1,$X9) -> 0 | ... EQ9: =(IF(AND(AND($T9>=(EQ$4-DAY(EQ$4)+1),$T9<=EQ$4),AND($U9>=(EQ$4-DAY(EQ$4)+1),$U9<=EQ$4)),$U9-$T9+1,IF(AND($T9>=(EQ$4-DAY(EQ$4)+1),$T9<=EQ$4),EQ$4-$T9+1,IF(AND($U9>=(EQ$4-DAY(EQ$4)+1),$U9<=EQ$4),$U9-(EQ$4-DAY(EQ$4)+1)+1,IF(OR(AND((EQ$4-DAY(EQ$4)+1)>=$T9,(EQ$4-DAY(EQ$4)+1)<=$U9),AND((EQ$4>=$T9),(EQ$4<=$U9))),EQ$4-(EQ$4-DAY(EQ$4)+1)+1,0))))/IF($R9="mes",_xlfn.DAYS(EQ$4,(EQ$4-DAY(EQ$4)+1))+1,(_xlfn.DAYS($U9,$T9)+1))*$S9)*IF($X$1="Físico",1,$X9) -> 0
D10: =IF(E10=$L$7,$M$1,$N$1) -> 1.0341959 | E10: =VLOOKUP(TEXT(Z10,0),'G2'!B:D,3,0) -> MN | F10: =SUM(BS10:CB10) -> 18352.156 | G10: =IF(OR($I10="REAL",$I10="INCURRIDO"),$I10&" "&$Z10&" "&O10&" "&Q10,) -> REAL 91243110 CO-H-007/2024 CANN_AUS | H10: MB-2025 | I10: REAL | J10: FEE SS | K10: 510102 | L10: =IFERROR(VLOOKUP(TEXT(Z10,0),'G2'!$B$5:$D$21,3,0),"") -> MN | N10: Geólogo Juan R. | O10: CO-H-007/2024 | Q10: CANN_AUS | R10: mes | T10: 45505 | U10: 45777 | V10: =(U10-T10)/30 -> 9.0666667 | W10: 0 | X10: {=+IF($W$1="Pesos CLP",W10,W10/TC)*MB_24A25} -> 0 | Y10: =SUM(BH10:DU10) -> 18352.156 | Z10: 91243110 | AA10: =IF(OR($I10="REAL",$I10="INCURRIDO"),SUMIF(S!$O:$O,$I10&$O10&$Q10&UPPER(TEXT(AA$4,"MMMMYYYY"))&$Z10,IF($W$1="Pesos CLP",S!$AD:$AD,S!$AO:$AO)),0) -> 0 | AB10: =IF(OR($I10="REAL",$I10="INCURRIDO"),SUMIF(S!$O:$O,$I10&$O10&$Q10&UPPER(TEXT(AB$4,"MMMMYYYY"))&$Z10,IF($W$1="Pesos CLP",S!$AD:$AD,S!$AO:$AO)),0) -> 0 | AC10: =IF(OR($I10="REAL",$I10="INCURRIDO"),SUMIF(S!$O:$O,$I10&$O10&$Q10&UPPER(TEXT(AC$4,"MMMMYYYY"))&$Z10,IF($W$1="Pesos CLP",S!$AD:$AD,S!$AO:$AO)),0) -> 0 | AD10: =IF(OR($I10="REAL",$I10="INCURRIDO"),SUMIF(S!$O:$O,$I10&$O10&$Q10&UPPER(TEXT(AD$4,"MMMMYYYY"))&$Z10,IF($W$1="Pesos CLP",S!$AD:$AD,S!$AO:$AO)),0) -> 0 | AE10: =IF(OR($I10="REAL",$I10="INCURRIDO"),SUMIF(S!$O:$O,$I10&$O10&$Q10&UPPER(TEXT(AE$4,"MMMMYYYY"))&$Z10,IF($W$1="Pesos CLP",S!$AD:$AD,S!$AO:$AO)),0) -> 0 | AF10: =IF(OR($I10="REAL",$I10="INCURRIDO"),SUMIF(S!$O:$O,$I10&$O10&$Q10&UPPER(TEXT(AF$4,"MMMMYYYY"))&$Z10,IF($W$1="Pesos CLP",S!$AD:$AD,S!$AO:$AO)),0) -> 0 | AG10: =IF(OR($I10="REAL",$I10="INCURRIDO"),SUMIF(S!$O:$O,$I10&$O10&$Q10&UPPER(TEXT(AG$4,"MMMMYYYY"))&$Z10,IF($W$1="Pesos CLP",S!$AD:$AD,S!$AO:$AO)),0) -> 0 | AH10: =IF(OR($I10="REAL",$I10="INCURRIDO"),SUMIF(S!$O:$O,$I10&$O10&$Q10&UPPER(TEXT(AH$4,"MMMMYYYY"))&$Z10,IF($W$1="Pesos CLP",S!$AD:$AD,S!$AO:$AO)),0) -> 0 | ... CJ10: =IF(OR($I10="REAL",$I10="INCURRIDO"),SUMIF(S!$O:$O,$I10&$O10&$Q10&UPPER(TEXT(CJ$4,"MMMMYYYY"))&$Z10,IF($W$1="Pesos CLP",S!$AD:$AD,S!$AO:$AO)),0) -> 0 | CK10: =(IF(AND(AND($T10>=(CK$4-DAY(CK$4)+1),$T10<=CK$4),AND($U10>=(CK$4-DAY(CK$4)+1),$U10<=CK$4)),$U10-$T10+1,IF(AND($T10>=(CK$4-DAY(CK$4)+1),$T10<=CK$4),CK$4-$T10+1,IF(AND($U10>=(CK$4-DAY(CK$4)+1),$U10<=CK$4),$U10-(CK$4-DAY(CK$4)+1)+1,IF(OR(AND((CK$4-DAY(CK$4)+1)>=$T10,(CK$4-DAY(CK$4)+1)<=$U10),AND((CK$4>=$T10),(CK$4<=$U10))),CK$4-(CK$4-DAY(CK$4)+1)+1,0))))/IF($R10="mes",_xlfn.DAYS(CK$4,(CK$4-DAY(CK$4)+1))+1,(_xlfn.DAYS($U10,$T10)+1))*$S10)*IF($X$1="Físico",1,$X10) -> 0 | CL10: =(IF(AND(AND($T10>=(CL$4-DAY(CL$4)+1),$T10<=CL$4),AND($U10>=(CL$4-DAY(CL$4)+1),$U10<=CL$4)),$U10-$T10+1,IF(AND($T10>=(CL$4-DAY(CL$4)+1),$T10<=CL$4),CL$4-$T10+1,IF(AND($U10>=(CL$4-DAY(CL$4)+1),$U10<=CL$4),$U10-(CL$4-DAY(CL$4)+1)+1,IF(OR(AND((CL$4-DAY(CL$4)+1)>=$T10,(CL$4-DAY(CL$4)+1)<=$U10),AND((CL$4>=$T10),(CL$4<=$U10))),CL$4-(CL$4-DAY(CL$4)+1)+1,0))))/IF($R10="mes",_xlfn.DAYS(CL$4,(CL$4-DAY(CL$4)+1))+1,(_xlfn.DAYS($U10,$T10)+1))*$S10)*IF($X$1="Físico",1,$X10) -> 0 | CM10: =(IF(AND(AND($T10>=(CM$4-DAY(CM$4)+1),$T10<=CM$4),AND($U10>=(CM$4-DAY(CM$4)+1),$U10<=CM$4)),$U10-$T10+1,IF(AND($T10>=(CM$4-DAY(CM$4)+1),$T10<=CM$4),CM$4-$T10+1,IF(AND($U10>=(CM$4-DAY(CM$4)+1),$U10<=CM$4),$U10-(CM$4-DAY(CM$4)+1)+1,IF(OR(AND((CM$4-DAY(CM$4)+1)>=$T10,(CM$4-DAY(CM$4)+1)<=$U10),AND((CM$4>=$T10),(CM$4<=$U10))),CM$4-(CM$4-DAY(CM$4)+1)+1,0))))/IF($R10="mes",_xlfn.DAYS(CM$4,(CM$4-DAY(CM$4)+1))+1,(_xlfn.DAYS($U10,$T10)+1))*$S10)*IF($X$1="Físico",1,$X10) -> 0 | CN10: =(IF(AND(AND($T10>=(CN$4-DAY(CN$4)+1),$T10<=CN$4),AND($U10>=(CN$4-DAY(CN$4)+1),$U10<=CN$4)),$U10-$T10+1,IF(AND($T10>=(CN$4-DAY(CN$4)+1),$T10<=CN$4),CN$4-$T10+1,IF(AND($U10>=(CN$4-DAY(CN$4)+1),$U10<=CN$4),$U10-(CN$4-DAY(CN$4)+1)+1,IF(OR(AND((CN$4-DAY(CN$4)+1)>=$T10,(CN$4-DAY(CN$4)+1)<=$U10),AND((CN$4>=$T10),(CN$4<=$U10))),CN$4-(CN$4-DAY(CN$4)+1)+1,0))))/IF($R10="mes",_xlfn.DAYS(CN$4,(CN$4-DAY(CN$4)+1))+1,(_xlfn.DAYS($U10,$T10)+1))*$S10)*IF($X$1="Físico",1,$X10) -> 0 | CO10: =(IF(AND(AND($T10>=(CO$4-DAY(CO$4)+1),$T10<=CO$4),AND($U10>=(CO$4-DAY(CO$4)+1),$U10<=CO$4)),$U10-$T10+1,IF(AND($T10>=(CO$4-DAY(CO$4)+1),$T10<=CO$4),CO$4-$T10+1,IF(AND($U10>=(CO$4-DAY(CO$4)+1),$U10<=CO$4),$U10-(CO$4-DAY(CO$4)+1)+1,IF(OR(AND((CO$4-DAY(CO$4)+1)>=$T10,(CO$4-DAY(CO$4)+1)<=$U10),AND((CO$4>=$T10),(CO$4<=$U10))),CO$4-(CO$4-DAY(CO$4)+1)+1,0))))/IF($R10="mes",_xlfn.DAYS(CO$4,(CO$4-DAY(CO$4)+1))+1,(_xlfn.DAYS($U10,$T10)+1))*$S10)*IF($X$1="Físico",1,$X10) -> 0 | CP10: =(IF(AND(AND($T10>=(CP$4-DAY(CP$4)+1),$T10<=CP$4),AND($U10>=(CP$4-DAY(CP$4)+1),$U10<=CP$4)),$U10-$T10+1,IF(AND($T10>=(CP$4-DAY(CP$4)+1),$T10<=CP$4),CP$4-$T10+1,IF(AND($U10>=(CP$4-DAY(CP$4)+1),$U10<=CP$4),$U10-(CP$4-DAY(CP$4)+1)+1,IF(OR(AND((CP$4-DAY(CP$4)+1)>=$T10,(CP$4-DAY(CP$4)+1)<=$U10),AND((CP$4>=$T10),(CP$4<=$U10))),CP$4-(CP$4-DAY(CP$4)+1)+1,0))))/IF($R10="mes",_xlfn.DAYS(CP$4,(CP$4-DAY(CP$4)+1))+1,(_xlfn.DAYS($U10,$T10)+1))*$S10)*IF($X$1="Físico",1,$X10) -> 0 | CQ10: =(IF(AND(AND($T10>=(CQ$4-DAY(CQ$4)+1),$T10<=CQ$4),AND($U10>=(CQ$4-DAY(CQ$4)+1),$U10<=CQ$4)),$U10-$T10+1,IF(AND($T10>=(CQ$4-DAY(CQ$4)+1),$T10<=CQ$4),CQ$4-$T10+1,IF(AND($U10>=(CQ$4-DAY(CQ$4)+1),$U10<=CQ$4),$U10-(CQ$4-DAY(CQ$4)+1)+1,IF(OR(AND((CQ$4-DAY(CQ$4)+1)>=$T10,(CQ$4-DAY(CQ$4)+1)<=$U10),AND((CQ$4>=$T10),(CQ$4<=$U10))),CQ$4-(CQ$4-DAY(CQ$4)+1)+1,0))))/IF($R10="mes",_xlfn.DAYS(CQ$4,(CQ$4-DAY(CQ$4)+1))+1,(_xlfn.DAYS($U10,$T10)+1))*$S10)*IF($X$1="Físico",1,$X10) -> 0 | CR10: =(IF(AND(AND($T10>=(CR$4-DAY(CR$4)+1),$T10<=CR$4),AND($U10>=(CR$4-DAY(CR$4)+1),$U10<=CR$4)),$U10-$T10+1,IF(AND($T10>=(CR$4-DAY(CR$4)+1),$T10<=CR$4),CR$4-$T10+1,IF(AND($U10>=(CR$4-DAY(CR$4)+1),$U10<=CR$4),$U10-(CR$4-DAY(CR$4)+1)+1,IF(OR(AND((CR$4-DAY(CR$4)+1)>=$T10,(CR$4-DAY(CR$4)+1)<=$U10),AND((CR$4>=$T10),(CR$4<=$U10))),CR$4-(CR$4-DAY(CR$4)+1)+1,0))))/IF($R10="mes",_xlfn.DAYS(CR$4,(CR$4-DAY(CR$4)+1))+1,(_xlfn.DAYS($U10,$T10)+1))*$S10)*IF($X$1="Físico",1,$X10) -> 0 | ... EQ10: =(IF(AND(AND($T10>=(EQ$4-DAY(EQ$4)+1),$T10<=EQ$4),AND($U10>=(EQ$4-DAY(EQ$4)+1),$U10<=EQ$4)),$U10-$T10+1,IF(AND($T10>=(EQ$4-DAY(EQ$4)+1),$T10<=EQ$4),EQ$4-$T10+1,IF(AND($U10>=(EQ$4-DAY(EQ$4)+1),$U10<=EQ$4),$U10-(EQ$4-DAY(EQ$4)+1)+1,IF(OR(AND((EQ$4-DAY(EQ$4)+1)>=$T10,(EQ$4-DAY(EQ$4)+1)<=$U10),AND((EQ$4>=$T10),(EQ$4<=$U10))),EQ$4-(EQ$4-DAY(EQ$4)+1)+1,0))))/IF($R10="mes",_xlfn.DAYS(EQ$4,(EQ$4-DAY(EQ$4)+1))+1,(_xlfn.DAYS($U10,$T10)+1))*$S10)*IF($X$1="Físico",1,$X10) -> 0
D11: =IF(E11=$L$7,$M$1,$N$1) -> #N/A | E11: =VLOOKUP(TEXT(Z11,0),'G2'!B:D,3,0) -> #N/A | F11: =SUM(BS11:CB11) -> 0 | G11: =IF(OR($I11="REAL",$I11="INCURRIDO"),$I11&" "&$Z11&" "&O11&" "&Q11,) -> 0 | H11: MB-2025 | L11: =IFERROR(VLOOKUP(TEXT(Z11,0),'G2'!$B$5:$D$21,3,0),"") | N11:  ASESORIA EXPERTA | W11: #N/A | AA11: =IF(OR($I11="REAL",$I11="INCURRIDO"),SUMIF(S!$O:$O,$I11&$O11&$Q11&UPPER(TEXT(AA$4,"MMMMYYYY"))&$Z11,IF($W$1="Pesos CLP",S!$AD:$AD,S!$AO:$AO)),0) -> 0 | AB11: =IF(OR($I11="REAL",$I11="INCURRIDO"),SUMIF(S!$O:$O,$I11&$O11&$Q11&UPPER(TEXT(AB$4,"MMMMYYYY"))&$Z11,IF($W$1="Pesos CLP",S!$AD:$AD,S!$AO:$AO)),0) -> 0 | AC11: =IF(OR($I11="REAL",$I11="INCURRIDO"),SUMIF(S!$O:$O,$I11&$O11&$Q11&UPPER(TEXT(AC$4,"MMMMYYYY"))&$Z11,IF($W$1="Pesos CLP",S!$AD:$AD,S!$AO:$AO)),0) -> 0 | AD11: =IF(OR($I11="REAL",$I11="INCURRIDO"),SUMIF(S!$O:$O,$I11&$O11&$Q11&UPPER(TEXT(AD$4,"MMMMYYYY"))&$Z11,IF($W$1="Pesos CLP",S!$AD:$AD,S!$AO:$AO)),0) -> 0 | AE11: =IF(OR($I11="REAL",$I11="INCURRIDO"),SUMIF(S!$O:$O,$I11&$O11&$Q11&UPPER(TEXT(AE$4,"MMMMYYYY"))&$Z11,IF($W$1="Pesos CLP",S!$AD:$AD,S!$AO:$AO)),0) -> 0 | AF11: =IF(OR($I11="REAL",$I11="INCURRIDO"),SUMIF(S!$O:$O,$I11&$O11&$Q11&UPPER(TEXT(AF$4,"MMMMYYYY"))&$Z11,IF($W$1="Pesos CLP",S!$AD:$AD,S!$AO:$AO)),0) -> 0 | AG11: =IF(OR($I11="REAL",$I11="INCURRIDO"),SUMIF(S!$O:$O,$I11&$O11&$Q11&UPPER(TEXT(AG$4,"MMMMYYYY"))&$Z11,IF($W$1="Pesos CLP",S!$AD:$AD,S!$AO:$AO)),0) -> 0 | AH11: =IF(OR($I11="REAL",$I11="INCURRIDO"),SUMIF(S!$O:$O,$I11&$O11&$Q11&UPPER(TEXT(AH$4,"MMMMYYYY"))&$Z11,IF($W$1="Pesos CLP",S!$AD:$AD,S!$AO:$AO)),0) -> 0 | ... BQ11: =IF(OR($I11="REAL",$I11="INCURRIDO"),SUMIF(S!$O:$O,$I11&$O11&$Q11&UPPER(TEXT(BQ$4,"MMMMYYYY"))&$Z11,IF($W$1="Pesos CLP",S!$AD:$AD,S!$AO:$AO)),0) -> 0
D12: =IF(E12=$L$7,$M$1,$N$1) -> 1.0658056 | E12: =VLOOKUP(TEXT(Z12,0),'G2'!B:D,3,0) -> ME | F12: =SUM(BS12:CB12) -> -74.911207 | G12: =IF(OR($I12="REAL",$I12="INCURRIDO"),$I12&" "&$Z12&" "&O12&" "&Q12,) -> INCURRIDO 91243120 CO-055/2024 BERG_CAD | H12: MB-2025 | I12: INCURRIDO | J12: FEE SS | K12: 510102 | L12: =IFERROR(VLOOKUP(TEXT(Z12,0),'G2'!$B$5:$D$21,3,0),"") -> ME | N12: Darren Obrian Cad | O12: CO-055/2024 | Q12: BERG_CAD | R12: días | T12: 45523 | U12: 45538 | V12: =(U12-T12)/30 -> 0.5 | W12: 0 | X12: {=+IF($W$1="Pesos CLP",W12,W12/TC)*MB_24A25} -> 0 | Y12: =SUM(BH12:DU12) -> -74.911207 | Z12: 91243120 | AA12: =IF(OR($I12="REAL",$I12="INCURRIDO"),SUMIF(S!$O:$O,$I12&$O12&$Q12&UPPER(TEXT(AA$4,"MMMMYYYY"))&$Z12,IF($W$1="Pesos CLP",S!$AD:$AD,S!$AO:$AO)),0) -> 0 | AB12: =IF(OR($I12="REAL",$I12="INCURRIDO"),SUMIF(S!$O:$O,$I12&$O12&$Q12&UPPER(TEXT(AB$4,"MMMMYYYY"))&$Z12,IF($W$1="Pesos CLP",S!$AD:$AD,S!$AO:$AO)),0) -> 0 | AC12: =IF(OR($I12="REAL",$I12="INCURRIDO"),SUMIF(S!$O:$O,$I12&$O12&$Q12&UPPER(TEXT(AC$4,"MMMMYYYY"))&$Z12,IF($W$1="Pesos CLP",S!$AD:$AD,S!$AO:$AO)),0) -> 0 | AD12: =IF(OR($I12="REAL",$I12="INCURRIDO"),SUMIF(S!$O:$O,$I12&$O12&$Q12&UPPER(TEXT(AD$4,"MMMMYYYY"))&$Z12,IF($W$1="Pesos CLP",S!$AD:$AD,S!$AO:$AO)),0) -> 0 | AE12: =IF(OR($I12="REAL",$I12="INCURRIDO"),SUMIF(S!$O:$O,$I12&$O12&$Q12&UPPER(TEXT(AE$4,"MMMMYYYY"))&$Z12,IF($W$1="Pesos CLP",S!$AD:$AD,S!$AO:$AO)),0) -> 0 | AF12: =IF(OR($I12="REAL",$I12="INCURRIDO"),SUMIF(S!$O:$O,$I12&$O12&$Q12&UPPER(TEXT(AF$4,"MMMMYYYY"))&$Z12,IF($W$1="Pesos CLP",S!$AD:$AD,S!$AO:$AO)),0) -> 0 | AG12: =IF(OR($I12="REAL",$I12="INCURRIDO"),SUMIF(S!$O:$O,$I12&$O12&$Q12&UPPER(TEXT(AG$4,"MMMMYYYY"))&$Z12,IF($W$1="Pesos CLP",S!$AD:$AD,S!$AO:$AO)),0) -> 0 | AH12: =IF(OR($I12="REAL",$I12="INCURRIDO"),SUMIF(S!$O:$O,$I12&$O12&$Q12&UPPER(TEXT(AH$4,"MMMMYYYY"))&$Z12,IF($W$1="Pesos CLP",S!$AD:$AD,S!$AO:$AO)),0) -> 0 | ... CJ12: =IF(OR($I12="REAL",$I12="INCURRIDO"),SUMIF(S!$O:$O,$I12&$O12&$Q12&UPPER(TEXT(CJ$4,"MMMMYYYY"))&$Z12,IF($W$1="Pesos CLP",S!$AD:$AD,S!$AO:$AO)),0) -> 0 | CK12: =(IF(AND(AND($T12>=(CK$4-DAY(CK$4)+1),$T12<=CK$4),AND($U12>=(CK$4-DAY(CK$4)+1),$U12<=CK$4)),$U12-$T12+1,IF(AND($T12>=(CK$4-DAY(CK$4)+1),$T12<=CK$4),CK$4-$T12+1,IF(AND($U12>=(CK$4-DAY(CK$4)+1),$U12<=CK$4),$U12-(CK$4-DAY(CK$4)+1)+1,IF(OR(AND((CK$4-DAY(CK$4)+1)>=$T12,(CK$4-DAY(CK$4)+1)<=$U12),AND((CK$4>=$T12),(CK$4<=$U12))),CK$4-(CK$4-DAY(CK$4)+1)+1,0))))/IF($R12="mes",_xlfn.DAYS(CK$4,(CK$4-DAY(CK$4)+1))+1,(_xlfn.DAYS($U12,$T12)+1))*$S12)*IF($X$1="Físico",1,$X12) -> 0 | CL12: =(IF(AND(AND($T12>=(CL$4-DAY(CL$4)+1),$T12<=CL$4),AND($U12>=(CL$4-DAY(CL$4)+1),$U12<=CL$4)),$U12-$T12+1,IF(AND($T12>=(CL$4-DAY(CL$4)+1),$T12<=CL$4),CL$4-$T12+1,IF(AND($U12>=(CL$4-DAY(CL$4)+1),$U12<=CL$4),$U12-(CL$4-DAY(CL$4)+1)+1,IF(OR(AND((CL$4-DAY(CL$4)+1)>=$T12,(CL$4-DAY(CL$4)+1)<=$U12),AND((CL$4>=$T12),(CL$4<=$U12))),CL$4-(CL$4-DAY(CL$4)+1)+1,0))))/IF($R12="mes",_xlfn.DAYS(CL$4,(CL$4-DAY(CL$4)+1))+1,(_xlfn.DAYS($U12,$T12)+1))*$S12)*IF($X$1="Físico",1,$X12) -> 0 | CM12: =(IF(AND(AND($T12>=(CM$4-DAY(CM$4)+1),$T12<=CM$4),AND($U12>=(CM$4-DAY(CM$4)+1),$U12<=CM$4)),$U12-$T12+1,IF(AND($T12>=(CM$4-DAY(CM$4)+1),$T12<=CM$4),CM$4-$T12+1,IF(AND($U12>=(CM$4-DAY(CM$4)+1),$U12<=CM$4),$U12-(CM$4-DAY(CM$4)+1)+1,IF(OR(AND((CM$4-DAY(CM$4)+1)>=$T12,(CM$4-DAY(CM$4)+1)<=$U12),AND((CM$4>=$T12),(CM$4<=$U12))),CM$4-(CM$4-DAY(CM$4)+1)+1,0))))/IF($R12="mes",_xlfn.DAYS(CM$4,(CM$4-DAY(CM$4)+1))+1,(_xlfn.DAYS($U12,$T12)+1))*$S12)*IF($X$1="Físico",1,$X12) -> 0 | CN12: =(IF(AND(AND($T12>=(CN$4-DAY(CN$4)+1),$T12<=CN$4),AND($U12>=(CN$4-DAY(CN$4)+1),$U12<=CN$4)),$U12-$T12+1,IF(AND($T12>=(CN$4-DAY(CN$4)+1),$T12<=CN$4),CN$4-$T12+1,IF(AND($U12>=(CN$4-DAY(CN$4)+1),$U12<=CN$4),$U12-(CN$4-DAY(CN$4)+1)+1,IF(OR(AND((CN$4-DAY(CN$4)+1)>=$T12,(CN$4-DAY(CN$4)+1)<=$U12),AND((CN$4>=$T12),(CN$4<=$U12))),CN$4-(CN$4-DAY(CN$4)+1)+1,0))))/IF($R12="mes",_xlfn.DAYS(CN$4,(CN$4-DAY(CN$4)+1))+1,(_xlfn.DAYS($U12,$T12)+1))*$S12)*IF($X$1="Físico",1,$X12) -> 0 | CO12: =(IF(AND(AND($T12>=(CO$4-DAY(CO$4)+1),$T12<=CO$4),AND($U12>=(CO$4-DAY(CO$4)+1),$U12<=CO$4)),$U12-$T12+1,IF(AND($T12>=(CO$4-DAY(CO$4)+1),$T12<=CO$4),CO$4-$T12+1,IF(AND($U12>=(CO$4-DAY(CO$4)+1),$U12<=CO$4),$U12-(CO$4-DAY(CO$4)+1)+1,IF(OR(AND((CO$4-DAY(CO$4)+1)>=$T12,(CO$4-DAY(CO$4)+1)<=$U12),AND((CO$4>=$T12),(CO$4<=$U12))),CO$4-(CO$4-DAY(CO$4)+1)+1,0))))/IF($R12="mes",_xlfn.DAYS(CO$4,(CO$4-DAY(CO$4)+1))+1,(_xlfn.DAYS($U12,$T12)+1))*$S12)*IF($X$1="Físico",1,$X12) -> 0 | CP12: =(IF(AND(AND($T12>=(CP$4-DAY(CP$4)+1),$T12<=CP$4),AND($U12>=(CP$4-DAY(CP$4)+1),$U12<=CP$4)),$U12-$T12+1,IF(AND($T12>=(CP$4-DAY(CP$4)+1),$T12<=CP$4),CP$4-$T12+1,IF(AND($U12>=(CP$4-DAY(CP$4)+1),$U12<=CP$4),$U12-(CP$4-DAY(CP$4)+1)+1,IF(OR(AND((CP$4-DAY(CP$4)+1)>=$T12,(CP$4-DAY(CP$4)+1)<=$U12),AND((CP$4>=$T12),(CP$4<=$U12))),CP$4-(CP$4-DAY(CP$4)+1)+1,0))))/IF($R12="mes",_xlfn.DAYS(CP$4,(CP$4-DAY(CP$4)+1))+1,(_xlfn.DAYS($U12,$T12)+1))*$S12)*IF($X$1="Físico",1,$X12) -> 0 | CQ12: =(IF(AND(AND($T12>=(CQ$4-DAY(CQ$4)+1),$T12<=CQ$4),AND($U12>=(CQ$4-DAY(CQ$4)+1),$U12<=CQ$4)),$U12-$T12+1,IF(AND($T12>=(CQ$4-DAY(CQ$4)+1),$T12<=CQ$4),CQ$4-$T12+1,IF(AND($U12>=(CQ$4-DAY(CQ$4)+1),$U12<=CQ$4),$U12-(CQ$4-DAY(CQ$4)+1)+1,IF(OR(AND((CQ$4-DAY(CQ$4)+1)>=$T12,(CQ$4-DAY(CQ$4)+1)<=$U12),AND((CQ$4>=$T12),(CQ$4<=$U12))),CQ$4-(CQ$4-DAY(CQ$4)+1)+1,0))))/IF($R12="mes",_xlfn.DAYS(CQ$4,(CQ$4-DAY(CQ$4)+1))+1,(_xlfn.DAYS($U12,$T12)+1))*$S12)*IF($X$1="Físico",1,$X12) -> 0 | CR12: =(IF(AND(AND($T12>=(CR$4-DAY(CR$4)+1),$T12<=CR$4),AND($U12>=(CR$4-DAY(CR$4)+1),$U12<=CR$4)),$U12-$T12+1,IF(AND($T12>=(CR$4-DAY(CR$4)+1),$T12<=CR$4),CR$4-$T12+1,IF(AND($U12>=(CR$4-DAY(CR$4)+1),$U12<=CR$4),$U12-(CR$4-DAY(CR$4)+1)+1,IF(OR(AND((CR$4-DAY(CR$4)+1)>=$T12,(CR$4-DAY(CR$4)+1)<=$U12),AND((CR$4>=$T12),(CR$4<=$U12))),CR$4-(CR$4-DAY(CR$4)+1)+1,0))))/IF($R12="mes",_xlfn.DAYS(CR$4,(CR$4-DAY(CR$4)+1))+1,(_xlfn.DAYS($U12,$T12)+1))*$S12)*IF($X$1="Físico",1,$X12) -> 0 | ... EQ12: =(IF(AND(AND($T12>=(EQ$4-DAY(EQ$4)+1),$T12<=EQ$4),AND($U12>=(EQ$4-DAY(EQ$4)+1),$U12<=EQ$4)),$U12-$T12+1,IF(AND($T12>=(EQ$4-DAY(EQ$4)+1),$T12<=EQ$4),EQ$4-$T12+1,IF(AND($U12>=(EQ$4-DAY(EQ$4)+1),$U12<=EQ$4),$U12-(EQ$4-DAY(EQ$4)+1)+1,IF(OR(AND((EQ$4-DAY(EQ$4)+1)>=$T12,(EQ$4-DAY(EQ$4)+1)<=$U12),AND((EQ$4>=$T12),(EQ$4<=$U12))),EQ$4-(EQ$4-DAY(EQ$4)+1)+1,0))))/IF($R12="mes",_xlfn.DAYS(EQ$4,(EQ$4-DAY(EQ$4)+1))+1,(_xlfn.DAYS($U12,$T12)+1))*$S12)*IF($X$1="Físico",1,$X12) -> 0
D13: =IF(E13=$L$7,$M$1,$N$1) -> 1.0658056 | E13: =VLOOKUP(TEXT(Z13,0),'G2'!B:D,3,0) -> ME | F13: =SUM(BS13:CB13) -> 25446.716 | G13: =IF(OR($I13="REAL",$I13="INCURRIDO"),$I13&" "&$Z13&" "&O13&" "&Q13,) -> REAL 91243120 CO-055/2024 BERG_CAD | H13: MB-2025 | I13: REAL | J13: FEE SS | K13: 510102 | L13: =IFERROR(VLOOKUP(TEXT(Z13,0),'G2'!$B$5:$D$21,3,0),"") -> ME | N13: Darren Obrian Cad | O13: CO-055/2024 | Q13: BERG_CAD | R13: días | T13: 45523 | U13: 45538 | V13: =(U13-T13)/30 -> 0.5 | W13: 0 | X13: {=+IF($W$1="Pesos CLP",W13,W13/TC)*MB_24A25} -> 0 | Y13: =SUM(BH13:DU13) -> 40829.196 | Z13: 91243120 | AA13: =IF(OR($I13="REAL",$I13="INCURRIDO"),SUMIF(S!$O:$O,$I13&$O13&$Q13&UPPER(TEXT(AA$4,"MMMMYYYY"))&$Z13,IF($W$1="Pesos CLP",S!$AD:$AD,S!$AO:$AO)),0) -> 0 | AB13: =IF(OR($I13="REAL",$I13="INCURRIDO"),SUMIF(S!$O:$O,$I13&$O13&$Q13&UPPER(TEXT(AB$4,"MMMMYYYY"))&$Z13,IF($W$1="Pesos CLP",S!$AD:$AD,S!$AO:$AO)),0) -> 0 | AC13: =IF(OR($I13="REAL",$I13="INCURRIDO"),SUMIF(S!$O:$O,$I13&$O13&$Q13&UPPER(TEXT(AC$4,"MMMMYYYY"))&$Z13,IF($W$1="Pesos CLP",S!$AD:$AD,S!$AO:$AO)),0) -> 0 | AD13: =IF(OR($I13="REAL",$I13="INCURRIDO"),SUMIF(S!$O:$O,$I13&$O13&$Q13&UPPER(TEXT(AD$4,"MMMMYYYY"))&$Z13,IF($W$1="Pesos CLP",S!$AD:$AD,S!$AO:$AO)),0) -> 0 | AE13: =IF(OR($I13="REAL",$I13="INCURRIDO"),SUMIF(S!$O:$O,$I13&$O13&$Q13&UPPER(TEXT(AE$4,"MMMMYYYY"))&$Z13,IF($W$1="Pesos CLP",S!$AD:$AD,S!$AO:$AO)),0) -> 0 | AF13: =IF(OR($I13="REAL",$I13="INCURRIDO"),SUMIF(S!$O:$O,$I13&$O13&$Q13&UPPER(TEXT(AF$4,"MMMMYYYY"))&$Z13,IF($W$1="Pesos CLP",S!$AD:$AD,S!$AO:$AO)),0) -> 0 | AG13: =IF(OR($I13="REAL",$I13="INCURRIDO"),SUMIF(S!$O:$O,$I13&$O13&$Q13&UPPER(TEXT(AG$4,"MMMMYYYY"))&$Z13,IF($W$1="Pesos CLP",S!$AD:$AD,S!$AO:$AO)),0) -> 0 | AH13: =IF(OR($I13="REAL",$I13="INCURRIDO"),SUMIF(S!$O:$O,$I13&$O13&$Q13&UPPER(TEXT(AH$4,"MMMMYYYY"))&$Z13,IF($W$1="Pesos CLP",S!$AD:$AD,S!$AO:$AO)),0) -> 0 | ... CJ13: =IF(OR($I13="REAL",$I13="INCURRIDO"),SUMIF(S!$O:$O,$I13&$O13&$Q13&UPPER(TEXT(CJ$4,"MMMMYYYY"))&$Z13,IF($W$1="Pesos CLP",S!$AD:$AD,S!$AO:$AO)),0) -> -108.40965 | CK13: =(IF(AND(AND($T13>=(CK$4-DAY(CK$4)+1),$T13<=CK$4),AND($U13>=(CK$4-DAY(CK$4)+1),$U13<=CK$4)),$U13-$T13+1,IF(AND($T13>=(CK$4-DAY(CK$4)+1),$T13<=CK$4),CK$4-$T13+1,IF(AND($U13>=(CK$4-DAY(CK$4)+1),$U13<=CK$4),$U13-(CK$4-DAY(CK$4)+1)+1,IF(OR(AND((CK$4-DAY(CK$4)+1)>=$T13,(CK$4-DAY(CK$4)+1)<=$U13),AND((CK$4>=$T13),(CK$4<=$U13))),CK$4-(CK$4-DAY(CK$4)+1)+1,0))))/IF($R13="mes",_xlfn.DAYS(CK$4,(CK$4-DAY(CK$4)+1))+1,(_xlfn.DAYS($U13,$T13)+1))*$S13)*IF($X$1="Físico",1,$X13) -> 0 | CL13: =(IF(AND(AND($T13>=(CL$4-DAY(CL$4)+1),$T13<=CL$4),AND($U13>=(CL$4-DAY(CL$4)+1),$U13<=CL$4)),$U13-$T13+1,IF(AND($T13>=(CL$4-DAY(CL$4)+1),$T13<=CL$4),CL$4-$T13+1,IF(AND($U13>=(CL$4-DAY(CL$4)+1),$U13<=CL$4),$U13-(CL$4-DAY(CL$4)+1)+1,IF(OR(AND((CL$4-DAY(CL$4)+1)>=$T13,(CL$4-DAY(CL$4)+1)<=$U13),AND((CL$4>=$T13),(CL$4<=$U13))),CL$4-(CL$4-DAY(CL$4)+1)+1,0))))/IF($R13="mes",_xlfn.DAYS(CL$4,(CL$4-DAY(CL$4)+1))+1,(_xlfn.DAYS($U13,$T13)+1))*$S13)*IF($X$1="Físico",1,$X13) -> 0 | CM13: =(IF(AND(AND($T13>=(CM$4-DAY(CM$4)+1),$T13<=CM$4),AND($U13>=(CM$4-DAY(CM$4)+1),$U13<=CM$4)),$U13-$T13+1,IF(AND($T13>=(CM$4-DAY(CM$4)+1),$T13<=CM$4),CM$4-$T13+1,IF(AND($U13>=(CM$4-DAY(CM$4)+1),$U13<=CM$4),$U13-(CM$4-DAY(CM$4)+1)+1,IF(OR(AND((CM$4-DAY(CM$4)+1)>=$T13,(CM$4-DAY(CM$4)+1)<=$U13),AND((CM$4>=$T13),(CM$4<=$U13))),CM$4-(CM$4-DAY(CM$4)+1)+1,0))))/IF($R13="mes",_xlfn.DAYS(CM$4,(CM$4-DAY(CM$4)+1))+1,(_xlfn.DAYS($U13,$T13)+1))*$S13)*IF($X$1="Físico",1,$X13) -> 0 | CN13: =(IF(AND(AND($T13>=(CN$4-DAY(CN$4)+1),$T13<=CN$4),AND($U13>=(CN$4-DAY(CN$4)+1),$U13<=CN$4)),$U13-$T13+1,IF(AND($T13>=(CN$4-DAY(CN$4)+1),$T13<=CN$4),CN$4-$T13+1,IF(AND($U13>=(CN$4-DAY(CN$4)+1),$U13<=CN$4),$U13-(CN$4-DAY(CN$4)+1)+1,IF(OR(AND((CN$4-DAY(CN$4)+1)>=$T13,(CN$4-DAY(CN$4)+1)<=$U13),AND((CN$4>=$T13),(CN$4<=$U13))),CN$4-(CN$4-DAY(CN$4)+1)+1,0))))/IF($R13="mes",_xlfn.DAYS(CN$4,(CN$4-DAY(CN$4)+1))+1,(_xlfn.DAYS($U13,$T13)+1))*$S13)*IF($X$1="Físico",1,$X13) -> 0 | CO13: =(IF(AND(AND($T13>=(CO$4-DAY(CO$4)+1),$T13<=CO$4),AND($U13>=(CO$4-DAY(CO$4)+1),$U13<=CO$4)),$U13-$T13+1,IF(AND($T13>=(CO$4-DAY(CO$4)+1),$T13<=CO$4),CO$4-$T13+1,IF(AND($U13>=(CO$4-DAY(CO$4)+1),$U13<=CO$4),$U13-(CO$4-DAY(CO$4)+1)+1,IF(OR(AND((CO$4-DAY(CO$4)+1)>=$T13,(CO$4-DAY(CO$4)+1)<=$U13),AND((CO$4>=$T13),(CO$4<=$U13))),CO$4-(CO$4-DAY(CO$4)+1)+1,0))))/IF($R13="mes",_xlfn.DAYS(CO$4,(CO$4-DAY(CO$4)+1))+1,(_xlfn.DAYS($U13,$T13)+1))*$S13)*IF($X$1="Físico",1,$X13) -> 0 | CP13: =(IF(AND(AND($T13>=(CP$4-DAY(CP$4)+1),$T13<=CP$4),AND($U13>=(CP$4-DAY(CP$4)+1),$U13<=CP$4)),$U13-$T13+1,IF(AND($T13>=(CP$4-DAY(CP$4)+1),$T13<=CP$4),CP$4-$T13+1,IF(AND($U13>=(CP$4-DAY(CP$4)+1),$U13<=CP$4),$U13-(CP$4-DAY(CP$4)+1)+1,IF(OR(AND((CP$4-DAY(CP$4)+1)>=$T13,(CP$4-DAY(CP$4)+1)<=$U13),AND((CP$4>=$T13),(CP$4<=$U13))),CP$4-(CP$4-DAY(CP$4)+1)+1,0))))/IF($R13="mes",_xlfn.DAYS(CP$4,(CP$4-DAY(CP$4)+1))+1,(_xlfn.DAYS($U13,$T13)+1))*$S13)*IF($X$1="Físico",1,$X13) -> 0 | CQ13: =(IF(AND(AND($T13>=(CQ$4-DAY(CQ$4)+1),$T13<=CQ$4),AND($U13>=(CQ$4-DAY(CQ$4)+1),$U13<=CQ$4)),$U13-$T13+1,IF(AND($T13>=(CQ$4-DAY(CQ$4)+1),$T13<=CQ$4),CQ$4-$T13+1,IF(AND($U13>=(CQ$4-DAY(CQ$4)+1),$U13<=CQ$4),$U13-(CQ$4-DAY(CQ$4)+1)+1,IF(OR(AND((CQ$4-DAY(CQ$4)+1)>=$T13,(CQ$4-DAY(CQ$4)+1)<=$U13),AND((CQ$4>=$T13),(CQ$4<=$U13))),CQ$4-(CQ$4-DAY(CQ$4)+1)+1,0))))/IF($R13="mes",_xlfn.DAYS(CQ$4,(CQ$4-DAY(CQ$4)+1))+1,(_xlfn.DAYS($U13,$T13)+1))*$S13)*IF($X$1="Físico",1,$X13) -> 0 | CR13: =(IF(AND(AND($T13>=(CR$4-DAY(CR$4)+1),$T13<=CR$4),AND($U13>=(CR$4-DAY(CR$4)+1),$U13<=CR$4)),$U13-$T13+1,IF(AND($T13>=(CR$4-DAY(CR$4)+1),$T13<=CR$4),CR$4-$T13+1,IF(AND($U13>=(CR$4-DAY(CR$4)+1),$U13<=CR$4),$U13-(CR$4-DAY(CR$4)+1)+1,IF(OR(AND((CR$4-DAY(CR$4)+1)>=$T13,(CR$4-DAY(CR$4)+1)<=$U13),AND((CR$4>=$T13),(CR$4<=$U13))),CR$4-(CR$4-DAY(CR$4)+1)+1,0))))/IF($R13="mes",_xlfn.DAYS(CR$4,(CR$4-DAY(CR$4)+1))+1,(_xlfn.DAYS($U13,$T13)+1))*$S13)*IF($X$1="Físico",1,$X13) -> 0 | ... EQ13: =(IF(AND(AND($T13>=(EQ$4-DAY(EQ$4)+1),$T13<=EQ$4),AND($U13>=(EQ$4-DAY(EQ$4)+1),$U13<=EQ$4)),$U13-$T13+1,IF(AND($T13>=(EQ$4-DAY(EQ$4)+1),$T13<=EQ$4),EQ$4-$T13+1,IF(AND($U13>=(EQ$4-DAY(EQ$4)+1),$U13<=EQ$4),$U13-(EQ$4-DAY(EQ$4)+1)+1,IF(OR(AND((EQ$4-DAY(EQ$4)+1)>=$T13,(EQ$4-DAY(EQ$4)+1)<=$U13),AND((EQ$4>=$T13),(EQ$4<=$U13))),EQ$4-(EQ$4-DAY(EQ$4)+1)+1,0))))/IF($R13="mes",_xlfn.DAYS(EQ$4,(EQ$4-DAY(EQ$4)+1))+1,(_xlfn.DAYS($U13,$T13)+1))*$S13)*IF($X$1="Físico",1,$X13) -> 0
